[{"page":20,"original":"20   ÁRBOLES NATIVOS\n\n\n\n\n                                    Familia: Araliaceae\n                                        Pumamaqui\n\n                             Nombre científico: Oreopanax andreanus Marchal\n                       Otros nombres comunes:        “jorapanga”, “pumamaqui macho”\n\n\n     Hábito: Árbol de hasta 15 m de altura y 30 cm de diámetro a la altura del pecho (DAP). Tron-\n     co cilíndrico recto, ramificación alterna, copa amplia e irregular.\n\n     Hojas: Simples alternas de textura coriácea, helicoidalmente arregladas; lámina general-\n     mente lanceolada o frecuentemente lobulada de dimensiones variables dependiendo de\n     su forma, de 12 a 25 cm de largo por 5 a 19 cm de ancho, margen entero revoluto y palma-\n     tisecto dentado, ápice obtuso y base obtusa; haz verde lustroso, envés pubescente de color\n     pardo amarillento.\n\n     Flores: Reunidas en racimos terminales de 15 a 25 cm de largo, con 15 a 30 cabezuelas glo-\n     bosas. Flores unisexuales de 5 mm de diámetro; cáliz en forma de copa; corola conformada\n     por 5 pétalos libres de forma oblonga; androceo conformado por 5 estambres libres inser-\n     tados en un disco estaminal poco desarrollado; ovario ínfero 4 locular, con 4 estilos en las\n     flores femeninas y un estilo en las flores masculinas, estigma lobado.\n\n     Fruto: Drupa de forma elipsoide, de color café rojizo cuando está madura.\n\n     Distribución y ecología: Especie endémica de los Andes del centro y sur del Ecuador. Se ha\n     registrado en las provincias de Azuay, Cañar, Chimborazo, Loja, Morona Santiago y Zamora\n     Chinchipe, entre 2500 y 3500 m de altitud. Crece comúnmente en sitios con fuertes pen-\n     dientes y en márgenes de quebradas y ríos pequeños, se adapta bien a suelos pedregosos;\n     posee capacidad de rebrote y su regeneración es muy escasa. En los márgenes de los ríos, se\n     la encuentra en la parte occidental alta de los ríos Tomebamba y Yanuncay.\n\n     Usos tradicionales: Su madera es empleada para la elaboración de guitarras y cucharas de\n     palo, sus inflorescencias secas se usan como adornos (Minga, 2000) y sus hojas sirven como\n     forraje para el ganado (De la Torre et al, 2008).\n\n     Propagación: Se recomienda propagar mediante semillas, para el efecto es necesario reco-\n     lectar los frutos directamente del árbol cuando éstos presenten un color púrpura oscuro.\n     Una vez recolectados, sumergirlos en agua durante una semana con el fin de facilitar la\n     extracción de las semillas por estrujamiento (Loján, 1992), con este procedimiento la germi-\n     nación ocurre en un lapso de 30 a 45 días después de la siembra.\n","familia":"Araliaceae\n","nombre":"Pumamaqui","descripcíon":"","otros_nombres_comunes":["jorapanga","pumamaqui macho"],"nombre_cientifica":"Oreopanax andreanus Marchal","habito":" Árbol de hasta 15 m de altura y 30 cm de diámetro a la altura del pecho (DAP). Tron-\n     co cilíndrico recto, ramificación alterna, copa amplia e irregular.","hojas":"Simples alternas de textura coriácea, helicoidalmente arregladas; lámina general-\n     mente lanceolada o frecuentemente lobulada de dimensiones variables dependiendo de\n     su forma, de 12 a 25 cm de largo por 5 a 19 cm de ancho, margen entero revoluto y palma-\n     tisecto dentado, ápice obtuso y base obtusa; haz verde lustroso, envés pubescente de color\n     pardo amarillento.","flores":"Reunidas en racimos terminales de 15 a 25 cm de largo, con 15 a 30 cabezuelas glo-\n     bosas. Flores unisexuales de 5 mm de diámetro; cáliz en forma de copa; corola conformada\n     por 5 pétalos libres de forma oblonga; androceo conformado por 5 estambres libres inser-\n     tados en un disco estaminal poco desarrollado; ovario ínfero 4 locular, con 4 estilos en las\n     flores femeninas y un estilo en las flores masculinas, estigma lobado.","fruta":"Drupa de forma elipsoide, de color café rojizo cuando está madura.","distribucion_y_ecologia":"Especie endémica de los Andes del centro y sur del Ecuador. Se ha\n     registrado en las provincias de Azuay, Cañar, Chimborazo, Loja, Morona Santiago y Zamora\n     Chinchipe, entre 2500 y 3500 m de altitud. Crece comúnmente en sitios con fuertes pen-\n     dientes y en márgenes de quebradas y ríos pequeños, se adapta bien a suelos pedregosos;\n     posee capacidad de rebrote y su regeneración es muy escasa. En los márgenes de los ríos, se\n     la encuentra en la parte occidental alta de los ríos Tomebamba y Yanuncay.","usos_tradicionales":"Su madera es empleada para la elaboración de guitarras y cucharas de\n     palo, sus inflorescencias secas se usan como adornos (Minga, 2000) y sus hojas sirven como\n     forraje para el ganado (De la Torre et al, 2008).","propagacion":"Se recomienda propagar mediante semillas, para el efecto es necesario reco-\n     lectar los frutos directamente del árbol cuando éstos presenten un color púrpura oscuro.\n     Una vez recolectados, sumergirlos en agua durante una semana con el fin de facilitar la\n     extracción de las semillas por estrujamiento (Loján, 1992), con este procedimiento la germi-\n     nación ocurre en un lapso de 30 a 45 días después de la siembra.","images":["/resources/img/arboles-21_0.jpg","/resources/img/arboles-21_1.jpg","/resources/img/arboles-21_2.jpg"],"slug":"pumamaqui"},{"page":22,"original":"22   ÁRBOLES NATIVOS\n\n\n\n\n                                    Familia: Araliaceae\n                                 Pumamaqui hembra\n\n             Nombre científico: Oreopanax avicenniifolius (Kunth) Decne. & Planch\n      Otros nombres comunes: “pumamaqui blanco”\n\n\n     Hábito: Árbol de 8 a 10 m de altura y 10 a 15 cm de DAP, tronco cilíndrico, corteza externa\n     gris blanquecina e interna verde cremosa, ramificación alterna y difusa, copa irregular.\n\n     Hojas: Simples alternas, de consistencia cactácea, largamente pecioladas; lámina de elíptica\n     a lanceolada o frecuentemente lobulada de dimensiones variables dependiendo de su for-\n     ma, comúnmente de 10 a 14 cm de largo por 3,5 a 6,5 cm de ancho, margen entero, ápice\n     obtuso o acuminado, haz verde oscuro farinoso, envés verde blanquecino, nervadura reti-\n     culada basal, con 7 nervios prominentes en el envés.\n\n     Flores: Reunidas en cabezuelas formando panículas terminales de 6 a 10 cm de largo; ca-\n     bezuelas globosas de 7 cm de diámetro. Flores pequeñas de 3,5 mm de diámetro; cáliz con\n     forma de copa con 5 dientes diminutos; corola compuesta por 5 o 6 pétalos oblongos de\n     color amarillo verdoso; androceo conformado por 6 o 5 estambres, insertos en un disco\n     estaminal; ovario ínfero 5 locular, 5 estilos ligeramente unidos en la base.\n\n     Fruto: Drupa elipsoide de color verde amarillento cuando está madura; cáliz y estambres\n     persistentes.\n\n     Distribución y ecología: Especie endémica de los Andes del centro y sur del Ecuador, loca-\n     lizada en las provincias de: Cotopaxi, Bolívar, Chimborazo, Cañar, Azuay, Loja y Morona San-\n     tiago entre 2500 y 3500 m de altitud. Crece particularmente en laderas y suelos escarpados\n     y hacia los bordes de quebradas; presenta capacidad de rebrote y su regeneración natural\n     es relativamente buena. En los márgenes de los ríos de Cuenca es una especie relativamente\n     común, encontrándose individuos de esta especie incluso dentro del casco urbano de la\n     ciudad.\n\n     Usos tradicionales: Su madera es buena para la elaboración de artesanías como cucharas,\n     bateas, trompos y timones; sus hojas sirven para baños calientes que se aplican a mujeres\n     campesinas luego del parto.\n","familia":"Araliaceae\n","nombre":"Pumamaqui hembra","descripcíon":"","otros_nombres_comunes":["pumamaqui blanco"],"nombre_cientifica":"Oreopanax avicenniifolius (Kunth) Decne. & Planch","habito":" Árbol de 8 a 10 m de altura y 10 a 15 cm de DAP, tronco cilíndrico, corteza externa\n     gris blanquecina e interna verde cremosa, ramificación alterna y difusa, copa irregular.","hojas":"Simples alternas, de consistencia cactácea, largamente pecioladas; lámina de elíptica\n     a lanceolada o frecuentemente lobulada de dimensiones variables dependiendo de su for-\n     ma, comúnmente de 10 a 14 cm de largo por 3,5 a 6,5 cm de ancho, margen entero, ápice\n     obtuso o acuminado, haz verde oscuro farinoso, envés verde blanquecino, nervadura reti-\n     culada basal, con 7 nervios prominentes en el envés.","flores":"Reunidas en cabezuelas formando panículas terminales de 6 a 10 cm de largo; ca-\n     bezuelas globosas de 7 cm de diámetro. Flores pequeñas de 3,5 mm de diámetro; cáliz con\n     forma de copa con 5 dientes diminutos; corola compuesta por 5 o 6 pétalos oblongos de\n     color amarillo verdoso; androceo conformado por 6 o 5 estambres, insertos en un disco\n     estaminal; ovario ínfero 5 locular, 5 estilos ligeramente unidos en la base.","fruta":"Drupa elipsoide de color verde amarillento cuando está madura; cáliz y estambres\n     persistentes.","distribucion_y_ecologia":"Especie endémica de los Andes del centro y sur del Ecuador, loca-\n     lizada en las provincias de: Cotopaxi, Bolívar, Chimborazo, Cañar, Azuay, Loja y Morona San-\n     tiago entre 2500 y 3500 m de altitud. Crece particularmente en laderas y suelos escarpados\n     y hacia los bordes de quebradas; presenta capacidad de rebrote y su regeneración natural\n     es relativamente buena. En los márgenes de los ríos de Cuenca es una especie relativamente\n     común, encontrándose individuos de esta especie incluso dentro del casco urbano de la\n     ciudad.","usos_tradicionales":"Su madera es buena para la elaboración de artesanías como cucharas,\n     bateas, trompos y timones; sus hojas sirven para baños calientes que se aplican a mujeres\n     campesinas luego del parto.","propagacion":"","images":["/resources/img/arboles-23_0.jpg","/resources/img/arboles-23_1.jpg","/resources/img/arboles-23_2.jpg"],"slug":"pumamaqui-hembra"},{"page":24,"original":"24   ÁRBOLES NATIVOS\n\n\n\n\n                                   Familia: Betulaceae\n                                              Aliso\n\n                             Nombre científico: Alnus acuminata Kunth\n                       Otros nombres comunes: “rambrán”, “ranrán”\n\n\n     Hábito: Árbol de hasta 15 m de altura y 30 cm de DAP; copa abierta, tronco cilíndrico recto\n     con ramificación opuesta, corteza con lenticelas dispersas.\n\n     Hojas: Hojas simples alternas, dispuestas alrededor de las ramitas, lámina de forma elíptica\n     a ovada y margen irregularmente aserrado.\n\n     Flores: Unisexuales, flores masculinas dispuestas en amentos péndulos de 10 a 20 cm de\n     largo, flores femeninas en amentos leñosos.\n\n     Fruto: En forma de conos leñosos que contienen pequeñas semillas de color marrón.\n\n     Distribución y ecología: Especie nativa de amplia distribución en América Central y Amé-\n     rica del Sur. En el Ecuador crece en la región andina entre 2000 y 3500 m de altitud. Se\n     adapta a una gran variedad de suelos, pero prefiere los suelos arenosos y bien drenados.\n     En el bosque de ribera de los ríos Yanuncay y Tomebamba, es quizá la especie arbórea más\n     abundante.\n\n     Usos tradicionales: Se reconocen dos tipos de aliso: Aliso blanco que muestra un fuste rec-\n     to; y aliso rojo, de fuste algo tortuoso y generalmente de menor tamaño. La madera de am-\n     bos es suave y antiguamente se empleaba para la elaboración de artesanías como cucharas\n     de palo, puertas y ventanas. Por su capacidad de fijar nitrógeno es utilizado en programas\n     silvopastoriles.\n\n     Propagación: Para propagar por semillas estas deben recolectarse cuando los conos pre-\n     sentan un color marrón claro. Las semillas no deben almacenarse más de 15 días porque\n     pierden su viabilidad. Para el almácigo se recomienda un sustrato de tierra negra con arena,\n     las semillas deben enterrarse a no más de 1 cm de profundidad y el almácigo debe prote-\n     gerse con una cubierta de paja para que durante el riego no las descubra y las plantitas\n     recién germinadas estén protegidas. La germinación inicia después de 10 a 12 días luego de\n     la siembra. El repique se lo realiza alrededor de cuatro a cinco meses, cuando las plántulas\n     hayan alcanzado los 5 cm. La siembra final debe realizarse cuando las plántulas alcancen\n     por lo menos 20 cm.\n\n     Para la propagación vegetativa se recomienda hacerla mediante estacas semimaduras de 2\n     cm de diámetro y que contengan al menos dos yemas. También se pueden obtener plantas\n     de regeneración natural ubicando árboles semilleros en sitios abiertos.\n","familia":"Betulaceae\n","nombre":"Aliso","descripcíon":"","otros_nombres_comunes":["rambrán","ranrán"],"nombre_cientifica":"Alnus acuminata Kunth","habito":" Árbol de hasta 15 m de altura y 30 cm de DAP; copa abierta, tronco cilíndrico recto\n     con ramificación opuesta, corteza con lenticelas dispersas.","hojas":"Hojas simples alternas, dispuestas alrededor de las ramitas, lámina de forma elíptica\n     a ovada y margen irregularmente aserrado.","flores":"Unisexuales, flores masculinas dispuestas en amentos péndulos de 10 a 20 cm de\n     largo, flores femeninas en amentos leñosos.","fruta":"En forma de conos leñosos que contienen pequeñas semillas de color marrón.","distribucion_y_ecologia":"Especie nativa de amplia distribución en América Central y Amé-\n     rica del Sur. En el Ecuador crece en la región andina entre 2000 y 3500 m de altitud. Se\n     adapta a una gran variedad de suelos, pero prefiere los suelos arenosos y bien drenados.\n     En el bosque de ribera de los ríos Yanuncay y Tomebamba, es quizá la especie arbórea más\n     abundante.","usos_tradicionales":"Se reconocen dos tipos de aliso: Aliso blanco que muestra un fuste rec-\n     to; y aliso rojo, de fuste algo tortuoso y generalmente de menor tamaño. La madera de am-\n     bos es suave y antiguamente se empleaba para la elaboración de artesanías como cucharas\n     de palo, puertas y ventanas. Por su capacidad de fijar nitrógeno es utilizado en programas\n     silvopastoriles.","propagacion":"Para propagar por semillas estas deben recolectarse cuando los conos pre-\n     sentan un color marrón claro. Las semillas no deben almacenarse más de 15 días porque\n     pierden su viabilidad. Para el almácigo se recomienda un sustrato de tierra negra con arena,\n     las semillas deben enterrarse a no más de 1 cm de profundidad y el almácigo debe prote-\n     gerse con una cubierta de paja para que durante el riego no las descubra y las plantitas\n     recién germinadas estén protegidas. La germinación inicia después de 10 a 12 días luego de\n     la siembra. El repique se lo realiza alrededor de cuatro a cinco meses, cuando las plántulas\n     hayan alcanzado los 5 cm. La siembra final debe realizarse cuando las plántulas alcancen\n     por lo menos 20 cm.\n\n     Para la propagación vegetativa se recomienda hacerla mediante estacas semimaduras de 2\n     cm de diámetro y que contengan al menos dos yemas. También se pueden obtener plantas\n     de regeneración natural ubicando árboles semilleros en sitios abiertos.","images":["/resources/img/arboles-25_0.jpg","/resources/img/arboles-25_1.jpg","/resources/img/arboles-25_2.jpg","/resources/img/arboles-26_0.jpg","/resources/img/arboles-27_0.jpg"],"slug":"aliso"},{"page":28,"original":"28   ÁRBOLES NATIVOS\n\n\n\n\n                                  Familia: Bignoniaceae\n                                             Guaylo\n\n                             Nombre científico: Delostoma integrifolium D. Don\n                       Otros nombres comunes: “yalomán”, “cholán morado”\n\n\n     Hábito: Arbusto o árbol de hasta 15 m de alto. Tronco tortuoso, ramificación opuesta, copa\n     de ancha a globosa.\n\n     Hojas: Simples, opuestas de forma elíptica u oblongo-elíptica de 12 a 20 cm de largo por 3\n     a 6 cm de ancho, margen mayormente entero y ápice obtuso.\n\n     Flores: Agrupadas en racimos terminales con 2 a 4 flores; flores bisexuales; cáliz de forma de\n     campana de 1 a 1,5 cm de largo; corola tubular campanulada de 5 a 7 cm de largo por 2 a 3\n     cm de diámetro, de color magenta, rosado o blanco; androceo conformado por 4 estambres\n     didínamos insertados en la base de la corola, ovario súpero con 2 lóculos, estilo de 4 mm de\n     largo, estigma con 2 labios.\n\n     Fruto: Cápsula loculicida de forma oblongo- elíptica que contiene numerosas semillas con\n     alas membranosas.\n\n     Distribución y ecología: Especie nativa de amplia distribución en la región andina; ha sido\n     localizada desde Venezuela hasta Perú. En nuestro país crece preferentemente en la región\n     interandina desde 1000 hasta 3500 m de altitud. En las riberas de los ríos de Cuenca, en for-\n     ma silvestre es más bien una especie rara registrándose solo un individuo en el río Yanuncay\n     sector de Barabón Chico. No obstante dentro de la zona urbana se encuentra ampliamente\n     cultivada en parques y jardines. Se adapta a una gran variedad de suelos, pero alcanza su\n     óptimo desarrollo en suelos bien drenados de textura limo arenosa. Sus flores son visitadas\n     por colibríes e insectos.\n\n     Usos tradicionales: Su madera es muy apreciada para la elaboración de artesanías, como\n     cucharas de palo; también es muy apreciada como planta ornamental por sus vistosas flores.\n\n     Propagación: Mediante semillas que pueden recolectarse durante los meses de noviembre\n     y diciembre\n","familia":"Bignoniaceae\n","nombre":"Guaylo","descripcíon":"","otros_nombres_comunes":["yalomán","cholán morado"],"nombre_cientifica":"Delostoma integrifolium D. Don","habito":" Arbusto o árbol de hasta 15 m de alto. Tronco tortuoso, ramificación opuesta, copa\n     de ancha a globosa.","hojas":"Simples, opuestas de forma elíptica u oblongo-elíptica de 12 a 20 cm de largo por 3\n     a 6 cm de ancho, margen mayormente entero y ápice obtuso.","flores":"Agrupadas en racimos terminales con 2 a 4 flores; flores bisexuales; cáliz de forma de\n     campana de 1 a 1,5 cm de largo; corola tubular campanulada de 5 a 7 cm de largo por 2 a 3\n     cm de diámetro, de color magenta, rosado o blanco; androceo conformado por 4 estambres\n     didínamos insertados en la base de la corola, ovario súpero con 2 lóculos, estilo de 4 mm de\n     largo, estigma con 2 labios.","fruta":"Cápsula loculicida de forma oblongo- elíptica que contiene numerosas semillas con\n     alas membranosas.","distribucion_y_ecologia":"Especie nativa de amplia distribución en la región andina; ha sido\n     localizada desde Venezuela hasta Perú. En nuestro país crece preferentemente en la región\n     interandina desde 1000 hasta 3500 m de altitud. En las riberas de los ríos de Cuenca, en for-\n     ma silvestre es más bien una especie rara registrándose solo un individuo en el río Yanuncay\n     sector de Barabón Chico. No obstante dentro de la zona urbana se encuentra ampliamente\n     cultivada en parques y jardines. Se adapta a una gran variedad de suelos, pero alcanza su\n     óptimo desarrollo en suelos bien drenados de textura limo arenosa. Sus flores son visitadas\n     por colibríes e insectos.","usos_tradicionales":"Su madera es muy apreciada para la elaboración de artesanías, como\n     cucharas de palo; también es muy apreciada como planta ornamental por sus vistosas flores.","propagacion":"Mediante semillas que pueden recolectarse durante los meses de noviembre\n     y diciembre","images":["/resources/img/arboles-29_0.jpg","/resources/img/arboles-29_1.jpg","/resources/img/arboles-29_2.jpg"],"slug":"guaylo"},{"page":30,"original":"30   ÁRBOLES NATIVOS\n\n\n\n\n                                   Familia: Celastraceae\n                                              Disñán\n\n                             Nombre científico: Maytenus verticillata (Ruiz & Pav.) DC.\n                       Otros nombres comunes: “laurel”, “sara”, “zherga”\n\n\n     Hábito: Arbolito de 3 a 7 m de altura, copa irregular, ramificación alterna. Tronco cilíndrico,\n     corteza externa de color café marrón o grisáceo.\n\n     Hojas: Simples, alternas, de consistencia coriácea, margen aserrado glandular y ápice agu-\n     do; lámina elíptica de 3 a 5 cm de largo por 1,5 a 3 cm de ancho; haz glabro verde oscuro\n     lustroso, envés opaco con nerviación secundaria inconspicua.\n\n     Flores: Dispuestas en pequeñas cimas axilares de 1 a 2 cm de largo. Flores bisexuales, regu-\n     lares de 0,3 a 0,6 cm de diámetro. Cáliz conformado por 5 sépalos unidos en la base. Corola\n     de color rojizo claro o verde cremoso, compuesta por 5 pétalos libres; androceo provisto\n     de un disco estaminal y compuesto por 5 estambres cortos. Ovario súpero embebido en el\n     disco, estilo corto y estigma trilobado y translúcido.\n\n     Fruto: Cápsula loculicida 3 valvada, de 0,5 a 1 cm de diámetro, que contiene 3 semillas pro-\n     vistas de arilo.\n\n     Distribución y ecología: Especie nativa de los Andes del Ecuador y Perú. Crece en bosques\n     montanos entre 1000 y 3500 m de altitud (Pennington et al, 2004). En nuestro país se en-\n     cuentra en las provincias de Azuay, Bolívar, Cañar, Carchi, Chimborazo, Imbabura y Loja,\n     entre 2000 y 3500 m de altitud. Se establece preferentemente en sitios planos con suelos\n     profundos; no presenta capacidad de rebrote y su regeneración natural es buena. Es una\n     especie común en los márgenes de los ríos de Cuenca, en algunos sitios es abundante.\n\n     Usos tradicionales: En algunas comunidades campesinas de la provincia del Azuay se em-\n     plea para la elaboración de postes y estacas debido a la dureza de su madera. En la comu-\n     nidad de Saraguro se conoce como Sara y su madera sirve para la construcción (Elleman,\n     1990).\n\n     Propagación: Se propaga mediante semillas, las cuales deben ser recolectadas de la planta\n     madre, cuando los frutos estén maduros y empiecen a abrirse; luego se las debe secar y\n     retirar el arilo antes de ponerlas en el semillero, con este procedimiento se obtiene un por-\n     centaje de germinación de alrededor del 10 %.\n","familia":"Celastraceae\n","nombre":"Disñán","descripcíon":"","otros_nombres_comunes":["laurel","sara","zherga"],"nombre_cientifica":"Maytenus verticillata (Ruiz & Pav.) DC.","habito":" Arbolito de 3 a 7 m de altura, copa irregular, ramificación alterna. Tronco cilíndrico,\n     corteza externa de color café marrón o grisáceo.","hojas":"Simples, alternas, de consistencia coriácea, margen aserrado glandular y ápice agu-\n     do; lámina elíptica de 3 a 5 cm de largo por 1,5 a 3 cm de ancho; haz glabro verde oscuro\n     lustroso, envés opaco con nerviación secundaria inconspicua.","flores":"Dispuestas en pequeñas cimas axilares de 1 a 2 cm de largo. Flores bisexuales, regu-\n     lares de 0,3 a 0,6 cm de diámetro. Cáliz conformado por 5 sépalos unidos en la base. Corola\n     de color rojizo claro o verde cremoso, compuesta por 5 pétalos libres; androceo provisto\n     de un disco estaminal y compuesto por 5 estambres cortos. Ovario súpero embebido en el\n     disco, estilo corto y estigma trilobado y translúcido.","fruta":"Cápsula loculicida 3 valvada, de 0,5 a 1 cm de diámetro, que contiene 3 semillas pro-\n     vistas de arilo.","distribucion_y_ecologia":"Especie nativa de los Andes del Ecuador y Perú. Crece en bosques\n     montanos entre 1000 y 3500 m de altitud (Pennington et al, 2004). En nuestro país se en-\n     cuentra en las provincias de Azuay, Bolívar, Cañar, Carchi, Chimborazo, Imbabura y Loja,\n     entre 2000 y 3500 m de altitud. Se establece preferentemente en sitios planos con suelos\n     profundos; no presenta capacidad de rebrote y su regeneración natural es buena. Es una\n     especie común en los márgenes de los ríos de Cuenca, en algunos sitios es abundante.","usos_tradicionales":"En algunas comunidades campesinas de la provincia del Azuay se em-\n     plea para la elaboración de postes y estacas debido a la dureza de su madera. En la comu-\n     nidad de Saraguro se conoce como Sara y su madera sirve para la construcción (Elleman,\n     1990).","propagacion":"Se propaga mediante semillas, las cuales deben ser recolectadas de la planta\n     madre, cuando los frutos estén maduros y empiecen a abrirse; luego se las debe secar y\n     retirar el arilo antes de ponerlas en el semillero, con este procedimiento se obtiene un por-\n     centaje de germinación de alrededor del 10 %.","images":["/resources/img/arboles-31_0.jpg","/resources/img/arboles-31_1.jpg","/resources/img/arboles-31_2.jpg"],"slug":"disn"},{"page":32,"original":"32   ÁRBOLES NATIVOS\n\n\n\n\n                                    Familia: Clethraceae\n                                             Tulapo\n\n                             Nombre científico: Clethra fimbriata Kunth\n                       Otros nombres comunes: “león”\n\n\n     Hábito: Árbol de 10 a 12 m de altura. Tronco recto, copa estrecha, ramificación alterna, rami-\n     tas terminales de color café rojizo.\n\n     Hojas: Simples alternas; lámina de ovada a ligeramente elíptica, margen entero, ápice obtu-\n     so. Haz verde oscuro cubierto con tricomas de color café rojizo, envés opaco con pubescen-\n     cia tomentosa ferruginosa.\n\n     Flores: Bisexuales fragantes, agrupadas en racimos terminales de 5 a 10 cm de largo, poseen\n     dos brácteas de 4 mm. Cáliz con 5 sépalos de forma elíptica. Corola con 5 pétalos blancos\n     obovados u orbiculares con el margen ciliado. Androceo conformado por 10 estambres dis-\n     puestos en 2 verticilos, anteras dehiscentes por medio de poros. Ovario súpero con 3 car-\n     pelos y 3 lóculos.\n\n     Fruto: Cápsula loculicida de 4 mm de diámetro, con el cáliz persistente.\n\n     Distribución y ecología: Especie nativa de amplia distribución en los Andes ecuatorianos,\n     crece entre 2200 y 3400 m de altitud. Es frecuente en los bosques andinos del sur del país.\n     En los márgenes de los ríos de Cuenca se ha observado en el río Yanuncay en los sectores de\n     Sustag y Soldados. Esta especie, se adapta a una gran variedad de suelos, pero en suelos\n     pobres adquiere forma arbustiva; no tiene capacidad de rebrote y su regeneración natural\n     es pobre. Debido a la fragancia de sus flores, éstas son visitadas por gran cantidad de insec-\n     tos que ayudan a su polinización.\n\n     Usos tradicionales: Antiguamente su madera era empleada en la construcción de viviendas\n     campesinas para pilares, vigas y umbrales; en la actualidad su usa únicamente para leña.\n","familia":"Clethraceae\n","nombre":"Tulapo","descripcíon":"","otros_nombres_comunes":["león"],"nombre_cientifica":"Clethra fimbriata Kunth","habito":" Árbol de 10 a 12 m de altura. Tronco recto, copa estrecha, ramificación alterna, rami-\n     tas terminales de color café rojizo.","hojas":"Simples alternas; lámina de ovada a ligeramente elíptica, margen entero, ápice obtu-\n     so. Haz verde oscuro cubierto con tricomas de color café rojizo, envés opaco con pubescen-\n     cia tomentosa ferruginosa.","flores":"Bisexuales fragantes, agrupadas en racimos terminales de 5 a 10 cm de largo, poseen\n     dos brácteas de 4 mm. Cáliz con 5 sépalos de forma elíptica. Corola con 5 pétalos blancos\n     obovados u orbiculares con el margen ciliado. Androceo conformado por 10 estambres dis-\n     puestos en 2 verticilos, anteras dehiscentes por medio de poros. Ovario súpero con 3 car-\n     pelos y 3 lóculos.","fruta":"Cápsula loculicida de 4 mm de diámetro, con el cáliz persistente.","distribucion_y_ecologia":"Especie nativa de amplia distribución en los Andes ecuatorianos,\n     crece entre 2200 y 3400 m de altitud. Es frecuente en los bosques andinos del sur del país.\n     En los márgenes de los ríos de Cuenca se ha observado en el río Yanuncay en los sectores de\n     Sustag y Soldados. Esta especie, se adapta a una gran variedad de suelos, pero en suelos\n     pobres adquiere forma arbustiva; no tiene capacidad de rebrote y su regeneración natural\n     es pobre. Debido a la fragancia de sus flores, éstas son visitadas por gran cantidad de insec-\n     tos que ayudan a su polinización.","usos_tradicionales":"Antiguamente su madera era empleada en la construcción de viviendas\n     campesinas para pilares, vigas y umbrales; en la actualidad su usa únicamente para leña.","propagacion":"","images":["/resources/img/arboles-33_0.jpg","/resources/img/arboles-33_1.jpg","/resources/img/arboles-33_2.jpg","/resources/img/arboles-34_0.jpg","/resources/img/arboles-35_0.jpg"],"slug":"tulapo"},{"page":36,"original":"36   ÁRBOLES NATIVOS\n\n\n\n\n                                     Familia: Cornaceae\n                                         Palo de rosa\n\n                             Nombre científico: Cornus peruviana J.F. Macbr.\n                       Otros nombres comunes: “mentol”\n\n\n     Hábito: Árbol de 8 a 12 m de altura y 20 a 30 cm de DAP. Tronco cilíndrico recto, corteza\n     externa rugosa, lenticelada, de color café oscuro, con fuerte olor a mentol cuando se corta;\n     ramificación opuesta y copa amplia irregular.\n\n     Hojas: Simples, opuestas, sostenidos por peciolos de 0,5 a 1 cm de largo, lámina elíptica-\n     ovada de 2,5 a 5,5 cm de ancho por 8 a 14 cm de largo, ápice acuminado margen entero y\n     base cuneada, haz de color verde opaco glabro, envés verde claro, venación prominente\n     con 5 pares de nervios secundarios.\n\n     Flores: Bisexuales actinomorfas, reunidas en corimbos de 4 a 7 cm de largo; cáliz tubular\n     truncado de 0,4 mm de largo; corola con 4 pétalos valvados de color blanco; androceo cons-\n     tituido por 4 pétalos alternos a los pétalos, anteras dorsifijas; ovario conformado por 2 car-\n     pelos, 2 locular, estilo columnar y estigmas capitados.\n\n     Fruto: Drupa oblonga de 0,5 cm de largo, verde cuando está tierna y púrpura al madurar.\n\n     Distribución y ecología: Especie de amplia distribución, se ha registrado en los Andes de\n     Venezuela, Colombia, Ecuador, Perú y Bolivia. En nuestro país crece en bosques y matorra-\n     les húmedos andinos entre 2000 y 3500 m de altitud. Prefiere ambientes húmedos y suelos\n     profundos; es componente importante de la vegetación de ribera de los ríos y quebradas y\n     en los márgenes de los ríos Tomebamba y Yanuncay.\n\n     Usos tradicionales: En la región se emplea únicamente como leña, mientras que en la pro-\n     vincia de Imbabura su madera se emplea para la construcción como encofrados (Cuamacás\n     y Tipaz, 1995).\n","familia":"Cornaceae\n","nombre":"Palo de rosa","descripcíon":"","otros_nombres_comunes":["mentol"],"nombre_cientifica":"Cornus peruviana J.F. Macbr.","habito":" Árbol de 8 a 12 m de altura y 20 a 30 cm de DAP. Tronco cilíndrico recto, corteza\n     externa rugosa, lenticelada, de color café oscuro, con fuerte olor a mentol cuando se corta;\n     ramificación opuesta y copa amplia irregular.","hojas":"Simples, opuestas, sostenidos por peciolos de 0,5 a 1 cm de largo, lámina elíptica-\n     ovada de 2,5 a 5,5 cm de ancho por 8 a 14 cm de largo, ápice acuminado margen entero y\n     base cuneada, haz de color verde opaco glabro, envés verde claro, venación prominente\n     con 5 pares de nervios secundarios.","flores":"Bisexuales actinomorfas, reunidas en corimbos de 4 a 7 cm de largo; cáliz tubular\n     truncado de 0,4 mm de largo; corola con 4 pétalos valvados de color blanco; androceo cons-\n     tituido por 4 pétalos alternos a los pétalos, anteras dorsifijas; ovario conformado por 2 car-\n     pelos, 2 locular, estilo columnar y estigmas capitados.","fruta":"Drupa oblonga de 0,5 cm de largo, verde cuando está tierna y púrpura al madurar.","distribucion_y_ecologia":"Especie de amplia distribución, se ha registrado en los Andes de\n     Venezuela, Colombia, Ecuador, Perú y Bolivia. En nuestro país crece en bosques y matorra-\n     les húmedos andinos entre 2000 y 3500 m de altitud. Prefiere ambientes húmedos y suelos\n     profundos; es componente importante de la vegetación de ribera de los ríos y quebradas y\n     en los márgenes de los ríos Tomebamba y Yanuncay.","usos_tradicionales":"En la región se emplea únicamente como leña, mientras que en la pro-\n     vincia de Imbabura su madera se emplea para la construcción como encofrados (Cuamacás\n     y Tipaz, 1995).","propagacion":"","images":["/resources/img/arboles-37_0.jpg","/resources/img/arboles-37_1.jpg","/resources/img/arboles-37_2.jpg"],"slug":"palo-de-rosa"},{"page":38,"original":"38   ÁRBOLES NATIVOS\n\n\n\n\n                                   Familia: Cunoniaceae\n                                               Sarar\n\n                            Nombre científico: Weinmannia fagaroides Kunth\n                    Otros nombres comunes: “cashco”, “guishmo”, “encino” (Loján 1992),\n                                           “matache”, “sara fino”\n\n\n     Hábito: Árbol de 10 a 15 m de altura y 30 cm de DAP. Fuste recto, ramificación alterna, copa\n     irregular, ramitas teretes leñosas de color negro.\n\n     Hojas: Compuestas, imparipinnadas de 2 a 5 cm de longitud con 9 a 16 foliolos, raquis alado,\n     con una hilera de pelos en los nudos, estípulas ovadas o suborbiculares; foliolos de forma\n     ovada de 0,5 a 0,9 cm de largo por 0,3 a 4,5 cm de ancho con el margen irregularmente cre-\n     nado, ápice redondeado y base cuneada, haz verde lustroso de color gris, envés verde claro.\n\n     Flores: Dispuestas en racimos terminales simples fasciculados de 2 a 6 cm de largo, raquis\n     esparcidamente hirsuto rojizo; fascículos compuestos por 2 a 5 flores pequeñas. Flores pe-\n     queñas bisexuales, pedicelos de 3 mm de largo; cáliz con 4 sépalos libres ampliamente ova-\n     dos de 1,3 mm de largo x 1 mm de ancho; corola con 4 pétalos blancos ovados de 2 a 2,5\n     mm de largo; androceo compuesto por 10 estambres dispuestos en dos verticilos, ovario\n     súpero, 4 locular.\n\n     Fruto: Cápsula oblongo-ovoide de 3 a 4 mm de largo, con los estilos persistentes, de color\n     café marrón cuando está madura.\n\n     Distribución y ecología: Se distribuye en Costa Rica, Colombia y de Venezuela hasta Bolivia\n     en bosques húmedos, secos y subpáramos entre 2000 y 3600 m de altitud (Harling, 1999).\n     En nuestro país es una especie muy abundante en los bosques altoandinos del sur del país,\n     crece entre 2700 y 3600 m de altitud; es una especie dominante en los bosques nativos de\n     la cuenca del río Paute, sin embargo en los bosques de ribera de los ríos de Cuenca, es más\n     bien una especie rara. Posee una excelente capacidad de rebrote y su regeneración natural\n     es buena.\n\n     Usos tradicionales: Madera para construcción de casas pequeñas (vigas, pilares); para ela-\n     borar timones de arado y yugos y para leña. Medicinalmente se usa para limpias y baños de\n     dieta. Sus hojas sirven como forraje para el ganado.\n\n     Propagación: Se recomienda propagarla mediante semillas, para lo cual, se deben recolec-\n     tar las cápsulas antes de que se abran y, secarlas al sol durante 2 días para separar las semi-\n     llas, luego deben sembrarse en almácigos con tierra de vivero, se recomienda sembrarlas al\n     voleo y cubrirlas con una capa fina de arena. El semillero debe taparse con paja, para evitar\n     lavar las semillas durante el riego. La germinación ocurre en un lapso de 60 a 70 días.\n","familia":"Cunoniaceae\n","nombre":"Sarar","descripcíon":"","otros_nombres_comunes":["cashco","guishmo","encino (Loján 1992)","matache","sara fino"],"nombre_cientifica":"Weinmannia fagaroides Kunth","habito":" Árbol de 10 a 15 m de altura y 30 cm de DAP. Fuste recto, ramificación alterna, copa\n     irregular, ramitas teretes leñosas de color negro.","hojas":"Compuestas, imparipinnadas de 2 a 5 cm de longitud con 9 a 16 foliolos, raquis alado,\n     con una hilera de pelos en los nudos, estípulas ovadas o suborbiculares; foliolos de forma\n     ovada de 0,5 a 0,9 cm de largo por 0,3 a 4,5 cm de ancho con el margen irregularmente cre-\n     nado, ápice redondeado y base cuneada, haz verde lustroso de color gris, envés verde claro.","flores":"Dispuestas en racimos terminales simples fasciculados de 2 a 6 cm de largo, raquis\n     esparcidamente hirsuto rojizo; fascículos compuestos por 2 a 5 flores pequeñas. Flores pe-\n     queñas bisexuales, pedicelos de 3 mm de largo; cáliz con 4 sépalos libres ampliamente ova-\n     dos de 1,3 mm de largo x 1 mm de ancho; corola con 4 pétalos blancos ovados de 2 a 2,5\n     mm de largo; androceo compuesto por 10 estambres dispuestos en dos verticilos, ovario\n     súpero, 4 locular.","fruta":"Cápsula oblongo-ovoide de 3 a 4 mm de largo, con los estilos persistentes, de color\n     café marrón cuando está madura.","distribucion_y_ecologia":"Se distribuye en Costa Rica, Colombia y de Venezuela hasta Bolivia\n     en bosques húmedos, secos y subpáramos entre 2000 y 3600 m de altitud (Harling, 1999).\n     En nuestro país es una especie muy abundante en los bosques altoandinos del sur del país,\n     crece entre 2700 y 3600 m de altitud; es una especie dominante en los bosques nativos de\n     la cuenca del río Paute, sin embargo en los bosques de ribera de los ríos de Cuenca, es más\n     bien una especie rara. Posee una excelente capacidad de rebrote y su regeneración natural\n     es buena.","usos_tradicionales":"Madera para construcción de casas pequeñas (vigas, pilares); para ela-\n     borar timones de arado y yugos y para leña. Medicinalmente se usa para limpias y baños de\n     dieta. Sus hojas sirven como forraje para el ganado.","propagacion":"Se recomienda propagarla mediante semillas, para lo cual, se deben recolec-\n     tar las cápsulas antes de que se abran y, secarlas al sol durante 2 días para separar las semi-\n     llas, luego deben sembrarse en almácigos con tierra de vivero, se recomienda sembrarlas al\n     voleo y cubrirlas con una capa fina de arena. El semillero debe taparse con paja, para evitar\n     lavar las semillas durante el riego. La germinación ocurre en un lapso de 60 a 70 días.","images":["/resources/img/arboles-39_0.jpg","/resources/img/arboles-39_1.jpg","/resources/img/arboles-39_2.jpg","/resources/img/arboles-40_0.jpg","/resources/img/arboles-41_0.jpg"],"slug":"sarar"},{"page":42,"original":"42   ÁRBOLES NATIVOS\n\n\n\n\n                                 Familia: Elaeocarpaceae\n                                              Pichul\n\n                             Nombre científico: Vallea stipularis L. f.\n                       Otros nombres comunes: “sacha capulí”, “chul chul”\n\n\n     Hábito: Árbol de 10 m de altura y 20 cm de DAP. Fuste tortuoso, ramificación esparcida,\n     copa estrecha, corteza externa gris fisurada.\n\n     Hojas: Simples alternas con estípulas reniformes, lámina de ampliamente ovada a orbicular,\n     margen entero, ápice agudo y base cordada; haz verde oscuro, envés verde claro glauco.\n\n     Flores: Bisexuales regulares, reunidas en cimas terminales de 3 a 4 cm de largo, cáliz confor-\n     mado por 5 sépalos libres de color verde, corola compuesta por 5 pétalos de color rosado;\n     numerosos estambres dispuestos en dos hileras; ovario súpero con 4 lóculos.\n\n     Fruto: Una cápsula carnosa de color verde amarillento, provisto de apéndices redondeados.\n\n     Distribución y ecología: Es una especie típica de bosque andino alto, crece entre 2500 y\n     3700 m de altitud, con rangos de temperatura entre 10 y 17° C. Es muy frecuente en márge-\n     nes de quebradas y ríos pequeños. En las riberas de los ríos de Cuenca esta especie crece\n     solamente en las partes altas de los ríos Tomebamba, Yanuncay y Tarqui. Posee gran capa-\n     cidad de rebrote y su regeneración natural es buena. Es una especie semicaducifolia, sus\n     hojas adquieren un color rojizo antes de desprenderse del árbol, lo cual ocurre durante la\n     época de estiaje. Sus flores son visitadas por algunas especies de colibríes\n\n     Usos tradicionales: En algunas comunidades campesinas del Azuay, sus hojas y brotes tier-\n     nos se emplean como alimento para el ganado y cuando alcanza fustes de más de 5 m, se\n     emplea para la construcción de viviendas.\n\n     Propagación: Se puede propagar por semillas o estacas. Mediante semillas, éstas deben\n     recolectarse cuando los frutos están maduros en el árbol, luego deben secarse al sol y antes\n     de sembrarse deben sumergírselas en agua durante 48 horas, la germinación ocurre a los\n     45 días. Para propagarlo mediante estacas se recomienda emplear estacas de 2 años con 4\n     a 6 yemas (Serrano, 1996)\n","familia":"Elaeocarpaceae\n","nombre":"Pichul","descripcíon":"","otros_nombres_comunes":["sacha capulí","chul chul"],"nombre_cientifica":"Vallea stipularis L. f.","habito":" Árbol de 10 m de altura y 20 cm de DAP. Fuste tortuoso, ramificación esparcida,\n     copa estrecha, corteza externa gris fisurada.","hojas":"Simples alternas con estípulas reniformes, lámina de ampliamente ovada a orbicular,\n     margen entero, ápice agudo y base cordada; haz verde oscuro, envés verde claro glauco.","flores":"Bisexuales regulares, reunidas en cimas terminales de 3 a 4 cm de largo, cáliz confor-\n     mado por 5 sépalos libres de color verde, corola compuesta por 5 pétalos de color rosado;\n     numerosos estambres dispuestos en dos hileras; ovario súpero con 4 lóculos.","fruta":"Una cápsula carnosa de color verde amarillento, provisto de apéndices redondeados.","distribucion_y_ecologia":"Es una especie típica de bosque andino alto, crece entre 2500 y\n     3700 m de altitud, con rangos de temperatura entre 10 y 17° C. Es muy frecuente en márge-\n     nes de quebradas y ríos pequeños. En las riberas de los ríos de Cuenca esta especie crece\n     solamente en las partes altas de los ríos Tomebamba, Yanuncay y Tarqui. Posee gran capa-\n     cidad de rebrote y su regeneración natural es buena. Es una especie semicaducifolia, sus\n     hojas adquieren un color rojizo antes de desprenderse del árbol, lo cual ocurre durante la\n     época de estiaje. Sus flores son visitadas por algunas especies de colibríes","usos_tradicionales":"En algunas comunidades campesinas del Azuay, sus hojas y brotes tier-\n     nos se emplean como alimento para el ganado y cuando alcanza fustes de más de 5 m, se\n     emplea para la construcción de viviendas.","propagacion":"Se puede propagar por semillas o estacas. Mediante semillas, éstas deben\n     recolectarse cuando los frutos están maduros en el árbol, luego deben secarse al sol y antes\n     de sembrarse deben sumergírselas en agua durante 48 horas, la germinación ocurre a los\n     45 días. Para propagarlo mediante estacas se recomienda emplear estacas de 2 años con 4\n     a 6 yemas (Serrano, 1996)","images":["/resources/img/arboles-43_0.jpg","/resources/img/arboles-43_1.jpg","/resources/img/arboles-43_2.jpg","/resources/img/arboles-44_0.jpg","/resources/img/arboles-45_0.jpg"],"slug":"pichul"},{"page":46,"original":"46   ÁRBOLES NATIVOS\n\n\n\n\n                                  Familia: Escalloniaceae\n                                            Chachaco\n\n                              Nombre científico: Escallonia myrtilloides L.f.\n                       Otros nombres comunes: “chachacoma”, “shisha”, “cerotillo”\n\n\n     Hábito: Árbol de hasta 15 m de altura, con ramificación alterna y copa plana. Tronco cilíndri-\n     co ligeramente tortuoso, corteza externa fisurada de color café oscuro o gris.\n\n     Hojas: Simples alternas, de textura coriácea; lámina ovado espatulada de 1,4 a 2,6 cm de\n     largo por 0,8 a 1,5 cm de ancho, margen aserrado y ápice de agudo a obtuso. Haz glabro\n     verde oscuro, envés verde claro.\n\n     Flores: Solitarias, de 0,8 a 1 cm de largo, dispuestas en las axilas de las hojas o en la parte\n     terminal de las ramitas. Cáliz conformado por 5 sépalos unidos. Corola compuesta por 5 pé-\n     talos unidos con forma urceolada de color verde claro; androceo con 5 estambres de tecas\n     adnatas. Ovario ínfero, estilo cilíndrico y estigma lobado.\n\n     Fruto: Cápsula de color oscuro que contiene muchas semillas (Serrano, 1996).\n\n     Distribución y ecología: Escallonia myrtilloides incluye dos variedades: E. myrtilloides var.\n     myrtilloides y E. myrtilloides var. patens (Romoleroux & Freire Fierro, 2004). La primera se en-\n     cuentra entre 3000 y 3400 m de altitud y se reconoce por sus hojas pequeñas y coriáceas,\n     mientras que E. myrtilloides var. patens, se encuentra entre 2400 y 3800 m de altitud y se\n     reconoce por sus hojas y flores más grandes que las de : E. myrtilloides var. myrtilloides (Ro-\n     moleroux & Freire Fierro, 2004). En las riberas de los ríos de Cuenca crece E. myrtilloides var.\n     patens.\n\n     Esta variedad crece óptimamente en suelos sueltos y profundos y es común en márgenes\n     de ríos y quebradas así como en sitios planos. En las zonas altas de los ríos Yanuncay y To-\n     mebamba es una especie común. Presenta buena capacidad de rebrote y su regeneración\n     natural es muy escasa.\n\n     Usos tradicionales: Generalmente su madera ha sido empleada para postes, vigas y peque-\n     ñas construcciones. Las flores y su resina sirven para la preparación de bebidas que ayudan\n     a curar las molestias del parto (Serrano, 1996).\n\n     Propagación: Se recomienda propagarla mediante semillas, las mismas que deben recolec-\n     tarse directamente del árbol antes que las cápsulas se abran y luego deben secarse por un\n     lapso de 100 días para obtener un buen porcentaje de germinación.\n","familia":"Escalloniaceae\n","nombre":"Chachaco","descripcíon":"","otros_nombres_comunes":["chachacoma","shisha","cerotillo"],"nombre_cientifica":"Escallonia myrtilloides L.f.","habito":" Árbol de hasta 15 m de altura, con ramificación alterna y copa plana. Tronco cilíndri-\n     co ligeramente tortuoso, corteza externa fisurada de color café oscuro o gris.","hojas":"Simples alternas, de textura coriácea; lámina ovado espatulada de 1,4 a 2,6 cm de\n     largo por 0,8 a 1,5 cm de ancho, margen aserrado y ápice de agudo a obtuso. Haz glabro\n     verde oscuro, envés verde claro.","flores":"Solitarias, de 0,8 a 1 cm de largo, dispuestas en las axilas de las hojas o en la parte\n     terminal de las ramitas. Cáliz conformado por 5 sépalos unidos. Corola compuesta por 5 pé-\n     talos unidos con forma urceolada de color verde claro; androceo con 5 estambres de tecas\n     adnatas. Ovario ínfero, estilo cilíndrico y estigma lobado.","fruta":"Cápsula de color oscuro que contiene muchas semillas (Serrano, 1996).","distribucion_y_ecologia":"Escallonia myrtilloides incluye dos variedades: E. myrtilloides var.\n     myrtilloides y E. myrtilloides var. patens (Romoleroux & Freire Fierro, 2004). La primera se en-\n     cuentra entre 3000 y 3400 m de altitud y se reconoce por sus hojas pequeñas y coriáceas,\n     mientras que E. myrtilloides var. patens, se encuentra entre 2400 y 3800 m de altitud y se\n     reconoce por sus hojas y flores más grandes que las de : E. myrtilloides var. myrtilloides (Ro-\n     moleroux & Freire Fierro, 2004). En las riberas de los ríos de Cuenca crece E. myrtilloides var.\n     patens.","usos_tradicionales":"Generalmente su madera ha sido empleada para postes, vigas y peque-\n     ñas construcciones. Las flores y su resina sirven para la preparación de bebidas que ayudan\n     a curar las molestias del parto (Serrano, 1996).","propagacion":"Se recomienda propagarla mediante semillas, las mismas que deben recolec-\n     tarse directamente del árbol antes que las cápsulas se abran y luego deben secarse por un\n     lapso de 100 días para obtener un buen porcentaje de germinación.","images":["/resources/img/arboles-47_0.jpg","/resources/img/arboles-47_1.jpg","/resources/img/arboles-47_2.jpg","/resources/img/arboles-47_3.jpg"],"slug":"chachaco"},{"page":48,"original":"48   ÁRBOLES NATIVOS\n\n\n\n\n                                      Familia: Fabaceae\n                                             Cáñaro\n                             Nombre científico: Erythrina edulis Triana ex Micheli\n                       Otros nombres comunes: “guato”, “porotón”, “cañaro”\n\n     Hábito: Árbol semicaducifolio de 8 a 15 m de altura y 20 a 40 cm de DAP. Tronco y ramas con\n     espinas dispersas, copa globosa e irregular.\n\n     Hojas: Compuestas pinnadas, con 3 folíolos ovado-triangulares, de 7,5 a 14,5 cm de largo\n     por 4,5 a 11,5 cm de ancho; estípulas y glándulas presentes.\n\n     Flores: Agrupadas en racimos terminales o axilares a menudo surgen del tronco de 20 a\n     45 cm de largo. Flores bisexuales, de 2 a 3,5 cm de largo; cáliz campanulado; corola papi-\n     lionoidea (estandarte erecto, más grande que las alas y la quilla, alas menores a la quilla y\n     quilla compuesta de 2 pétalos unidos), comúnmente roja o naranja a veces crema o amarilla.\n     Androceo compuesto por 10 estambres basalmente fusionados en un tubo. Ovario súpero\n     unicarpelar.\n\n     Fruto: Su fruto es una legumbre suave, constreñida entre cada semilla, de 25 a 30 cm de\n     largo, cada vaina contiene de 2 a 6 semillas.\n\n     Distribución y ecología: Se distribuye en la zona andina desde Venezuela hasta Bolivia (Ba-\n     rrera, 1996). Crece entre 900 y 3200 m de altitud. En nuestro país se ha registrado entre 1500\n     y 2500 m de altitud en todas las provincias de la sierra (Jorgensen & León-Yánez, 1999). Es\n     una especie de crecimiento rápido, prefiere ambientes iluminados, pero tolera la sombra\n     sobre todo en etapas juveniles. Se adapta a un amplio intervalo de zonas agroecológicas\n     con precipitaciones que oscilan entre 450 y 2000 mm anuales y temperaturas entre 5 y 25\n     °C. En cuanto a los suelos, crece bien en suelos franco arenosos de textura suelta, pero se\n     adaptan a suelos arcillosos de textura pesada, aunque es poco tolerante al encharcamiento.\n\n     Usos tradicionales: El cáñaro, es una especie muy apreciada y cultivada en huertos, cercas\n     vivas y sitios agrícolas por sus propiedades para fijar nitrógeno y mejorar el suelo. Tradi-\n     cionalmente sus semillas han sido empleadas como alimento, cocidas o en harinas y me-\n     dicinalmente sus flores han sido empleadas como expectorantes naturales y para aliviar\n     problemas de reumatismo (Loján, 1992), su corteza en cocción sirve para curar afecciones\n     bucales y de garganta mediante gárgaras (Reynel y León, 1990). También se emplea como\n     forraje para el ganado con un alto valor nutritivo (Reynel y León, 1990).\n\n     Propagación: Se puede propagar sexual o vegetativamente. Para propagación de forma se-\n     xual, sus semillas se deben recolectar cuando los frutos empiecen a caerse y abrirse (Loján,\n     1992) y sembrarlas lo más pronto posible ya que son semillas recalcitrantes. Para la siembra\n     se recomienda ponerlas en platabandas con la parte cóncava hacia arriba y a 2 cm de pro-\n     fundidad (Loján, 1992). Vegetativamente se propaga mediante estacas semimaduras de 15\n     a 30 cm de largo y 2 a 3 cm de diámetro (Loján, 1992), las mismas que deben plantarse en\n     sustrato orgánico y ser protegidas del viento y la resequedad hasta que las plántulas alcan-\n     cen los 50 o 60 cm de altura para ser trasplantadas al lugar definitivo.\n","familia":"Fabaceae\n\n                             Nombre científico: Erythrina edulis Triana ex Micheli\n                       Otros nombres comunes: “guato”, “porotón”, “cañaro”","nombre":"Fabaceae\n                                             Cáñaro","descripcíon":"","otros_nombres_comunes":["guato","porotón","cañaro"],"nombre_cientifica":"Erythrina edulis Triana ex Micheli","habito":" Árbol semicaducifolio de 8 a 15 m de altura y 20 a 40 cm de DAP. Tronco y ramas con\n     espinas dispersas, copa globosa e irregular.","hojas":"Compuestas pinnadas, con 3 folíolos ovado-triangulares, de 7,5 a 14,5 cm de largo\n     por 4,5 a 11,5 cm de ancho; estípulas y glándulas presentes.","flores":"Agrupadas en racimos terminales o axilares a menudo surgen del tronco de 20 a\n     45 cm de largo. Flores bisexuales, de 2 a 3,5 cm de largo; cáliz campanulado; corola papi-\n     lionoidea (estandarte erecto, más grande que las alas y la quilla, alas menores a la quilla y\n     quilla compuesta de 2 pétalos unidos), comúnmente roja o naranja a veces crema o amarilla.\n     Androceo compuesto por 10 estambres basalmente fusionados en un tubo. Ovario súpero\n     unicarpelar.","fruta":"Su fruto es una legumbre suave, constreñida entre cada semilla, de 25 a 30 cm de\n     largo, cada vaina contiene de 2 a 6 semillas.","distribucion_y_ecologia":"Se distribuye en la zona andina desde Venezuela hasta Bolivia (Ba-\n     rrera, 1996). Crece entre 900 y 3200 m de altitud. En nuestro país se ha registrado entre 1500\n     y 2500 m de altitud en todas las provincias de la sierra (Jorgensen & León-Yánez, 1999). Es\n     una especie de crecimiento rápido, prefiere ambientes iluminados, pero tolera la sombra\n     sobre todo en etapas juveniles. Se adapta a un amplio intervalo de zonas agroecológicas\n     con precipitaciones que oscilan entre 450 y 2000 mm anuales y temperaturas entre 5 y 25\n     °C. En cuanto a los suelos, crece bien en suelos franco arenosos de textura suelta, pero se\n     adaptan a suelos arcillosos de textura pesada, aunque es poco tolerante al encharcamiento.","usos_tradicionales":"El cáñaro, es una especie muy apreciada y cultivada en huertos, cercas\n     vivas y sitios agrícolas por sus propiedades para fijar nitrógeno y mejorar el suelo. Tradi-\n     cionalmente sus semillas han sido empleadas como alimento, cocidas o en harinas y me-\n     dicinalmente sus flores han sido empleadas como expectorantes naturales y para aliviar\n     problemas de reumatismo (Loján, 1992), su corteza en cocción sirve para curar afecciones\n     bucales y de garganta mediante gárgaras (Reynel y León, 1990). También se emplea como\n     forraje para el ganado con un alto valor nutritivo (Reynel y León, 1990).","propagacion":"Se puede propagar sexual o vegetativamente. Para propagación de forma se-\n     xual, sus semillas se deben recolectar cuando los frutos empiecen a caerse y abrirse (Loján,\n     1992) y sembrarlas lo más pronto posible ya que son semillas recalcitrantes. Para la siembra\n     se recomienda ponerlas en platabandas con la parte cóncava hacia arriba y a 2 cm de pro-\n     fundidad (Loján, 1992). Vegetativamente se propaga mediante estacas semimaduras de 15\n     a 30 cm de largo y 2 a 3 cm de diámetro (Loján, 1992), las mismas que deben plantarse en\n     sustrato orgánico y ser protegidas del viento y la resequedad hasta que las plántulas alcan-\n     cen los 50 o 60 cm de altura para ser trasplantadas al lugar definitivo.","images":["/resources/img/arboles-49_0.jpg","/resources/img/arboles-49_1.jpg","/resources/img/arboles-49_2.jpg","/resources/img/arboles-49_3.jpg"],"slug":"fabaceae-caro"},{"page":50,"original":"50   ÁRBOLES NATIVOS\n\n\n\n\n                                     Familia: Fabaceae\n                                              Guaba\n\n                             Nombre científico: Inga insignis Kunth\n                       Otros nombres comunes: “pacay”, “guabilla”, “guagua”\n\n\n     Hábito: Árbol pequeño de 4 a 8 m de alto, con ramificación alterna desde cerca de la base,\n     copa ancha, follaje verde brillante a veces rojizo en los brotes y ramas tiernas.\n\n     Hojas: Alternas, compuestas imparipinnadas, raquis alado y nectarios foliares; 4 a 6 pares de\n     folíolos elípticos, de 10 a 14 cm de largo por 4 a 6 cm de ancho.\n\n     Flores: Reunidas en racimos axilares de 6 a 10 cm de largo. Flores de 3 a 4 cm de largo; cáliz\n     cupuliforme, con 5 lóbulos; corola tubular de color verde amarillento; numerosos estambres\n     largos de color blanco y unidos basalmente en un tubo de la corola; ovario unicarpelar.\n\n     Fruto: Legumbre cuadrangular pubescente con márgenes surcados de 12 a 14 cm de largo\n     x 2 a 3 cm de ancho, de color marrón.\n\n     Distribución y ecología: Especie nativa distribuida en los Andes de Colombia, Perú y Ecua-\n     dor entre 1000 y 3000 m de altitud. En nuestro país crece a lo largo del callejón interandino\n     en las provincias de Azuay, Cañar, Chimborazo, El Oro, Loja, Napo, Pichincha y Tungurahua,\n     en donde es ampliamente cultivada en huertos, jardines y zonas agrícolas (Pennington &\n     Revelo, 1997). En la ribera del río Yanuncay se han registrado 8 individuos en el área urbana\n     de Cuenca, pero en general es una especie común en todo el valle de Cuenca-Azogues.\n\n     Florece y fructifica con un rango de temperatura de 8 a 25 °C y es tolerante a la sequía (Penn-\n     ington & Revelo, 1997). Crece óptimamente en ambientes plenamente iluminados y prefiere\n     suelo franco arenoso y bien drenado.\n\n     Usos tradicionales: La pulpa de su fruto es comestible. La madera se emplea para vigas e\n     instrumentos de labranza (Jaramillo, 2013). Se emplea también como leña y para fabricar\n     carbón y es una especie recomendada para agroforestería por su rápido crecimiento y su\n     capacidad de fijar nitrógeno en asociación con bacterias.\n\n     Propagación: Se propaga fácilmente mediante semillas, las mismas que deben extraerse\n     cuando los frutos estén maduros y sembrarse inmediatamente, porque son semillas que\n     no toleran el almacenamiento, a veces las semillas han iniciado la germinación en el mismo\n     fruto, en tal caso deben extraerse con cuidado.\n","familia":"Fabaceae\n","nombre":"Guaba","descripcíon":"","otros_nombres_comunes":["pacay","guabilla","guagua"],"nombre_cientifica":"Inga insignis Kunth","habito":" Árbol pequeño de 4 a 8 m de alto, con ramificación alterna desde cerca de la base,\n     copa ancha, follaje verde brillante a veces rojizo en los brotes y ramas tiernas.","hojas":"Alternas, compuestas imparipinnadas, raquis alado y nectarios foliares; 4 a 6 pares de\n     folíolos elípticos, de 10 a 14 cm de largo por 4 a 6 cm de ancho.","flores":"Reunidas en racimos axilares de 6 a 10 cm de largo. Flores de 3 a 4 cm de largo; cáliz\n     cupuliforme, con 5 lóbulos; corola tubular de color verde amarillento; numerosos estambres\n     largos de color blanco y unidos basalmente en un tubo de la corola; ovario unicarpelar.","fruta":"Legumbre cuadrangular pubescente con márgenes surcados de 12 a 14 cm de largo\n     x 2 a 3 cm de ancho, de color marrón.","distribucion_y_ecologia":"Especie nativa distribuida en los Andes de Colombia, Perú y Ecua-\n     dor entre 1000 y 3000 m de altitud. En nuestro país crece a lo largo del callejón interandino\n     en las provincias de Azuay, Cañar, Chimborazo, El Oro, Loja, Napo, Pichincha y Tungurahua,\n     en donde es ampliamente cultivada en huertos, jardines y zonas agrícolas (Pennington &\n     Revelo, 1997). En la ribera del río Yanuncay se han registrado 8 individuos en el área urbana\n     de Cuenca, pero en general es una especie común en todo el valle de Cuenca-Azogues.","usos_tradicionales":"La pulpa de su fruto es comestible. La madera se emplea para vigas e\n     instrumentos de labranza (Jaramillo, 2013). Se emplea también como leña y para fabricar\n     carbón y es una especie recomendada para agroforestería por su rápido crecimiento y su\n     capacidad de fijar nitrógeno en asociación con bacterias.","propagacion":"Se propaga fácilmente mediante semillas, las mismas que deben extraerse\n     cuando los frutos estén maduros y sembrarse inmediatamente, porque son semillas que\n     no toleran el almacenamiento, a veces las semillas han iniciado la germinación en el mismo\n     fruto, en tal caso deben extraerse con cuidado.","images":["/resources/img/arboles-51_0.jpg","/resources/img/arboles-51_1.jpg","/resources/img/arboles-51_2.jpg"],"slug":"guaba"},{"page":52,"original":"52   ÁRBOLES NATIVOS\n\n\n\n\n                                  Familia: Juglandaceae\n                                               Nogal\n\n                             Nombre científico: Juglans neotropica Diels\n                       Otros nombres comunes: “tocte”\n\n     Hábito: Árbol de hasta 25 m de altura y 80 cm de diámetro. Tronco recto, copa globosa,\n     corteza externa gris agrietada.\n\n     Hojas: Compuestas caducifolias, con 5 a 9 pares de folíolos de forma ovalado-lanceolada, de\n     colores verde oscuro y aromáticas al frotarlas.\n\n     Flores: Unisexuales, las masculinas agrupadas en amentos pendulares de hasta 20 cm de\n     largo, provistas de numerosos estambres, con anteras dehiscentes longitudinalmente. Flo-\n     res femeninas reunidas en inflorescencias de 6 cm de largo, sostenidas por una bráctea, con\n     4 sépalos fusionados al ovario.\n\n     Fruto: Drupa redonda de 4 a 6 cm de diámetro con una semilla de embrión ovoide y cotile-\n     dones corrugados.\n\n     Distribución y ecología: Está ampliamente distribuido en bosques montanos y premon-\n     tanos de Centro y Sur América entre 1000 y 3500 m de altitud (Pennington et al, 2004). En\n     nuestro país se encuentra a lo largo de la región andina entre 1000 y 3500. En los valles inte-\n     randinos esta especie se cultiva cerca de viviendas y zonas agrícolas. Es una especie frecuen-\n     te en los márgenes de los ríos de Cuenca y en general en todo el valle de Cuenca-Azogues.\n\n     Usos tradicionales: En la región sus semillas y su madera es muy apreciada para la fabrica-\n     ción de muebles y artesanías, especialmente guitarras. En la provincia de Imbabura al norte\n     del país, con sus semillas se preparan dulces típicos conocidos como nogadas (Quintana,\n     2010).\n\n     Propagación: Se propaga mediante semillas, que deben obtenerse de frutos maduros reco-\n     lectados directamente del árbol o cuando se han caído. Para facilitar la germinación los fru-\n     tos deben agruparse y dejar que se descomponga la pulpa, luego deben lavarse y secarse.\n     Loján (1992), recomienda dos tratamientos pregerminativos a saber:\n\n        Estratificación: Consiste en poner las semillas entre capas de arena húmeda durante 15\n        a 21 días antes de la siembra, luego estas semillas deben sembrarse en platabandas o\n        fundas y la germinación inicia después de tres meses.\n\n        Soleamiento: Consiste en exponer las semillas al sol directo por un lapso de dos horas,\n        transcurrido este tiempo las semillas presentan fisuras por donde se debe poner arena\n        fina para impedir que se cierren nuevamente, de esta manera al sembrarse se facilita la\n        penetración de agua para activar el proceso de germinación.\n","familia":"Juglandaceae\n","nombre":"Nogal","descripcíon":"","otros_nombres_comunes":["tocte"],"nombre_cientifica":"Juglans neotropica Diels","habito":" Árbol de hasta 25 m de altura y 80 cm de diámetro. Tronco recto, copa globosa,\n     corteza externa gris agrietada.","hojas":"Compuestas caducifolias, con 5 a 9 pares de folíolos de forma ovalado-lanceolada, de\n     colores verde oscuro y aromáticas al frotarlas.","flores":"Unisexuales, las masculinas agrupadas en amentos pendulares de hasta 20 cm de\n     largo, provistas de numerosos estambres, con anteras dehiscentes longitudinalmente. Flo-\n     res femeninas reunidas en inflorescencias de 6 cm de largo, sostenidas por una bráctea, con\n     4 sépalos fusionados al ovario.","fruta":"Drupa redonda de 4 a 6 cm de diámetro con una semilla de embrión ovoide y cotile-\n     dones corrugados.","distribucion_y_ecologia":"Está ampliamente distribuido en bosques montanos y premon-\n     tanos de Centro y Sur América entre 1000 y 3500 m de altitud (Pennington et al, 2004). En\n     nuestro país se encuentra a lo largo de la región andina entre 1000 y 3500. En los valles inte-\n     randinos esta especie se cultiva cerca de viviendas y zonas agrícolas. Es una especie frecuen-\n     te en los márgenes de los ríos de Cuenca y en general en todo el valle de Cuenca-Azogues.","usos_tradicionales":"En la región sus semillas y su madera es muy apreciada para la fabrica-\n     ción de muebles y artesanías, especialmente guitarras. En la provincia de Imbabura al norte\n     del país, con sus semillas se preparan dulces típicos conocidos como nogadas (Quintana,\n     2010).","propagacion":"Se propaga mediante semillas, que deben obtenerse de frutos maduros reco-\n     lectados directamente del árbol o cuando se han caído. Para facilitar la germinación los fru-\n     tos deben agruparse y dejar que se descomponga la pulpa, luego deben lavarse y secarse.\n     Loján (1992), recomienda dos tratamientos pregerminativos a saber:\n\n        Estratificación: Consiste en poner las semillas entre capas de arena húmeda durante 15\n        a 21 días antes de la siembra, luego estas semillas deben sembrarse en platabandas o\n        fundas y la germinación inicia después de tres meses.\n\n        Soleamiento: Consiste en exponer las semillas al sol directo por un lapso de dos horas,\n        transcurrido este tiempo las semillas presentan fisuras por donde se debe poner arena\n        fina para impedir que se cierren nuevamente, de esta manera al sembrarse se facilita la\n        penetración de agua para activar el proceso de germinación.","images":["/resources/img/arboles-53_0.jpg","/resources/img/arboles-53_1.jpg","/resources/img/arboles-53_2.jpg","/resources/img/arboles-54_0.jpg","/resources/img/arboles-55_0.jpg"],"slug":"nogal"},{"page":56,"original":"56   ÁRBOLES NATIVOS\n\n\n\n\n                                    Familia: Lamiaceae\n                                           Jiguerón\n\n                             Nombre científico: Aegiphila ferruginea Hayek & Spruce\n\n\n\n\n     Hábito: Árbol de hasta 10 m de altura, copa globosa, tronco cilíndrico, tortuoso, con ra-\n     mificación alterna.\n\n     Hojas: Simples, opuestas; lámina con forma elíptica oblonga 9 a 12 cm de largo por 3 a 6 cm\n     de ancho, base obtusa, ápice acuminado y margen entero; presentan pubescencia ferrugi-\n     nosa particularmente en el envés.\n\n     Flores: Flores reunidas en pequeñas cimas axilares, de 2 a 3 cm de largo, sostenidas por un\n     pedúnculo de 5 cm de largo. Flores actinomorfas, bisexuales, con pedicelos de 2 a 3 mm\n     de largo; corola actinomorfa, conformada por 4 pétalos blancos, reflexos; androceo con 4\n     estambres que sobresalen de la corola, filamentos blancos; ovario superior con 4 lóculos,\n     estigma bífido.\n\n     Fruto: Drupa subglobosa, con el cáliz persistente, de color verde cuando está tierna y ama-\n     rilla al madurar. Contiene 4 semillas.\n\n     Distribución y ecología: Especie endémica de los Andes ecuatorianos, crece en bosques\n     andinos húmedos entre 2500 y 3600 m de altitud; es frecuente en bosques secundarios y ha\n     sido tolerado en zonas de pastizal, bordes de caminos, linderos y cercas vivas. Prefiere sue-\n     los profundos de textura variable. Su regeneración natural es escasa, sus semillas germinan\n     luego de ser dispersadas por aves. Posee buena capacidad de rebrote.\n\n     Usos tradicionales: Antiguamente su madera se empleaba para la elaboración de vigas y\n     pilares que eran empleados en la construcción de viviendas campesinas, en la actualidad se\n     emplea como postes.\n\n     Propagación: Se propaga mediante semillas, las mismas que deben recolectarse directa-\n     mente de los árboles semilleros cuando los frutos presentan un color amarillo o café amari-\n     llento. Para la germinación se recomienda seguir las siguientes recomendaciones: 1) secado\n     al sol durante 15 a 20 días, 2) inmersión en agua durante 48 horas, 3) siembra directa en\n     semilleros o fundas de polietileno.\n","familia":"Lamiaceae\n","nombre":"Jiguerón","descripcíon":"","otros_nombres_comunes":[],"nombre_cientifica":"Aegiphila ferruginea Hayek & Spruce","habito":" Árbol de hasta 10 m de altura, copa globosa, tronco cilíndrico, tortuoso, con ra-\n     mificación alterna.","hojas":"Simples, opuestas; lámina con forma elíptica oblonga 9 a 12 cm de largo por 3 a 6 cm\n     de ancho, base obtusa, ápice acuminado y margen entero; presentan pubescencia ferrugi-\n     nosa particularmente en el envés.","flores":"Flores reunidas en pequeñas cimas axilares, de 2 a 3 cm de largo, sostenidas por un\n     pedúnculo de 5 cm de largo. Flores actinomorfas, bisexuales, con pedicelos de 2 a 3 mm\n     de largo; corola actinomorfa, conformada por 4 pétalos blancos, reflexos; androceo con 4\n     estambres que sobresalen de la corola, filamentos blancos; ovario superior con 4 lóculos,\n     estigma bífido.","fruta":"Drupa subglobosa, con el cáliz persistente, de color verde cuando está tierna y ama-\n     rilla al madurar. Contiene 4 semillas.","distribucion_y_ecologia":"Especie endémica de los Andes ecuatorianos, crece en bosques\n     andinos húmedos entre 2500 y 3600 m de altitud; es frecuente en bosques secundarios y ha\n     sido tolerado en zonas de pastizal, bordes de caminos, linderos y cercas vivas. Prefiere sue-\n     los profundos de textura variable. Su regeneración natural es escasa, sus semillas germinan\n     luego de ser dispersadas por aves. Posee buena capacidad de rebrote.","usos_tradicionales":"Antiguamente su madera se empleaba para la elaboración de vigas y\n     pilares que eran empleados en la construcción de viviendas campesinas, en la actualidad se\n     emplea como postes.","propagacion":"Se propaga mediante semillas, las mismas que deben recolectarse directa-\n     mente de los árboles semilleros cuando los frutos presentan un color amarillo o café amari-\n     llento. Para la germinación se recomienda seguir las siguientes recomendaciones: 1) secado\n     al sol durante 15 a 20 días, 2) inmersión en agua durante 48 horas, 3) siembra directa en\n     semilleros o fundas de polietileno.","images":["/resources/img/arboles-57_0.jpg","/resources/img/arboles-57_1.jpg","/resources/img/arboles-57_2.jpg","/resources/img/arboles-57_3.jpg"],"slug":"jiguern"},{"page":58,"original":"58   ÁRBOLES NATIVOS\n\n\n\n\n                                    Familia: Lauraceae\n                                         Aguacatillo\n\n                             Nombre científico: Ocotea heterochroma Mez & Sodiro\n                       Otros nombres comunes: “canelo”, “hihua amarilla”, “facte”\n\n\n     Hábito: Árbol de 10 a 25 m de altura y 40 a 80 cm de DAP. Tronco cilíndrico recto, ramifica-\n     ción alterna, copa aparasolada o globosa, corteza externa de color rojo amarillento escamo-\n     sa y lenticelada.\n\n     Hojas: Aromáticas, simples alternas de textura coriácea, lámina de forma oval a elíptica de 7\n     a 15 cm de largo por 3 a 8,5, margen entero y ápice mucronado, haz verde oscuro brillante,\n     envés verde amarillento, hojas jóvenes con tintes rojizos.\n\n     Flores: Reunidas en panículas axilares de 4 a 8 cm de largo. Flores bisexuales con un perian-\n     to de 6 tépalos triangulares de color verde amarillento, dispuestos en 2 verticilos; androceo\n     compuesto por 9 a 11 estambres dispuestos en 3 verticilos, filamentos de 2 mm, tecas adna-\n     tas. Ovario ínfero, estilo simple y estigma discoide.\n\n     Fruto: Drupa de forma oblonga provista de una cúpula, de 4 a 5 cm de largo por 1,8 a 2,5 cm\n     de ancho; de color negro cuando está madura.\n\n     Distribución y ecología: Árbol nativo de los Andes de Colombia y Ecuador. En nuestro país\n     se encuentra entre 2000 y 3500 m de altitud y se ha registrado en las provincias de Azuay,\n     Carchi, Chimborazo, Bolívar y Napo. Especie típica de bosques maduros, se establece bien\n     en sitios planos con suelos profundos. Presenta buena capacidad de rebrote y su regenera-\n     ción natural es buena. Ecológicamente es importante ya que sus frutos sirven de alimento a\n     loros, tucanes y pavas de monte, los cuales luego de consumirlos y digerirlos, regurgitan sus\n     semillas al suelo del bosque, las cuales germinan bajo la sombra del dosel.\n\n     Usos tradicionales: Su madera fina y de buena calidad es empleada en trabajos de ebanis-\n     tería (De la Torre et al, 2008) y su tronco se usa para la construcción de pequeñas viviendas\n     rurales. En medicina tradicional sus hojas en infusión se emplean para bañar niños enfermos\n     (De la Torre et al, 2008).\n\n     Propagación: Se puede multiplicar mediante semillas, para lo cual se pueden colectar los\n     frutos maduros que muestran un color verde amarillento. La germinación inicia entre 20 y\n     30 días después de la siembra. Es recomendable poner a las plántulas en crecimiento bajo\n     sombra parcial para tener un óptimo crecimiento.\n","familia":"Lauraceae\n","nombre":"Aguacatillo","descripcíon":"","otros_nombres_comunes":["canelo","hihua amarilla","facte"],"nombre_cientifica":"Ocotea heterochroma Mez & Sodiro","habito":" Árbol de 10 a 25 m de altura y 40 a 80 cm de DAP. Tronco cilíndrico recto, ramifica-\n     ción alterna, copa aparasolada o globosa, corteza externa de color rojo amarillento escamo-\n     sa y lenticelada.","hojas":"Aromáticas, simples alternas de textura coriácea, lámina de forma oval a elíptica de 7\n     a 15 cm de largo por 3 a 8,5, margen entero y ápice mucronado, haz verde oscuro brillante,\n     envés verde amarillento, hojas jóvenes con tintes rojizos.","flores":"Reunidas en panículas axilares de 4 a 8 cm de largo. Flores bisexuales con un perian-\n     to de 6 tépalos triangulares de color verde amarillento, dispuestos en 2 verticilos; androceo\n     compuesto por 9 a 11 estambres dispuestos en 3 verticilos, filamentos de 2 mm, tecas adna-\n     tas. Ovario ínfero, estilo simple y estigma discoide.","fruta":"Drupa de forma oblonga provista de una cúpula, de 4 a 5 cm de largo por 1,8 a 2,5 cm\n     de ancho; de color negro cuando está madura.","distribucion_y_ecologia":"Árbol nativo de los Andes de Colombia y Ecuador. En nuestro país\n     se encuentra entre 2000 y 3500 m de altitud y se ha registrado en las provincias de Azuay,\n     Carchi, Chimborazo, Bolívar y Napo. Especie típica de bosques maduros, se establece bien\n     en sitios planos con suelos profundos. Presenta buena capacidad de rebrote y su regenera-\n     ción natural es buena. Ecológicamente es importante ya que sus frutos sirven de alimento a\n     loros, tucanes y pavas de monte, los cuales luego de consumirlos y digerirlos, regurgitan sus\n     semillas al suelo del bosque, las cuales germinan bajo la sombra del dosel.","usos_tradicionales":"Su madera fina y de buena calidad es empleada en trabajos de ebanis-\n     tería (De la Torre et al, 2008) y su tronco se usa para la construcción de pequeñas viviendas\n     rurales. En medicina tradicional sus hojas en infusión se emplean para bañar niños enfermos\n     (De la Torre et al, 2008).","propagacion":"Se puede multiplicar mediante semillas, para lo cual se pueden colectar los\n     frutos maduros que muestran un color verde amarillento. La germinación inicia entre 20 y\n     30 días después de la siembra. Es recomendable poner a las plántulas en crecimiento bajo\n     sombra parcial para tener un óptimo crecimiento.","images":["/resources/img/arboles-59_0.jpg","/resources/img/arboles-59_1.jpg","/resources/img/arboles-59_2.jpg"],"slug":"aguacatillo"},{"page":60,"original":"60   ÁRBOLES NATIVOS\n\n\n\n\n                                     Familia: Meliaceae\n                                              Cedro\n\n                             Nombre científico: Cedrela montana Moritz ex Turcz\n                       Otros nombres comunes: “flor de madera”, “cedrillo”,\n                                              “cedro andino”\n\n\n     Hábito: Árbol monopódico de hasta 40 m de alto y 1 m de DAP. Tronco recto, corteza ex-\n     terna fisurada de color gris, con fuerte olor a ajo cuando se realizan cortes; madera de color\n     rosado.\n\n     Hojas: Dispuestas en espiral alrededor de las ramas, de 20 a 80 cm de largo y conformadas\n     por 7 a 14 pares de folíolos con forma oblongo lanceolada generalmente 8 a 11 cm de largo\n     por 2,5 a 3,5 cm de ancho, glabros en el haz y pubescentes en el envés.\n\n     Flores: Reunidas en panículas terminales de 30 a 50 cm de largo, normalmente péndulas.\n     Flores unisexuales (plantas monoicas); cáliz con forma de copa con 5 lóbulos; corola con 5\n     pétalos de color crema. Presentan un nectario columnar, donde se originan los estambres\n     y el ovario.\n\n     Fruto: Cápsula leñosa con forma elipsoide, péndula de 3 a 5 cm de diámetro, que contiene\n     semillas aladas.\n\n     Distribución y ecología: Especie nativa, con una amplia distribución desde Venezuela hasta\n     Perú. Crece en regiones montañosas y bosques nublados entre 1300 y 3000 m de altitud\n     (Pennington & Muellner, 2010). En nuestro país es frecuente encontrarla en valles secos in-\n     terandinos (con una precipitación inferior a los 2000 mm anuales). En estos lugares los indi-\n     viduos poseen hojas con folíolos glabros con forma lanceolada y sus flores poseen pétalos\n     blancos, mientras que los individuos que crecen en bosques nublados húmedos, poseen\n     hojas con folíolos más grandes y pubescentes, y sus flores tienen pétalos rosados.\n\n     Esta especie es ornamental en parques de la ciudad de Cuenca y existen algunos individuos\n     que crecen en forma natural en los márgenes de los ríos Tomebamba y Yanuncay, en este\n     último se han registrado diez individuos en el sector de Barabón.\n\n     Usos tradicionales: Su madera es apreciada especialmente para la fabricación de muebles.\n\n     Propagación: Se propaga mediante semillas, las cuales deben recolectarse cuando las cáp-\n     sulas todavía se encuentren en el árbol. Para acelerar el proceso de germinación se reco-\n     mienda remojar las semillas por un lapso de 20 a 30 horas antes de sembrarlas en macetas\n     o almácigos\n","familia":"Meliaceae\n","nombre":"Cedro","descripcíon":"","otros_nombres_comunes":["flor de madera","cedrillo","cedro andino"],"nombre_cientifica":"Cedrela montana Moritz ex Turcz","habito":" Árbol monopódico de hasta 40 m de alto y 1 m de DAP. Tronco recto, corteza ex-\n     terna fisurada de color gris, con fuerte olor a ajo cuando se realizan cortes; madera de color\n     rosado.","hojas":"Dispuestas en espiral alrededor de las ramas, de 20 a 80 cm de largo y conformadas\n     por 7 a 14 pares de folíolos con forma oblongo lanceolada generalmente 8 a 11 cm de largo\n     por 2,5 a 3,5 cm de ancho, glabros en el haz y pubescentes en el envés.","flores":"Reunidas en panículas terminales de 30 a 50 cm de largo, normalmente péndulas.\n     Flores unisexuales (plantas monoicas); cáliz con forma de copa con 5 lóbulos; corola con 5\n     pétalos de color crema. Presentan un nectario columnar, donde se originan los estambres\n     y el ovario.","fruta":"Cápsula leñosa con forma elipsoide, péndula de 3 a 5 cm de diámetro, que contiene\n     semillas aladas.","distribucion_y_ecologia":"Especie nativa, con una amplia distribución desde Venezuela hasta\n     Perú. Crece en regiones montañosas y bosques nublados entre 1300 y 3000 m de altitud\n     (Pennington & Muellner, 2010). En nuestro país es frecuente encontrarla en valles secos in-\n     terandinos (con una precipitación inferior a los 2000 mm anuales). En estos lugares los indi-\n     viduos poseen hojas con folíolos glabros con forma lanceolada y sus flores poseen pétalos\n     blancos, mientras que los individuos que crecen en bosques nublados húmedos, poseen\n     hojas con folíolos más grandes y pubescentes, y sus flores tienen pétalos rosados.","usos_tradicionales":"Su madera es apreciada especialmente para la fabricación de muebles.","propagacion":"Se propaga mediante semillas, las cuales deben recolectarse cuando las cáp-\n     sulas todavía se encuentren en el árbol. Para acelerar el proceso de germinación se reco-\n     mienda remojar las semillas por un lapso de 20 a 30 horas antes de sembrarlas en macetas\n     o almácigos","images":["/resources/img/arboles-61_0.jpg","/resources/img/arboles-61_1.jpg","/resources/img/arboles-61_2.jpg","/resources/img/arboles-61_3.jpg","/resources/img/arboles-61_4.jpg"],"slug":"cedro"},{"page":62,"original":"62   ÁRBOLES NATIVOS\n\n\n\n\n                               Familia: Melastomataceae\n                                            Yugyug\n\n                             Nombre científico: Miconia theaezans (Bonpl.) Cogn\n                       Otros nombres comunes: “cebolleta”\n\n\n     Hábito: Árbol de 6 a 10 m de altura y 15 a 30 cm de DAP. Tronco cilíndrico recto, corteza\n     externa lisa color café o marrón; ramificación alterna, copa amplia, follaje verde lustroso.\n\n     Hojas: Simples, opuestas, pecioladas, lámina de forma elíptica lanceolada de 5 a 7 cm de\n     largo, por 2 a 2,5 cm de ancho, margen entero, ápice de acuminado a agudo y base cuneada.\n     Haz verde lustroso, envés verde claro con 3 nervios prominentes, de tipo basal perfecto.\n\n     Flores: Dispuestas en panículas terminales de 4 a 6 cm de largo. Flores bisexuales, actino-\n     morfas de 0,6 cm de diámetro; cáliz semitubular con 5 dientes; corola compuesta por 5 pé-\n     talos de color blanco y forma orbicular que se caen en la antesis; androceo compuesto por\n     10 estambres isomorfos con anteras de color amarillo. Ovario semiínfero con 2 lóculos, estilo\n     blanco translúcido, estigma expandido.\n\n     Fruto: Baya carnosa de color verde de 0,4 cm de diámetro, que contiene numerosas semillas\n     de forma ovoide y color blanco (Minga, 2000).\n\n     Distribución y ecología: Especie nativa de amplia distribución a lo largo de la región andina\n     del Ecuador, se encuentra entre 500 y 3400 m de altitud. Crece en una gran variedad de\n     suelos y es componente importante de bosques andinos maduros y de sucesión secundaria.\n     Numerosas especies de aves nativas consumen sus frutos y potencialmente son agentes de\n     dispersión. En los márgenes de los ríos de Cuenca esta especie crece en el Tomebamba des-\n     de el sector de Sayausí hasta el límite del Parque Nacional Cajas y en el río Yanuncay desde\n     el sector de Barabón hasta Soldados.\n\n     Usos tradicionales: En algunas zonas rurales de la provincia del Azuay como Jadán, Ludo y\n     San Juan, su madera se emplea para postes, vigas, pilares y largueros, para la construcción\n     de viviendas.\n\n     Propagación: No se conoce sobre métodos para su propagación, pero se sabe que tiene\n     una buena capacidad de regeneración natural.\n","familia":"Melastomataceae\n","nombre":"Yugyug","descripcíon":"","otros_nombres_comunes":["cebolleta"],"nombre_cientifica":"Miconia theaezans (Bonpl.) Cogn","habito":" Árbol de 6 a 10 m de altura y 15 a 30 cm de DAP. Tronco cilíndrico recto, corteza\n     externa lisa color café o marrón; ramificación alterna, copa amplia, follaje verde lustroso.","hojas":"Simples, opuestas, pecioladas, lámina de forma elíptica lanceolada de 5 a 7 cm de\n     largo, por 2 a 2,5 cm de ancho, margen entero, ápice de acuminado a agudo y base cuneada.\n     Haz verde lustroso, envés verde claro con 3 nervios prominentes, de tipo basal perfecto.","flores":"Dispuestas en panículas terminales de 4 a 6 cm de largo. Flores bisexuales, actino-\n     morfas de 0,6 cm de diámetro; cáliz semitubular con 5 dientes; corola compuesta por 5 pé-\n     talos de color blanco y forma orbicular que se caen en la antesis; androceo compuesto por\n     10 estambres isomorfos con anteras de color amarillo. Ovario semiínfero con 2 lóculos, estilo\n     blanco translúcido, estigma expandido.","fruta":"Baya carnosa de color verde de 0,4 cm de diámetro, que contiene numerosas semillas\n     de forma ovoide y color blanco (Minga, 2000).","distribucion_y_ecologia":"Especie nativa de amplia distribución a lo largo de la región andina\n     del Ecuador, se encuentra entre 500 y 3400 m de altitud. Crece en una gran variedad de\n     suelos y es componente importante de bosques andinos maduros y de sucesión secundaria.\n     Numerosas especies de aves nativas consumen sus frutos y potencialmente son agentes de\n     dispersión. En los márgenes de los ríos de Cuenca esta especie crece en el Tomebamba des-\n     de el sector de Sayausí hasta el límite del Parque Nacional Cajas y en el río Yanuncay desde\n     el sector de Barabón hasta Soldados.","usos_tradicionales":"En algunas zonas rurales de la provincia del Azuay como Jadán, Ludo y\n     San Juan, su madera se emplea para postes, vigas, pilares y largueros, para la construcción\n     de viviendas.","propagacion":"No se conoce sobre métodos para su propagación, pero se sabe que tiene\n     una buena capacidad de regeneración natural.","images":["/resources/img/arboles-63_0.jpg","/resources/img/arboles-63_1.jpg","/resources/img/arboles-63_2.jpg"],"slug":"yugyug"},{"page":64,"original":"64   ÁRBOLES NATIVOS\n\n\n\n\n                                     Familia: Myrtaceae\n                                             Huahual\n\n                       Nombre científico: Myrcianthes rhopaloides (Kunth) McVaugh\n               Otros nombres comunes: “arrayán”\n\n\n     Hábito: Árbol, crece hasta los 15 m de altura, tronco cilíndrico, tortuoso corteza externa\n     exfoliable de color rojizo, ramificación abundante y copa irregular.\n\n     Hojas: Simples, opuestas, lámina de forma ovalada a elíptica de 2 a 6 cm de largo por 1,5 a\n     3,5 cm de ancho, margen entero, ápice agudo y base redondeada, haz verde lustroso, envés\n     verde amarillento, tienen puntos con aceites esenciales.\n\n     Flores: Reunidas en dicasios de 2,5 a 3,5 cm de largo, dispuestos en las ramitas y axilas de las\n     hojas. Flores bisexuales, regulares; cáliz dialisépalo de color verde; corola conformada por\n     4 pétalos blancos redondeados y caducos; androceo con numerosos estambres de color\n     blanco de 0,8 a 1 cm de largo. Ovario ínfero con un largo estilo y estigma capitado.\n\n     Fruto: Baya globosa y carnosa de 0,5 a 1 cm de diámetro, de color rojo oscuro al madurar.\n\n     Distribución y ecología: Esta especie se encuentra en la región andina del Ecuador entre\n     1500 y 3800 m de altitud, constituye una especie abundante en la vegetación ribereña del\n     río Mazán, en donde los árboles adquieren un crecimiento horizontal con fuertes raíces que\n     protegen los taludes (Serrano, 1996). En las riberas del río Yanuncay también su presencia es\n     importante en taludes bien conservados, notándose su crecimiento inclinado hacia el río.\n     Sus frutos son importantes para muchas especies de aves.\n\n     Usos tradicionales: Sus frutos son comestibles y se emplean para elaborar la tradicional co-\n     lada morada (Loján, 1992). Su madera de color rosado es dura y de buena calidad, por lo cual\n     se emplean para fabricar muebles, también en construcción como vigas, tablas y pilares\n     (Loján 1992). En medicina tradicional, sus hojas masticadas se emplea para contrarrestar las\n     caries (Serrano, 1996). En la provincia de Imbabura, sus hojas son empleadas en repostería\n     para dar sabor y como aromatizantes en bebidas (De la Torre et al, 2008).\n\n     Propagación: Se propaga mediante semillas, para lo cual se recomienda remojar los frutos\n     durante 24 horas, para facilitar la extracción de las semillas y luego sembrarla en almácigos\n     con sustratos húmedos para facilitar su desarrollo (Serrano, 1996). Para algunas especies\n     de arrayán se recomienda secar las semillas durante 15 días, con lo cual se obtiene un alto\n     porcentaje de germinación (Loján, 1992).\n\n     Vegetativamente se puede propagar mediante estacas de 15 cm de largo y 2 a 3 cm de\n     diámetro que contengan al menos tres yemas (Loján, 1992). También se pueden obtener\n     plántulas a partir de rebrotes o macollas (hijuelos), de la base del tronco, que deben ser\n     extraídas con algo de tierra (Reynel y León, 1990).\n","familia":"Myrtaceae\n","nombre":"Huahual","descripcíon":"","otros_nombres_comunes":["arrayán"],"nombre_cientifica":"Myrcianthes rhopaloides (Kunth) McVaugh","habito":" Árbol, crece hasta los 15 m de altura, tronco cilíndrico, tortuoso corteza externa\n     exfoliable de color rojizo, ramificación abundante y copa irregular.","hojas":"Simples, opuestas, lámina de forma ovalada a elíptica de 2 a 6 cm de largo por 1,5 a\n     3,5 cm de ancho, margen entero, ápice agudo y base redondeada, haz verde lustroso, envés\n     verde amarillento, tienen puntos con aceites esenciales.","flores":"Reunidas en dicasios de 2,5 a 3,5 cm de largo, dispuestos en las ramitas y axilas de las\n     hojas. Flores bisexuales, regulares; cáliz dialisépalo de color verde; corola conformada por\n     4 pétalos blancos redondeados y caducos; androceo con numerosos estambres de color\n     blanco de 0,8 a 1 cm de largo. Ovario ínfero con un largo estilo y estigma capitado.","fruta":"Baya globosa y carnosa de 0,5 a 1 cm de diámetro, de color rojo oscuro al madurar.","distribucion_y_ecologia":"Esta especie se encuentra en la región andina del Ecuador entre\n     1500 y 3800 m de altitud, constituye una especie abundante en la vegetación ribereña del\n     río Mazán, en donde los árboles adquieren un crecimiento horizontal con fuertes raíces que\n     protegen los taludes (Serrano, 1996). En las riberas del río Yanuncay también su presencia es\n     importante en taludes bien conservados, notándose su crecimiento inclinado hacia el río.\n     Sus frutos son importantes para muchas especies de aves.","usos_tradicionales":"Sus frutos son comestibles y se emplean para elaborar la tradicional co-\n     lada morada (Loján, 1992). Su madera de color rosado es dura y de buena calidad, por lo cual\n     se emplean para fabricar muebles, también en construcción como vigas, tablas y pilares\n     (Loján 1992). En medicina tradicional, sus hojas masticadas se emplea para contrarrestar las\n     caries (Serrano, 1996). En la provincia de Imbabura, sus hojas son empleadas en repostería\n     para dar sabor y como aromatizantes en bebidas (De la Torre et al, 2008).","propagacion":"Se propaga mediante semillas, para lo cual se recomienda remojar los frutos\n     durante 24 horas, para facilitar la extracción de las semillas y luego sembrarla en almácigos\n     con sustratos húmedos para facilitar su desarrollo (Serrano, 1996). Para algunas especies\n     de arrayán se recomienda secar las semillas durante 15 días, con lo cual se obtiene un alto\n     porcentaje de germinación (Loján, 1992).\n\n     Vegetativamente se puede propagar mediante estacas de 15 cm de largo y 2 a 3 cm de\n     diámetro que contengan al menos tres yemas (Loján, 1992). También se pueden obtener\n     plántulas a partir de rebrotes o macollas (hijuelos), de la base del tronco, que deben ser\n     extraídas con algo de tierra (Reynel y León, 1990).","images":["/resources/img/arboles-65_0.jpg","/resources/img/arboles-65_1.jpg","/resources/img/arboles-65_2.jpg","/resources/img/arboles-65_3.jpg"],"slug":"huahual"},{"page":66,"original":"66   ÁRBOLES NATIVOS\n\n\n\n\n                                 Familia: Phyllanthaceae\n                                            Cedrillo\n\n                             Nombre científico: Phyllanthus salviifolius Kunth\n                       Otros nombres comunes: “huañamín”, “yuquilla”\n\n\n     Hábito: Arbusto o árbol pequeño de 5 a 10 m de altura y 15 a 20 cm de DAP. Tronco cilíndri-\n     co, de corteza externa lisa, ramificación alterna y copa amplia globosa.\n\n     Hojas: Simples, alternas, de textura suave, con una lámina oblongo-lanceolada de 3,5 a 9\n     cm de largo por 2 a 5 de ancho, margen entero, base truncada y ápice agudo o acuminado;\n     nervadura secundaria paralela y marcada en el envés. Haz esparcidamente puberulento,\n     envés densamente pubescente.\n\n     Flores: Pequeñas, unisexuales. Planta monoica. Flores masculinas de 2 a 3 mm de diámetro,\n     dispuestas en pequeños fascículos axilares, provistos de 5 sépalos de color verde y 5 estam-\n     bres, disco anular con 3 glándulas. Flores femeninas solitarias, con un perianto en forma\n     de copa de color verde o crema rojizo; ovario con 3 lóculos, estilos fusionados, estigmas\n     hinchados.\n\n     Fruto: Cápsula loculicida de 3 a 4 mm de diámetro, dehiscente por 3 valvas y rodeada por el\n     cáliz persistente; semillas angulares y duras 2 por cada lóculo.\n\n     Distribución y ecología: Especie nativa, de amplia distribución en Costa Rica, Venezuela,\n     Colombia, Ecuador y Perú. En nuestro país se distribuye en la región andina entre 1800 y\n     3100 m de altitud (Jaramillo, 2013). Crece en los valles interandinos y bosques montanos, es\n     común encontrarla en bosques intervenidos y márgenes de quebradas y ríos. Se establece\n     bien en sitios abiertos con suelos sueltos. Aunque en sus primeras etapas tolera la sombra,\n     necesita de luz directa para florecer y fructificar. En los márgenes de los ríos de Cuenca, en\n     la actualidad es una especie rara registrándose alrededor de unos 10 individuos dentro de\n     la zona urbana de la ciudad.\n\n     Usos tradicionales: Esta especie ha sido cultivada como ornamental en los valles interan-\n     dinos del Ecuador. Los Saraguros lo emplean como barbasco para pescar (León-Yánez &\n     Ayala, 2007). Sus ramas son empleadas para cubrir los techos de las chozas y como cerca\n     viva (Jaramillo, 2013).\n","familia":"Phyllanthaceae\n","nombre":"Cedrillo","descripcíon":"","otros_nombres_comunes":["huañamín","yuquilla"],"nombre_cientifica":"Phyllanthus salviifolius Kunth","habito":" Arbusto o árbol pequeño de 5 a 10 m de altura y 15 a 20 cm de DAP. Tronco cilíndri-\n     co, de corteza externa lisa, ramificación alterna y copa amplia globosa.","hojas":"Simples, alternas, de textura suave, con una lámina oblongo-lanceolada de 3,5 a 9\n     cm de largo por 2 a 5 de ancho, margen entero, base truncada y ápice agudo o acuminado;\n     nervadura secundaria paralela y marcada en el envés. Haz esparcidamente puberulento,\n     envés densamente pubescente.","flores":"Pequeñas, unisexuales. Planta monoica. Flores masculinas de 2 a 3 mm de diámetro,\n     dispuestas en pequeños fascículos axilares, provistos de 5 sépalos de color verde y 5 estam-\n     bres, disco anular con 3 glándulas. Flores femeninas solitarias, con un perianto en forma\n     de copa de color verde o crema rojizo; ovario con 3 lóculos, estilos fusionados, estigmas\n     hinchados.","fruta":"Cápsula loculicida de 3 a 4 mm de diámetro, dehiscente por 3 valvas y rodeada por el\n     cáliz persistente; semillas angulares y duras 2 por cada lóculo.","distribucion_y_ecologia":"Especie nativa, de amplia distribución en Costa Rica, Venezuela,\n     Colombia, Ecuador y Perú. En nuestro país se distribuye en la región andina entre 1800 y\n     3100 m de altitud (Jaramillo, 2013). Crece en los valles interandinos y bosques montanos, es\n     común encontrarla en bosques intervenidos y márgenes de quebradas y ríos. Se establece\n     bien en sitios abiertos con suelos sueltos. Aunque en sus primeras etapas tolera la sombra,\n     necesita de luz directa para florecer y fructificar. En los márgenes de los ríos de Cuenca, en\n     la actualidad es una especie rara registrándose alrededor de unos 10 individuos dentro de\n     la zona urbana de la ciudad.","usos_tradicionales":"Esta especie ha sido cultivada como ornamental en los valles interan-\n     dinos del Ecuador. Los Saraguros lo emplean como barbasco para pescar (León-Yánez &\n     Ayala, 2007). Sus ramas son empleadas para cubrir los techos de las chozas y como cerca\n     viva (Jaramillo, 2013).","propagacion":"","images":["/resources/img/arboles-67_0.jpg","/resources/img/arboles-67_1.jpg","/resources/img/arboles-67_2.jpg","/resources/img/arboles-67_3.jpg"],"slug":"cedrillo"},{"page":68,"original":"68   ÁRBOLES NATIVOS\n\n\n\n\n                                 Familia: Podocarpaceae\n                                           Guabisay\n\n                             Nombre científico: Podocarpus sprucei Parl\n                       Otros nombres comunes: “romerillo”, “sisín”, “azuceno”\n\n\n     Hábito: Árbol de 10 a 15 m de altura y 20 a 40 cm de DAP. Tronco recto, corteza externa\n     fisurada de café a gris, copa plana y ramificación densa.\n\n     Hojas: Simples, enteras, duras, arregladas en espiral en las ramitas, lámina linear lanceolada\n     de 1,8 a 3,5 cm de largo por 0,2 a 0,4 cm de ancho, margen entero, base cuneada y ápice\n     agudo.\n\n     Flores: Unisexuales, plantas dioicas. Flores masculinas dispuestas en conos sobre las ramitas\n     laterales. Flores femeninas dispuestas en conos axilares y sobre un corto pedúnculo.\n\n     Fruto: Drupa de esférica a ligeramente elipsoide, de 5 a 7 mm de largo por 4 a 6 mm de\n     ancho, de color verde oliva, sostenida por un receptáculo carnoso.\n\n     Distribución y ecología: Especie nativa de los Andes, común en las montañas andinas del\n     norte del Perú y sur del Ecuador; crece entre 2000 y 3000 m de altitud. Se adapta muy bien a\n     una gran variedad de suelos y es moderadamente resistente a la sequía; presenta una buena\n     capacidad de rebrote y su regeneración natural es muy buena particularmente en terrenos\n     arenosos. En los márgenes de los ríos de Cuenca es una especie común en la zona alta de los\n     ríos Yanuncay y Tomebamba.\n\n     Usos tradicionales: Sus hojas en infusión se emplean en baños de asiento y para aliviar res-\n     friados (León-Yánez & Ayala, 2007). Su madera es de buena calidad y se usa para construc-\n     ciones como pilares, vigas y para la elaboración de muebles, arados, yugos y cabos de he-\n     rramientas manuales. En algunas comunidades indígenas de las provincias de Tungurahua,\n     Chimborazo y Cañar, se cree que es protector contra los espíritus y junto al ciprés y sauce se\n     emplea para adornar los altares en época de navidad y semana santa (De la Torre et al, 2008).\n\n     Propagación: Se propaga mediante semillas, para el efecto, la recolección de frutos debe\n     hacerse cuando éstos estén maduros (color verde oscuro o café) y luego deben secarse al\n     sol durante tres días (Sánchez, 2000). Para obtener una buena germinación se recomienda\n     usar un sustrato compuesto por tierra negra, humus y suelo con micorrizas obtenida bajo\n     los árboles de guabisay. La semilla debe ser cubierta con una capa fina de tierra y el almáci-\n     go debe ser cubierto con paja. También se recomienda plástico de invernadero en forma de\n     túnel para acelerar el proceso de germinación, la cual inicia alrededor de los 20 días después\n     de la siembra (Sánchez, 2000).\n","familia":"Podocarpaceae\n","nombre":"Guabisay","descripcíon":"","otros_nombres_comunes":["romerillo","sisín","azuceno"],"nombre_cientifica":"Podocarpus sprucei Parl","habito":" Árbol de 10 a 15 m de altura y 20 a 40 cm de DAP. Tronco recto, corteza externa\n     fisurada de café a gris, copa plana y ramificación densa.","hojas":"Simples, enteras, duras, arregladas en espiral en las ramitas, lámina linear lanceolada\n     de 1,8 a 3,5 cm de largo por 0,2 a 0,4 cm de ancho, margen entero, base cuneada y ápice\n     agudo.","flores":"Unisexuales, plantas dioicas. Flores masculinas dispuestas en conos sobre las ramitas\n     laterales. Flores femeninas dispuestas en conos axilares y sobre un corto pedúnculo.","fruta":"Drupa de esférica a ligeramente elipsoide, de 5 a 7 mm de largo por 4 a 6 mm de\n     ancho, de color verde oliva, sostenida por un receptáculo carnoso.","distribucion_y_ecologia":"Especie nativa de los Andes, común en las montañas andinas del\n     norte del Perú y sur del Ecuador; crece entre 2000 y 3000 m de altitud. Se adapta muy bien a\n     una gran variedad de suelos y es moderadamente resistente a la sequía; presenta una buena\n     capacidad de rebrote y su regeneración natural es muy buena particularmente en terrenos\n     arenosos. En los márgenes de los ríos de Cuenca es una especie común en la zona alta de los\n     ríos Yanuncay y Tomebamba.","usos_tradicionales":"Sus hojas en infusión se emplean en baños de asiento y para aliviar res-\n     friados (León-Yánez & Ayala, 2007). Su madera es de buena calidad y se usa para construc-\n     ciones como pilares, vigas y para la elaboración de muebles, arados, yugos y cabos de he-\n     rramientas manuales. En algunas comunidades indígenas de las provincias de Tungurahua,\n     Chimborazo y Cañar, se cree que es protector contra los espíritus y junto al ciprés y sauce se\n     emplea para adornar los altares en época de navidad y semana santa (De la Torre et al, 2008).","propagacion":"Se propaga mediante semillas, para el efecto, la recolección de frutos debe\n     hacerse cuando éstos estén maduros (color verde oscuro o café) y luego deben secarse al\n     sol durante tres días (Sánchez, 2000). Para obtener una buena germinación se recomienda\n     usar un sustrato compuesto por tierra negra, humus y suelo con micorrizas obtenida bajo\n     los árboles de guabisay. La semilla debe ser cubierta con una capa fina de tierra y el almáci-\n     go debe ser cubierto con paja. También se recomienda plástico de invernadero en forma de\n     túnel para acelerar el proceso de germinación, la cual inicia alrededor de los 20 días después\n     de la siembra (Sánchez, 2000).","images":["/resources/img/arboles-69_0.jpg","/resources/img/arboles-69_1.jpg","/resources/img/arboles-69_2.jpg","/resources/img/arboles-69_3.jpg"],"slug":"guabisay"},{"page":70,"original":"70   ÁRBOLES NATIVOS\n\n\n\n\n                                  Familia: Primulaceae\n                                             Yubar\n\n                             Nombre científico: Myrsine andina (Mez) Pipoly\n                       Otros nombres comunes: “samal”\n\n     Hábito: Árbol de 8 a 12 m de altura y 15 a 20 cm de DAP. Tronco cilíndrico o frecuentemente\n     retorcido, ramificación alterna, copa densa irregular, ramificación alterna que inicia desde\n     cerca del suelo, corteza externa lisa de color gris.\n\n     Hojas: Simples alternas, lámina de forma elíptica obovada de 3 a 3,5 cm de largo por 1,4 a\n     1,8 cm de ancho, margen entero, ápice redondeado y base atenuada, a veces ligeramente\n     involuto; haz verde oscuro brillante, envés glabro con puntuaciones glandulares.\n\n     Flores: Reunidas en pequeños fascículos axilares de 0,3 a 0,5 cm de largo. Flores unisexua-\n     les, sésiles de 0,5 cm de diámetro; cáliz compuesto por 5 sépalos, glandulares unidos en la\n     base; corola con 5 pétalos imbricados de color verde cremoso; androceo conformado por\n     5 estambres insertos en un tubo corolino, anteras grandes con dehiscencia longitudinal.\n     Ovario súpero unilocular, estigma sésil.\n\n     Fruto: Pequeña drupa punteado-glandular seca, esférica (0,3-0,4 mm de diámetro) provista\n     de una sola semilla.\n\n     Distribución y ecología: Especie nativa de amplia distribución en la región andina del Ecua-\n     dor; crece entre 2000 y 4000 m de altitud. Es frecuente en el subpáramo y en los márgenes\n     de ríos y quebradas. Varias especies de aves silvestres consumen sus frutos y posiblemente\n     son agentes dispersores.\n\n     Se establece en sitios abiertos, como potreros y bordes de bosque; prefiere suelos bien dre-\n     nados y profundos, pero se adapta a suelos pobres, pedregosos y arcillosos (Loján, 1992).\n     Presenta una buena capacidad de rebrote y su regeneración natural es buena (Minga, 2000).\n     Se han encontrado individuos de esta especie en los márgenes de los ríos Tomebamba,\n     Machángara, Yanuncay y Tarqui.\n\n     Usos tradicionales: En medicina tradicional campesina sus hojas cocinadas sirven para pre-\n     parar baños calientes que se aplican a mujeres cinco días después del parto (CESA, 1993).\n     En Saraguro lo emplean para combatir granos y salpullidos, mediante la preparación de\n     cataplasmas o emplastos (Elleman, 1990). Antiguamente su madera era empleada para la\n     construcción de pequeñas viviendas, pero en la actualidad se la usa solamente para leña y\n     postes.\n\n     Propagación: Se puede propagar mediante semillas, para lo cual es necesario recolectar los\n     frutos cuando éstos muestren un color verde amarillento, debido a que los frutos viejos de\n     color café que permanecen adheridos a los tallos contienen semillas que no germinan. Para\n     obtener un buen porcentaje de germinación, las semillas deben ser estratificadas, a fin de\n     acelerar el proceso, caso contrario la germinación puede tardar seis meses.\n","familia":"Primulaceae\n","nombre":"Yubar","descripcíon":"","otros_nombres_comunes":["samal"],"nombre_cientifica":"Myrsine andina (Mez) Pipoly","habito":" Árbol de 8 a 12 m de altura y 15 a 20 cm de DAP. Tronco cilíndrico o frecuentemente\n     retorcido, ramificación alterna, copa densa irregular, ramificación alterna que inicia desde\n     cerca del suelo, corteza externa lisa de color gris.","hojas":"Simples alternas, lámina de forma elíptica obovada de 3 a 3,5 cm de largo por 1,4 a\n     1,8 cm de ancho, margen entero, ápice redondeado y base atenuada, a veces ligeramente\n     involuto; haz verde oscuro brillante, envés glabro con puntuaciones glandulares.","flores":"Reunidas en pequeños fascículos axilares de 0,3 a 0,5 cm de largo. Flores unisexua-\n     les, sésiles de 0,5 cm de diámetro; cáliz compuesto por 5 sépalos, glandulares unidos en la\n     base; corola con 5 pétalos imbricados de color verde cremoso; androceo conformado por\n     5 estambres insertos en un tubo corolino, anteras grandes con dehiscencia longitudinal.\n     Ovario súpero unilocular, estigma sésil.","fruta":"Pequeña drupa punteado-glandular seca, esférica (0,3-0,4 mm de diámetro) provista\n     de una sola semilla.","distribucion_y_ecologia":"Especie nativa de amplia distribución en la región andina del Ecua-\n     dor; crece entre 2000 y 4000 m de altitud. Es frecuente en el subpáramo y en los márgenes\n     de ríos y quebradas. Varias especies de aves silvestres consumen sus frutos y posiblemente\n     son agentes dispersores.","usos_tradicionales":"En medicina tradicional campesina sus hojas cocinadas sirven para pre-\n     parar baños calientes que se aplican a mujeres cinco días después del parto (CESA, 1993).\n     En Saraguro lo emplean para combatir granos y salpullidos, mediante la preparación de\n     cataplasmas o emplastos (Elleman, 1990). Antiguamente su madera era empleada para la\n     construcción de pequeñas viviendas, pero en la actualidad se la usa solamente para leña y\n     postes.","propagacion":"Se puede propagar mediante semillas, para lo cual es necesario recolectar los\n     frutos cuando éstos muestren un color verde amarillento, debido a que los frutos viejos de\n     color café que permanecen adheridos a los tallos contienen semillas que no germinan. Para\n     obtener un buen porcentaje de germinación, las semillas deben ser estratificadas, a fin de\n     acelerar el proceso, caso contrario la germinación puede tardar seis meses.","images":["/resources/img/arboles-71_0.jpg","/resources/img/arboles-71_1.jpg","/resources/img/arboles-71_2.jpg","/resources/img/arboles-71_3.jpg"],"slug":"yubar"},{"page":72,"original":"72   ÁRBOLES NATIVOS\n\n\n\n\n                                   Familia: Primulaceae\n                                             Zhiripe\n\n                         Nombre científico: Myrsine dependens (Ruiz & Pav.) Spreng\n                 Otros nombres comunes: “samal”, “yubar pequeño”\n\n\n     Hábito: Arbusto o árbol pequeño de 4 a 10 m de altura y 10 a 30 cm de DAP. Tronco tortuoso,\n     ramificación alterna y copa irregular.\n\n     Hojas: Simples, alternas; lámina de elíptica a ovada de 1,2 a 1,8 cm de largo por 0,8 a 1,2 cm\n     de ancho, margen entero e involuto, ápice acuminado y base de obtusa a redondeada. Haz\n     verde claro, algo lustroso, envés verde amarillento con puntos glandulares.\n\n     Flores: Unisexuales pequeñas de 0,3 a 0,4 cm de diámetro, densamente agrupadas en fascí-\n     culos axilares; corola conformada por 5 pétalos de color verde cremoso con puntos glandu-\n     lares en el ápice; androceo conformado por 5 estambres y gineceos con un ovario súpero.\n\n     Fruto: Drupa globosa de 0,3 a 0,5 cm de diámetro, de color púrpura obscuro cuando está\n     madura.\n\n     Distribución y ecología: Especie nativa de amplia distribución en Costa Rica, Venezuela, Co-\n     lombia, Ecuador, Perú y Bolivia. En nuestro país es una especie frecuente en subpáramos y\n     en bosques altoandinos, cubriendo un intervalo altitudinal entre 2500 y 4000 m. Crece bien\n     en suelos pedregosos, presenta una buena capacidad de rebrote y una buena regeneración\n     natural.\n\n     Usos tradicionales: En algunas comunidades campesinas de las provincias de Azuay y Ca-\n     ñar sus hojas y ramas en decocción se emplean para los denominados baños del post parto\n     y sus hojas sirven para aliviar cólicos. Su madera se emplea en la elaboración de diversas\n     artesanías como arados, cabos, caballetes, bateas y para preparar carbón (De la Torre et al,\n     2008). En algunas comunidades de Cañar y Chimborazo sus hojas se usan para alimento de\n     animales (De la Torre et al, 2008).\n","familia":"Primulaceae\n","nombre":"Zhiripe","descripcíon":"","otros_nombres_comunes":["samal","yubar pequeño"],"nombre_cientifica":"Myrsine dependens (Ruiz & Pav.) Spreng","habito":" Arbusto o árbol pequeño de 4 a 10 m de altura y 10 a 30 cm de DAP. Tronco tortuoso,\n     ramificación alterna y copa irregular.","hojas":"Simples, alternas; lámina de elíptica a ovada de 1,2 a 1,8 cm de largo por 0,8 a 1,2 cm\n     de ancho, margen entero e involuto, ápice acuminado y base de obtusa a redondeada. Haz\n     verde claro, algo lustroso, envés verde amarillento con puntos glandulares.","flores":"Unisexuales pequeñas de 0,3 a 0,4 cm de diámetro, densamente agrupadas en fascí-\n     culos axilares; corola conformada por 5 pétalos de color verde cremoso con puntos glandu-\n     lares en el ápice; androceo conformado por 5 estambres y gineceos con un ovario súpero.","fruta":"Drupa globosa de 0,3 a 0,5 cm de diámetro, de color púrpura obscuro cuando está\n     madura.","distribucion_y_ecologia":"Especie nativa de amplia distribución en Costa Rica, Venezuela, Co-\n     lombia, Ecuador, Perú y Bolivia. En nuestro país es una especie frecuente en subpáramos y\n     en bosques altoandinos, cubriendo un intervalo altitudinal entre 2500 y 4000 m. Crece bien\n     en suelos pedregosos, presenta una buena capacidad de rebrote y una buena regeneración\n     natural.","usos_tradicionales":"En algunas comunidades campesinas de las provincias de Azuay y Ca-\n     ñar sus hojas y ramas en decocción se emplean para los denominados baños del post parto\n     y sus hojas sirven para aliviar cólicos. Su madera se emplea en la elaboración de diversas\n     artesanías como arados, cabos, caballetes, bateas y para preparar carbón (De la Torre et al,\n     2008). En algunas comunidades de Cañar y Chimborazo sus hojas se usan para alimento de\n     animales (De la Torre et al, 2008).","propagacion":"","images":["/resources/img/arboles-73_0.jpg","/resources/img/arboles-73_1.jpg","/resources/img/arboles-73_2.jpg"],"slug":"zhiripe"},{"page":74,"original":"74   ÁRBOLES NATIVOS\n\n\n\n\n                                    Familia: Proteaceae\n                                              Gañal\n\n                              Nombre científico: Oreocallis grandiflora (Lam.) R. Br.\n                       Otros nombres comunes: “cucharillo”, “galuay”, “chilla”, “boldo”\n\n\n     Hábito: Arbusto o árbol pequeño hasta de 10 m de altura, tronco cilíndrico, corteza externa\n     café a veces con lenticelas, ramificación alterna y copa irregular, ramitas terminales pubes-\n     centes ferruginosas.\n\n     Hojas: Simples, alternas de textura coriácea; lámina de elíptica a obovada de 13 a 6,5 cm de\n     largo por 6 a 2,5 cm de ancho, margen entero revoluto, base cuneada y ápice redondeado\n     a emarginado. Haz glabro verde lustroso, envés verde claro con pubescencia ferruginosa en\n     hojas tiernas.\n\n     Flores: Reunidas en inflorescencias ampliamente piramidales de 8 a 12 cm de largo, frecuen-\n     temente tomentosa ferruginosa. Flores de 4 a 7 cm de largo de color blanco o rosado. Pe-\n     rianto de color verde o blanco, compuesto por 4 segmentos fusionados en un tubo estrecho\n     con 4 valvas terminales y en cada una inserta una antera subsésil. Ovario súpero estipitado.\n\n     Fruto: Folículo oblongo de 5 a 6 cm de largo, con el estilo y estigma persistente. Cada fruto\n     contiene alrededor de 30 semillas provistas de alas.\n\n     Distribución y ecología: Especie nativa que crece en bosques montanos y páramos del\n     norte del Perú y sur del Ecuador entre 1400 y 3600 m de altitud. Crece en suelos ácidos y\n     poco profundos, es frecuente en bosques secundarios y vegetación arbustiva. Es una espe-\n     cie ecológicamente importante ya que sirve de alimento para muchas especies de colibríes\n     nativos y endémicos como Coeligena iris, Heliangelus viola, Metallura tryanthina, entre otros.\n\n     Usos tradicionales: Comúnmente sus flores mezcladas con toronjil y manzanilla, se emplea\n     para preparar la bebida tradicional conocida como horchata (León-Yánez & Ayala, 2007). En\n     los mercados de Cuenca se recetan sus flores en infusión para desinflamar riñones e hígado\n     y sus hojas se emplean para aliviar afeccionas de las vías urinarias. En algunas comunidades\n     de la provincia de El Oro, con sus hojas y flores se hacen preparaciones que se administran a\n     personas que no pueden orinar o defecar (Bonifaz & Cornejo, 2002). Su madera es empleada\n     para la elaboración de artesanías y herramientas manuales como arados, chicotes, yugos y\n     cabos (De la Torre et al, 2008).\n\n     Propagación: Se recomienda propagar mediante semillas, para lo cual se deben recolectar\n     los frutos maduros (verde amarillentos), secarlos al sol para que se abran y luego recoger\n     las semillas. Para acelerar el proceso de germinación se recomienda remojar las semillas\n     durante 48 horas antes de efectuar el almácigo. La germinación mejora si se emplea un sus-\n     trato elaborado con el suelo de los alrededores de plantas de gañal, pues estos contienen\n     micorrizas (Serrano, 1996).\n","familia":"Proteaceae\n","nombre":"Gañal","descripcíon":"","otros_nombres_comunes":["cucharillo","galuay","chilla","boldo"],"nombre_cientifica":"Oreocallis grandiflora (Lam.) R. Br.","habito":" Arbusto o árbol pequeño hasta de 10 m de altura, tronco cilíndrico, corteza externa\n     café a veces con lenticelas, ramificación alterna y copa irregular, ramitas terminales pubes-\n     centes ferruginosas.","hojas":"Simples, alternas de textura coriácea; lámina de elíptica a obovada de 13 a 6,5 cm de\n     largo por 6 a 2,5 cm de ancho, margen entero revoluto, base cuneada y ápice redondeado\n     a emarginado. Haz glabro verde lustroso, envés verde claro con pubescencia ferruginosa en\n     hojas tiernas.","flores":"Reunidas en inflorescencias ampliamente piramidales de 8 a 12 cm de largo, frecuen-\n     temente tomentosa ferruginosa. Flores de 4 a 7 cm de largo de color blanco o rosado. Pe-\n     rianto de color verde o blanco, compuesto por 4 segmentos fusionados en un tubo estrecho\n     con 4 valvas terminales y en cada una inserta una antera subsésil. Ovario súpero estipitado.","fruta":"Folículo oblongo de 5 a 6 cm de largo, con el estilo y estigma persistente. Cada fruto\n     contiene alrededor de 30 semillas provistas de alas.","distribucion_y_ecologia":"Especie nativa que crece en bosques montanos y páramos del\n     norte del Perú y sur del Ecuador entre 1400 y 3600 m de altitud. Crece en suelos ácidos y\n     poco profundos, es frecuente en bosques secundarios y vegetación arbustiva. Es una espe-\n     cie ecológicamente importante ya que sirve de alimento para muchas especies de colibríes\n     nativos y endémicos como Coeligena iris, Heliangelus viola, Metallura tryanthina, entre otros.","usos_tradicionales":"Comúnmente sus flores mezcladas con toronjil y manzanilla, se emplea\n     para preparar la bebida tradicional conocida como horchata (León-Yánez & Ayala, 2007). En\n     los mercados de Cuenca se recetan sus flores en infusión para desinflamar riñones e hígado\n     y sus hojas se emplean para aliviar afeccionas de las vías urinarias. En algunas comunidades\n     de la provincia de El Oro, con sus hojas y flores se hacen preparaciones que se administran a\n     personas que no pueden orinar o defecar (Bonifaz & Cornejo, 2002). Su madera es empleada\n     para la elaboración de artesanías y herramientas manuales como arados, chicotes, yugos y\n     cabos (De la Torre et al, 2008).","propagacion":"Se recomienda propagar mediante semillas, para lo cual se deben recolectar\n     los frutos maduros (verde amarillentos), secarlos al sol para que se abran y luego recoger\n     las semillas. Para acelerar el proceso de germinación se recomienda remojar las semillas\n     durante 48 horas antes de efectuar el almácigo. La germinación mejora si se emplea un sus-\n     trato elaborado con el suelo de los alrededores de plantas de gañal, pues estos contienen\n     micorrizas (Serrano, 1996).","images":["/resources/img/arboles-75_0.jpg","/resources/img/arboles-75_1.jpg","/resources/img/arboles-75_2.jpg"],"slug":"gaal"},{"page":76,"original":"76   ÁRBOLES NATIVOS\n\n\n\n\n                                  Familia: Rhamnaceae\n                                        Aya rambrán\n\n                       Nombre científico: Rhamnus granulosa (Ruiz& Pav.) Weberb.\n                                          ex M.C. Johnst\n                Otros nombres comunes: “aliso blanco”\n\n\n     Hábito: Árbol pequeño de hasta 12 m de altura y 20 cm de DAP. Fuste recto, ramificación de\n     alterna a subopuesta, copa abierta, corteza externa lisa parda grisácea.\n\n     Hojas: Simples, alternas, de textura coriácea, lámina de forma elíptica u oblongo elíptica (6\n     a 12 x 3 a 6 cm), ápice de agudo a acuminado, base obtusa y margen aserrado; haz glabro\n     verde oscuro, envés puberulento verde claro.\n\n     Flores: Reunidas en cimas axilares de 2 a 3 cm de largo. Flores bisexuales, con un tubo flo-\n     ral en forma de copa, cáliz conformado por 5 sépalos de color verde, corola con 5 pétalos\n     cremosos; androceo con 5 estambres insertos en un disco nectarífero adnado al tubo floral;\n     ovario súpero con 3 lóculos.\n\n     Fruto: Drupa subglobosa de 0,5–0,8 cm de diámetro, de color rojo marrón cuando está ma-\n     dura.\n\n     Distribución y ecología: Se distribuye en la región andina de Colombia, Ecuador y Perú. En\n     nuestro país crece entre 500 y 3000 m de altitud, en bosques montanos húmedos. Es una\n     especie de bosque maduro, no presenta capacidad de rebrote y su regeneración natural\n     es limitada. En la región florece en los meses de julio y agosto y fructifica en noviembre y\n     diciembre. Sus frutos son consumidos por aves. En los márgenes de los ríos de Cuenca, es\n     una especie poco frecuente y restringida a remanentes de bosque maduro de la zona alta\n     de los ríos Yanuncay y Tomebamba.\n\n     Usos tradicionales: Su madera se emplea en encofrados para la construcción y en la elabo-\n     ración de marcos y ventanas (Cuamacás & Tipaz, 1995). En algunas comunidades de Imbabu-\n     ra su fruto se consume y en Loja se utiliza como cerca viva (De la Torre et al, 2008).\n\n     Propagación: Semillas, para lo cual se deben recolectar los frutos cuando presenten una\n     coloración rojiza.\n","familia":"Rhamnaceae\n","nombre":"Aya rambrán","descripcíon":"","otros_nombres_comunes":["aliso blanco"],"nombre_cientifica":"Rhamnus granulosa (Ruiz& Pav.) Weberb.\n                                          ex M.C. Johnst","habito":" Árbol pequeño de hasta 12 m de altura y 20 cm de DAP. Fuste recto, ramificación de\n     alterna a subopuesta, copa abierta, corteza externa lisa parda grisácea.","hojas":"Simples, alternas, de textura coriácea, lámina de forma elíptica u oblongo elíptica (6\n     a 12 x 3 a 6 cm), ápice de agudo a acuminado, base obtusa y margen aserrado; haz glabro\n     verde oscuro, envés puberulento verde claro.","flores":"Reunidas en cimas axilares de 2 a 3 cm de largo. Flores bisexuales, con un tubo flo-\n     ral en forma de copa, cáliz conformado por 5 sépalos de color verde, corola con 5 pétalos\n     cremosos; androceo con 5 estambres insertos en un disco nectarífero adnado al tubo floral;\n     ovario súpero con 3 lóculos.","fruta":"Drupa subglobosa de 0,5–0,8 cm de diámetro, de color rojo marrón cuando está ma-\n     dura.","distribucion_y_ecologia":"Se distribuye en la región andina de Colombia, Ecuador y Perú. En\n     nuestro país crece entre 500 y 3000 m de altitud, en bosques montanos húmedos. Es una\n     especie de bosque maduro, no presenta capacidad de rebrote y su regeneración natural\n     es limitada. En la región florece en los meses de julio y agosto y fructifica en noviembre y\n     diciembre. Sus frutos son consumidos por aves. En los márgenes de los ríos de Cuenca, es\n     una especie poco frecuente y restringida a remanentes de bosque maduro de la zona alta\n     de los ríos Yanuncay y Tomebamba.","usos_tradicionales":"Su madera se emplea en encofrados para la construcción y en la elabo-\n     ración de marcos y ventanas (Cuamacás & Tipaz, 1995). En algunas comunidades de Imbabu-\n     ra su fruto se consume y en Loja se utiliza como cerca viva (De la Torre et al, 2008).","propagacion":"Semillas, para lo cual se deben recolectar los frutos cuando presenten una\n     coloración rojiza.","images":["/resources/img/arboles-77_0.jpg","/resources/img/arboles-77_1.jpg","/resources/img/arboles-77_2.jpg"],"slug":"aya-rambrn"},{"page":78,"original":"78   ÁRBOLES NATIVOS\n\n\n\n\n                                      Familia: Rosaceae\n                                         Quinua roja\n\n                             Nombre científico: Polylepis incana Kunth\n                       Otros nombres comunes: “pantsa”, “yagual”\n\n\n     Hábito: Árbol de 4 hasta 12 m de altura. Tronco de 20 a 40 cm de diámetro, irregular nudo-\n     so y retorcido en forma de helicoide. Corteza externa rojiza, posee láminas membranosas,\n     exfoliables; ramificación densa y copa globosa e irregular.\n\n     Hojas: Compuestas, arregladas en espiral, provistas de estípulas expandidas que forman\n     una vaina a lo largo de la base del pecíolo; lámina trifoliada; folíolos de forma obovada de 1\n     a 2,5 cm de largo por 0,4 a 0,7 cm de ancho, margen crenado y ápice de obtuso a emargina-\n     do, haz verde brillante, envés pubescente resinoso de color verde amarillento.\n\n     Flores: Dispuestas en racimos simples de 2 a 8 cm de largo con 5 a 8 flores pequeñas de\n     0,5 cm de diámetro; flores bisexuales, apétalas, con un tubo floral en forma de copa y de 4\n     sépalos de color crema; androceo provisto de 6 a 15 estambres; ovario ínfero unilocular con\n     un estilo y un estigma fimbriado.\n\n     Fruto: Aquenio seco globoso provisto de una semilla de 2 a 3 mm de longitud.\n\n     Distribución y ecología:Se distribuye en los altos Andes de Colombia, Ecuador y Perú, entre\n     3000 y 4300 m de altitud (Romolerux, 1996). En nuestro país es una especie frecuente en los\n     páramos y subpáramos. Crece en suelos pobres de textura y naturaleza variable, se adapta\n     bien a suelos pedregosos y es resistente a la sequía. En los márgenes de los ríos de Cuenca,\n     crece en la zona alta del Yanuncay, es abundante en la zona de Soldados y junto a Polylepis\n     weberbaueri, es dominante en algunos sectores.\n\n     Usos tradicionales: Su madera tiene múltiples usos, se emplea para la construcción de vi-\n     viendas campesinas y corrales para animales; también en la elaboración de arados, cabos\n     para herramientas manuales y para artesanías como bateas y cucharas (De la Torre et al,\n     2008). Es una especie muy apreciada para la elaboración de carbón y para leña. En medicina\n     tradicional, la infusión de sus hojas se emplea para tratar gripes y para baños post parto, en\n     emplastos sirve para tratar fracturas (De la Torre et al, 2008).\n\n     Propagación: Se puede propagar mediante semillas, las mismas que deben ser recolectadas\n     cuando los frutos presentan un color café plomizo, antes de efectuar la siembra es necesario\n     remojarlas durante 72 horas (CESA, 1989). También se puede propagar mediante estolones,\n     que deben ser separados de las plantas madres cuando tengan por lo menos 15 cm de alto.\n","familia":"Rosaceae\n","nombre":"Quinua roja","descripcíon":"","otros_nombres_comunes":["pantsa","yagual"],"nombre_cientifica":"Polylepis incana Kunth","habito":" Árbol de 4 hasta 12 m de altura. Tronco de 20 a 40 cm de diámetro, irregular nudo-\n     so y retorcido en forma de helicoide. Corteza externa rojiza, posee láminas membranosas,\n     exfoliables; ramificación densa y copa globosa e irregular.","hojas":"Compuestas, arregladas en espiral, provistas de estípulas expandidas que forman\n     una vaina a lo largo de la base del pecíolo; lámina trifoliada; folíolos de forma obovada de 1\n     a 2,5 cm de largo por 0,4 a 0,7 cm de ancho, margen crenado y ápice de obtuso a emargina-\n     do, haz verde brillante, envés pubescente resinoso de color verde amarillento.","flores":"Dispuestas en racimos simples de 2 a 8 cm de largo con 5 a 8 flores pequeñas de\n     0,5 cm de diámetro; flores bisexuales, apétalas, con un tubo floral en forma de copa y de 4\n     sépalos de color crema; androceo provisto de 6 a 15 estambres; ovario ínfero unilocular con\n     un estilo y un estigma fimbriado.","fruta":"Aquenio seco globoso provisto de una semilla de 2 a 3 mm de longitud.","distribucion_y_ecologia":"Se distribuye en los altos Andes de Colombia, Ecuador y Perú, entre\n     3000 y 4300 m de altitud (Romolerux, 1996). En nuestro país es una especie frecuente en los\n     páramos y subpáramos. Crece en suelos pobres de textura y naturaleza variable, se adapta\n     bien a suelos pedregosos y es resistente a la sequía. En los márgenes de los ríos de Cuenca,\n     crece en la zona alta del Yanuncay, es abundante en la zona de Soldados y junto a Polylepis\n     weberbaueri, es dominante en algunos sectores.","usos_tradicionales":"Su madera tiene múltiples usos, se emplea para la construcción de vi-\n     viendas campesinas y corrales para animales; también en la elaboración de arados, cabos\n     para herramientas manuales y para artesanías como bateas y cucharas (De la Torre et al,\n     2008). Es una especie muy apreciada para la elaboración de carbón y para leña. En medicina\n     tradicional, la infusión de sus hojas se emplea para tratar gripes y para baños post parto, en\n     emplastos sirve para tratar fracturas (De la Torre et al, 2008).","propagacion":"Se puede propagar mediante semillas, las mismas que deben ser recolectadas\n     cuando los frutos presentan un color café plomizo, antes de efectuar la siembra es necesario\n     remojarlas durante 72 horas (CESA, 1989). También se puede propagar mediante estolones,\n     que deben ser separados de las plantas madres cuando tengan por lo menos 15 cm de alto.","images":["/resources/img/arboles-79_0.jpg","/resources/img/arboles-79_1.jpg","/resources/img/arboles-79_2.jpg"],"slug":"quinua-roja"},{"page":80,"original":"80   ÁRBOLES NATIVOS\n\n\n\n\n                                      Familia: Rosaceae\n                                      Quinua blanca\n\n                             Nombre científico: Polylepis weberbaueri Pilg.\n                       Otros nombres comunes: “pantsa”, “yagual”\n\n\n     Hábito: Arbusto o árbol de 4 a 12 m de altura y 20 a 30 cm de DAP. Tronco tortuoso con rami-\n     ficación alterna y copa irregular, corteza externa café, con láminas exfoliables. Se distingue\n     por su follaje verde oliváceo característico.\n\n     Hojas: Compuestas imparipinnadas, con 3 a 5 pares de folíolos, dispuestos en las ramitas\n     en forma helicoidal; folíolos de forma ovada, margen entero revoluto, ápice emarginado y\n     base subcordada, haz verde lustroso, envés densamente pubescente lanoso (panosa), con\n     tricomas glandulares de color rojo oscuro.\n\n     Flores: Reunidas en racimos de 4 a 8 cm de largo con 4 a 10 flores. Flores bisexuales de 4 a\n     6 cm de diámetro, con un tubo floral (hipanto) en forma de copa, 4 sépalos ovados seríceo-\n     lanosos en la cara interna; androceo con 6 a 12 estambres púrpuras; ovario ínfero con 4\n     lóculos, glabros ligeramente barbados, estilo viloso.\n\n     Fruto: Aquenio turbinado irregularmente espinado, de 3 a 5 mm, que contiene semillas de\n     2 a 3 mm.\n\n     Distribución y ecología: Es una especie nativa de bosques altoandinos y páramos de Ecua-\n     dor y norte del Perú. Localizada entre 3000 y 3700 m de altitud (Romoleroux, 1996). Crece\n     en lugares protegidos y riberas de ríos y quebradas. En los márgenes de los ríos de Cuenca\n     ha sido localizada en la zona alta del río Yanuncay, específicamente en el sector de Soldados\n     en donde crece formando pequeños manchones junto a Polylepis incana.\n\n     Usos tradicionales: Sus tallos sirven para elaborar carbón y su madera se emplea para la\n     construcción de pequeñas viviendas, para la confección de herramientas manuales, mue-\n     bles y artesanías como bateas, cucharas (De la Torre et al, 2008). Sus hojas en decocción se\n     usan en baños de parto y en infusión sirven para tratar la gripe, en emplastos se aplican para\n     aliviar fracturas (De la Torre et al, 2008).\n\n     Propagación: Se recomienda propagar mediante estolones, para lo cual las plantitas deben\n     ser separadas cuando alcancen una altura de 15 cm, también se puede propagar mediante\n     esquejes, para el efecto se recomienda seleccionar esquejes de 8 a 12 cm de largo.\n","familia":"Rosaceae\n","nombre":"Quinua blanca","descripcíon":"","otros_nombres_comunes":["pantsa","yagual"],"nombre_cientifica":"Polylepis weberbaueri Pilg.","habito":" Arbusto o árbol de 4 a 12 m de altura y 20 a 30 cm de DAP. Tronco tortuoso con rami-\n     ficación alterna y copa irregular, corteza externa café, con láminas exfoliables. Se distingue\n     por su follaje verde oliváceo característico.","hojas":"Compuestas imparipinnadas, con 3 a 5 pares de folíolos, dispuestos en las ramitas\n     en forma helicoidal; folíolos de forma ovada, margen entero revoluto, ápice emarginado y\n     base subcordada, haz verde lustroso, envés densamente pubescente lanoso (panosa), con\n     tricomas glandulares de color rojo oscuro.","flores":"Reunidas en racimos de 4 a 8 cm de largo con 4 a 10 flores. Flores bisexuales de 4 a\n     6 cm de diámetro, con un tubo floral (hipanto) en forma de copa, 4 sépalos ovados seríceo-\n     lanosos en la cara interna; androceo con 6 a 12 estambres púrpuras; ovario ínfero con 4\n     lóculos, glabros ligeramente barbados, estilo viloso.","fruta":"Aquenio turbinado irregularmente espinado, de 3 a 5 mm, que contiene semillas de\n     2 a 3 mm.","distribucion_y_ecologia":"Es una especie nativa de bosques altoandinos y páramos de Ecua-\n     dor y norte del Perú. Localizada entre 3000 y 3700 m de altitud (Romoleroux, 1996). Crece\n     en lugares protegidos y riberas de ríos y quebradas. En los márgenes de los ríos de Cuenca\n     ha sido localizada en la zona alta del río Yanuncay, específicamente en el sector de Soldados\n     en donde crece formando pequeños manchones junto a Polylepis incana.","usos_tradicionales":"Sus tallos sirven para elaborar carbón y su madera se emplea para la\n     construcción de pequeñas viviendas, para la confección de herramientas manuales, mue-\n     bles y artesanías como bateas, cucharas (De la Torre et al, 2008). Sus hojas en decocción se\n     usan en baños de parto y en infusión sirven para tratar la gripe, en emplastos se aplican para\n     aliviar fracturas (De la Torre et al, 2008).","propagacion":"Se recomienda propagar mediante estolones, para lo cual las plantitas deben\n     ser separadas cuando alcancen una altura de 15 cm, también se puede propagar mediante\n     esquejes, para el efecto se recomienda seleccionar esquejes de 8 a 12 cm de largo.","images":["/resources/img/arboles-81_0.jpg","/resources/img/arboles-81_1.jpg","/resources/img/arboles-81_2.jpg","/resources/img/arboles-81_3.jpg"],"slug":"quinua-blanca"},{"page":82,"original":"82   ÁRBOLES NATIVOS\n\n\n\n\n                                      Familia: Rosaceae\n                                            Pintador\n\n                             Nombre científico: Prunus opaca (Benth.) Walp.\n                       Otros nombres comunes: “laurel”, “cérrac negro”,\n                                              “capulí del monte”\n\n\n     Hábito: Árbol de 10 a 12 m de altura y 30 cm de DAP. Tronco irregular, ramificación alterna y\n     abundante, copa ondulada.\n\n     Hojas: Simples, alternas, duras, lámina de ovada a elíptica (5 a 10 x 2,5 a 6 cm), margen ente-\n     ro o ligeramente aserrado en hojas tiernas, base redondeada con dos glándulas, haz verde\n     lustroso, envés opaco.\n\n     Flores: Dispuestas en racimos axilares simples de 5 a 11 cm de longitud. Flores bisexuales\n     actinomorfas, tubo floral urceolado, cáliz constituido por 5 sépalos de forma triangular, co-\n     rola conformada por 5 pétalos obovados o suborbiculares de color blanco; androceo con 20\n     estambres dispuestos en dos verticilos; ovario con un carpelo, estigma discoide.\n\n     Fruto: Drupa esférica (1,5 cm de diámetro), de color púrpura obscuro cuando está madura.\n\n     Distribución y ecología: Especie localizada en la región andina del Ecuador, entre 1600 y\n     2900 m de altitud (Romolerux, 1996). Es una especie poco común en los bosques montanos\n     de la región, se lo encuentra generalmente en bosques primarios, no posee capacidad de\n     rebrote y su regeneración natural es muy escasa (Minga, 2000). En los bosques de ribera\n     de los ríos de Cuenca, es una especie rara restringida a sitios bien conservados con bosque\n     maduro, en las zonas altas de los ríos Yanuncay y Tomebamba.\n\n     Usos tradicionales: Su madera dura es empleada en la elaboración de herramientas manua-\n     les tales como: arados, yugos y cabos para hachas, picos y palas. Antiguamente su tronco se\n     empleaba en construcciones en forma de vigas, pilares, puertas y ventanas (Minga, 2000).\n\n     Propagación: Se puede propagar mediante semillas, las mismas que deben ser recolecta-\n     das cuando los frutos están maduros, de color púrpura. En la zona esto ocurre durante los\n     meses de julio y agosto. Luego de la recolección los frutos deben ser lavados y secados al\n     sol, con este procedimiento se ha obtenido alrededor de un 20 % de germinación.\n","familia":"Rosaceae\n","nombre":"Pintador","descripcíon":"","otros_nombres_comunes":["laurel","cérrac negro","capulí del monte"],"nombre_cientifica":"Prunus opaca (Benth.) Walp.","habito":" Árbol de 10 a 12 m de altura y 30 cm de DAP. Tronco irregular, ramificación alterna y\n     abundante, copa ondulada.","hojas":"Simples, alternas, duras, lámina de ovada a elíptica (5 a 10 x 2,5 a 6 cm), margen ente-\n     ro o ligeramente aserrado en hojas tiernas, base redondeada con dos glándulas, haz verde\n     lustroso, envés opaco.","flores":"Dispuestas en racimos axilares simples de 5 a 11 cm de longitud. Flores bisexuales\n     actinomorfas, tubo floral urceolado, cáliz constituido por 5 sépalos de forma triangular, co-\n     rola conformada por 5 pétalos obovados o suborbiculares de color blanco; androceo con 20\n     estambres dispuestos en dos verticilos; ovario con un carpelo, estigma discoide.","fruta":"Drupa esférica (1,5 cm de diámetro), de color púrpura obscuro cuando está madura.","distribucion_y_ecologia":"Especie localizada en la región andina del Ecuador, entre 1600 y\n     2900 m de altitud (Romolerux, 1996). Es una especie poco común en los bosques montanos\n     de la región, se lo encuentra generalmente en bosques primarios, no posee capacidad de\n     rebrote y su regeneración natural es muy escasa (Minga, 2000). En los bosques de ribera\n     de los ríos de Cuenca, es una especie rara restringida a sitios bien conservados con bosque\n     maduro, en las zonas altas de los ríos Yanuncay y Tomebamba.","usos_tradicionales":"Su madera dura es empleada en la elaboración de herramientas manua-\n     les tales como: arados, yugos y cabos para hachas, picos y palas. Antiguamente su tronco se\n     empleaba en construcciones en forma de vigas, pilares, puertas y ventanas (Minga, 2000).","propagacion":"Se puede propagar mediante semillas, las mismas que deben ser recolecta-\n     das cuando los frutos están maduros, de color púrpura. En la zona esto ocurre durante los\n     meses de julio y agosto. Luego de la recolección los frutos deben ser lavados y secados al\n     sol, con este procedimiento se ha obtenido alrededor de un 20 % de germinación.","images":["/resources/img/arboles-83_0.jpg","/resources/img/arboles-83_1.jpg","/resources/img/arboles-83_2.jpg","/resources/img/arboles-83_3.jpg"],"slug":"pintador"},{"page":84,"original":"84   ÁRBOLES NATIVOS\n\n\n\n\n                                      Familia: Rosaceae\n                                              Capulí\n\n                             Nombre científico: Prunus serotina Ehrh\n                       Otros nombres comunes: “usun”\n\n\n     Hábito: Árbol de 8 a 15 m de altura y 30 a 50 cm de DAP. Fuste ligeramente tortuoso, corteza\n     externa fisurada, ramificación alterna y copa globosa.\n\n     Hojas: Simples, alternas, lámina de lanceolada a oblongo-ovada, margen aserrado, ápice\n     acuminado y base de cuneada a obtusa, haz verde oscuro seríceo, envés verde opaco glau-\n     co.\n\n     Flores: Reunidas en racimos axilares o terminales de 5 a 20 cm de largo, que contienen entre\n     10 y 40 flores. Flores bisexuales, actinomorfas de 0,6 cm de diámetro, tubo floral urceolado,\n     cáliz conformado por 5 sépalos de forma triangular, corola con 5 pétalos blancos de forma\n     orbicular; androceo conformado por 20 estambres de 3 mm de largo; ovario ínfero pubes-\n     cente, estigma discoide.\n\n     Fruto: Drupa globosa de 12 a 20 mm de diámetro y color negro cuando madura. Semillas\n     esféricas, rodeadas por un endocarpio hueso leñoso.\n\n     Distribución y ecología: Prunus serotina subesp. capuli, es nativa de México y ha sido introdu-\n     cida en Sudamérica por sus frutos comestibles (Romolerux, 1996), no se sabe con exactitud\n     la época de su introducción, pero se presume que fue con la llegada de los españoles. En la\n     región andina ha sido ampliamente cultivado y naturalizado entre 2500 y 3500 m de altitud\n     (Romolerux, 1996). Esta especie se adapta a una gran variedad de suelos, pero se establece\n     mejor en suelos profundos y bien drenados, presenta una buena capacidad de rebrote y\n     una buena capacidad de regeneración. Especie pionera poco tolerante a la sombra, se esta-\n     blece en ambientes abiertos.\n\n     Usos tradicionales: Su madera es utilizada para cabezas de arado, postes, estacas, vigas y\n     umbrales de casas (De la Torre et al, 2008). Las hojas sirven como sustrato para germinar el\n     maíz previo a la elaboración de la chicha de jora. Sus frutos son comestibles y se emplean\n     en la elaboración de mermeladas y vinos, además constituyen un recurso importante para\n     la alimentación de aves silvestres.\n\n     Propagación: Se propaga mediante semillas, para lo cual es necesario remojarlas durante\n     tres días y secarlas al sol antes de ponerlas en el semillero. Otro tratamiento pre germinativo\n     consiste en estratificarlas al frío durante 120 días a temperaturas de 3 a 5 °C bajo cero. Un\n     método fácil para romper el letargo de las semillas es dejarlas a la intemperie durante 8 días\n     antes de sembrarlas.\n","familia":"Rosaceae\n","nombre":"Capulí","descripcíon":"","otros_nombres_comunes":["usun"],"nombre_cientifica":"Prunus serotina Ehrh","habito":" Árbol de 8 a 15 m de altura y 30 a 50 cm de DAP. Fuste ligeramente tortuoso, corteza\n     externa fisurada, ramificación alterna y copa globosa.","hojas":"Simples, alternas, lámina de lanceolada a oblongo-ovada, margen aserrado, ápice\n     acuminado y base de cuneada a obtusa, haz verde oscuro seríceo, envés verde opaco glau-\n     co.","flores":"Reunidas en racimos axilares o terminales de 5 a 20 cm de largo, que contienen entre\n     10 y 40 flores. Flores bisexuales, actinomorfas de 0,6 cm de diámetro, tubo floral urceolado,\n     cáliz conformado por 5 sépalos de forma triangular, corola con 5 pétalos blancos de forma\n     orbicular; androceo conformado por 20 estambres de 3 mm de largo; ovario ínfero pubes-\n     cente, estigma discoide.","fruta":"Drupa globosa de 12 a 20 mm de diámetro y color negro cuando madura. Semillas\n     esféricas, rodeadas por un endocarpio hueso leñoso.","distribucion_y_ecologia":"Prunus serotina subesp. capuli, es nativa de México y ha sido introdu-\n     cida en Sudamérica por sus frutos comestibles (Romolerux, 1996), no se sabe con exactitud\n     la época de su introducción, pero se presume que fue con la llegada de los españoles. En la\n     región andina ha sido ampliamente cultivado y naturalizado entre 2500 y 3500 m de altitud\n     (Romolerux, 1996). Esta especie se adapta a una gran variedad de suelos, pero se establece\n     mejor en suelos profundos y bien drenados, presenta una buena capacidad de rebrote y\n     una buena capacidad de regeneración. Especie pionera poco tolerante a la sombra, se esta-\n     blece en ambientes abiertos.","usos_tradicionales":"Su madera es utilizada para cabezas de arado, postes, estacas, vigas y\n     umbrales de casas (De la Torre et al, 2008). Las hojas sirven como sustrato para germinar el\n     maíz previo a la elaboración de la chicha de jora. Sus frutos son comestibles y se emplean\n     en la elaboración de mermeladas y vinos, además constituyen un recurso importante para\n     la alimentación de aves silvestres.","propagacion":"Se propaga mediante semillas, para lo cual es necesario remojarlas durante\n     tres días y secarlas al sol antes de ponerlas en el semillero. Otro tratamiento pre germinativo\n     consiste en estratificarlas al frío durante 120 días a temperaturas de 3 a 5 °C bajo cero. Un\n     método fácil para romper el letargo de las semillas es dejarlas a la intemperie durante 8 días\n     antes de sembrarlas.","images":["/resources/img/arboles-85_0.jpg","/resources/img/arboles-85_1.jpg","/resources/img/arboles-85_2.jpg"],"slug":"capul"},{"page":86,"original":"86   ÁRBOLES NATIVOS\n\n\n\n\n                                     Familia: Salicaceae\n                                       Rabo de zorro\n\n                             Nombre científico: Abatia parviflora Ruiz & Pav.\n                       Otros nombres comunes: “sui sui”\n\n\n     Hábito: Árbol hasta 12 m de altura y 30 cm de DAP; Tronco recto, copa estrecha ramificación\n     alterna.\n\n     Hojas: Simples, opuestas; lámina con forma lanceolada de 6 a 21 cm de largo x 1,8 a 7 cm\n     de ancho; base obtusa, ápice agudo y margen serrulado; haz áspero verde brillante y envés\n     pubescente blanquecino.\n\n     Flores: Reunidas en racimos terminales espiciformes, de 20 a 30 cm de largo. Flores nu-\n     merosas actinomorfas de 4 mm de diámetro, apétalas; cáliz con 4 sépalos de color verde\n     amarillento; androceo con 40 estambres dispuestos en 2 verticilos. Ovario unilocular, estilo\n     filiforme, estigma truncado.\n\n     Fruto: Cápsula pardo grisácea, con forma triangular de 3 mm de largo.\n\n     Distribución y ecología: Especie nativa de los Andes de Colombia, Ecuador y Perú. Crece\n     en bosques húmedos andinos entre 1600 y 3400 m de altitud. Se establece bien en bordes\n     y claros de bosque, prefiere suelos profundos y bien drenados; presenta buena capacidad\n     de rebrote y en sitios talados se regenera fácilmente por lo cual es común en bosques se-\n     cundarios. En las riberas de los ríos de Cuenca se ha registrado tanto en el río Tomebamba\n     (sector de Sayausí) cuanto en el río Yanuncay (desde el sector de Barabón hasta Soldados).\n\n     Usos tradicionales: Antiguamente su madera se usaba para la construcción de chozas y\n     pequeñas viviendas rurales (Cordero, 1984), en la actualidad se usa solamente como leña.\n\n     Propagación: Se puede propagar vegetativamente, mediante estacas semimaduras, de 20\n     a 25 cm de largo y 3 cm de grosor. Las estacas desarrollan brotes a partir de los 20 días des-\n     pués de la siembra en fundas.\n","familia":"Salicaceae\n","nombre":"Rabo de zorro","descripcíon":"","otros_nombres_comunes":["sui sui"],"nombre_cientifica":"Abatia parviflora Ruiz & Pav.","habito":" Árbol hasta 12 m de altura y 30 cm de DAP; Tronco recto, copa estrecha ramificación\n     alterna.","hojas":"Simples, opuestas; lámina con forma lanceolada de 6 a 21 cm de largo x 1,8 a 7 cm\n     de ancho; base obtusa, ápice agudo y margen serrulado; haz áspero verde brillante y envés\n     pubescente blanquecino.","flores":"Reunidas en racimos terminales espiciformes, de 20 a 30 cm de largo. Flores nu-\n     merosas actinomorfas de 4 mm de diámetro, apétalas; cáliz con 4 sépalos de color verde\n     amarillento; androceo con 40 estambres dispuestos en 2 verticilos. Ovario unilocular, estilo\n     filiforme, estigma truncado.","fruta":"Cápsula pardo grisácea, con forma triangular de 3 mm de largo.","distribucion_y_ecologia":"Especie nativa de los Andes de Colombia, Ecuador y Perú. Crece\n     en bosques húmedos andinos entre 1600 y 3400 m de altitud. Se establece bien en bordes\n     y claros de bosque, prefiere suelos profundos y bien drenados; presenta buena capacidad\n     de rebrote y en sitios talados se regenera fácilmente por lo cual es común en bosques se-\n     cundarios. En las riberas de los ríos de Cuenca se ha registrado tanto en el río Tomebamba\n     (sector de Sayausí) cuanto en el río Yanuncay (desde el sector de Barabón hasta Soldados).","usos_tradicionales":"Antiguamente su madera se usaba para la construcción de chozas y\n     pequeñas viviendas rurales (Cordero, 1984), en la actualidad se usa solamente como leña.","propagacion":"Se puede propagar vegetativamente, mediante estacas semimaduras, de 20\n     a 25 cm de largo y 3 cm de grosor. Las estacas desarrollan brotes a partir de los 20 días des-\n     pués de la siembra en fundas.","images":["/resources/img/arboles-87_0.jpg","/resources/img/arboles-87_1.jpg","/resources/img/arboles-87_2.jpg"],"slug":"rabo-de-zorro"},{"page":88,"original":"88   ÁRBOLES NATIVOS\n\n\n\n\n                                       Familia: Salicaceae\n                                                 Sauce\n\n                               Nombre científico: Salix humboldtiana Willd.\n                       Otros nombres comunes: “sauce”\n\n\n     Hábito: Árbol de 5 a 12 m de altura y 50 cm de diámetro. Tronco tortuoso con la corteza\n     externa agrietada, copa amplia irregular con ramificación alterna.\n\n     Hojas: Simples, angostas de bordes aserrados, lámina de 6 por 0,6 a 13 por 0,8 cm, que con-\n     forman un follaje verde claro característico.\n\n     Flores: Reunidas en inflorescencias espiciformes terminales o en brotes laterales. Flores uni-\n     sexuales, plantas dioicas. Flores masculinas verde amarillentas con numerosos estambres\n     de filamentos libres. Flores femeninas, con ovario superior y estigma lobado.\n\n     Fruto: Una pequeña cápsula bivalvada de 4 mm de largo que contienen numerosas y dimi-\n     nutas semillas con pelos blancos.\n\n     Distribución y ecología: Especie de amplia distribución en México, Centro y Sur América\n     (Perú, Chile y Argentina). En nuestro país se encuentra mayoritariamente en los valles inte-\n     randinos, cultivado en riberas de ríos, parques y jardines urbanos y zonas agrícolas. Crece\n     muy bien en suelos temporalmente inundados, prefiere suelos húmedos, arenosos y con\n     buen drenaje. En la ribera del Yanuncay, constituye una especie dominante particularmente\n     en la zona urbana y al parecer es un árbol eficiente en la protección de taludes.\n\n     Usos tradicionales: Su madera se usa como postes, estacas además en la fabricación de\n     cucharas, bateas, cajones y palillos de fósforo. Con cualquier parte de la planta en infusión\n     se lava el cabello a fin de fortalecerlo y para tratar la caspa se utiliza la corteza. Las hojas ma-\n     ceradas colocadas en la frente detienen las hemorragias, el humo de las hojas se inhala para\n     detener la hemorragia nasal (De la Torre et al, 2008). Ambientalmente se usa como especie\n     protectora de riberas y quebradas.\n\n     Propagación: Se propaga fácil y extensivamente por estacas o esquejes, en cualquier es-\n     tado de madurez. También puede propagarse mediante semillas, las mismas que deben\n     sembrarse inmediatamente después de su recolección. Para el efecto las cápsulas deben\n     esparcirse en camas húmedas hasta el establecimiento de las plántulas; las plántulas deben\n     trasplantarse luego de transcurrido un año.\n\n     Es una especie susceptible a la sequía y a la contaminación del suelo y aire; posee un rápido\n     crecimiento particularmente durante los primeros cuatro años.\n","familia":"Salicaceae\n","nombre":"Sauce","descripcíon":"","otros_nombres_comunes":["sauce"],"nombre_cientifica":"Salix humboldtiana Willd.","habito":" Árbol de 5 a 12 m de altura y 50 cm de diámetro. Tronco tortuoso con la corteza\n     externa agrietada, copa amplia irregular con ramificación alterna.","hojas":"Simples, angostas de bordes aserrados, lámina de 6 por 0,6 a 13 por 0,8 cm, que con-\n     forman un follaje verde claro característico.","flores":"Reunidas en inflorescencias espiciformes terminales o en brotes laterales. Flores uni-\n     sexuales, plantas dioicas. Flores masculinas verde amarillentas con numerosos estambres\n     de filamentos libres. Flores femeninas, con ovario superior y estigma lobado.","fruta":"Una pequeña cápsula bivalvada de 4 mm de largo que contienen numerosas y dimi-\n     nutas semillas con pelos blancos.","distribucion_y_ecologia":"Especie de amplia distribución en México, Centro y Sur América\n     (Perú, Chile y Argentina). En nuestro país se encuentra mayoritariamente en los valles inte-\n     randinos, cultivado en riberas de ríos, parques y jardines urbanos y zonas agrícolas. Crece\n     muy bien en suelos temporalmente inundados, prefiere suelos húmedos, arenosos y con\n     buen drenaje. En la ribera del Yanuncay, constituye una especie dominante particularmente\n     en la zona urbana y al parecer es un árbol eficiente en la protección de taludes.","usos_tradicionales":"Su madera se usa como postes, estacas además en la fabricación de\n     cucharas, bateas, cajones y palillos de fósforo. Con cualquier parte de la planta en infusión\n     se lava el cabello a fin de fortalecerlo y para tratar la caspa se utiliza la corteza. Las hojas ma-\n     ceradas colocadas en la frente detienen las hemorragias, el humo de las hojas se inhala para\n     detener la hemorragia nasal (De la Torre et al, 2008). Ambientalmente se usa como especie\n     protectora de riberas y quebradas.","propagacion":"Se propaga fácil y extensivamente por estacas o esquejes, en cualquier es-\n     tado de madurez. También puede propagarse mediante semillas, las mismas que deben\n     sembrarse inmediatamente después de su recolección. Para el efecto las cápsulas deben\n     esparcirse en camas húmedas hasta el establecimiento de las plántulas; las plántulas deben\n     trasplantarse luego de transcurrido un año.\n\n     Es una especie susceptible a la sequía y a la contaminación del suelo y aire; posee un rápido\n     crecimiento particularmente durante los primeros cuatro años.","images":["/resources/img/arboles-89_0.jpg","/resources/img/arboles-89_1.jpg","/resources/img/arboles-89_2.jpg"],"slug":"sauce"},{"page":90,"original":"90   ÁRBOLES NATIVOS\n\n\n\n\n                                    Familia: Solanaceae\n                                         Guanto rojo\n\n                       Nombre científico: Brugmansia sanguinea (Ruiz & Pav.) D. Don.\n             Otros nombres comunes: “floripondio”, “huántug”.\n\n\n     Hábito: Arbusto o árbol pequeño de 2 a 6 m de altura. Tronco tortuoso, copa globosa, ra-\n     mificación alterna.\n\n     Hojas: Simples alternas, lámina lanceolada de 11 a 16 cm de largo por 5 a 6 cm de ancho\n     con margen entero sinuado, ápice acuminado. Haz verde obscuro, pubescente, envés blan-\n     quecino pubescente.\n\n     Flores: Solitarias péndulas. Corola tubular infundibuliforme de 20 cm de largo, amarilla ver-\n     dosa en la base y roja en el ápice. Androceo con 5 estambres iguales insertos en la corola.\n     Ovario bilocular, con muchos óvulos, estilo alargado (19 cm), estigma bilobulado.\n\n     Fruto: Baya con forma ovoide, que contiene numerosas semillas.\n\n     Distribución y ecología: Especie originaria de los Andes, se distribuye desde Colombia has-\n     ta Bolivia. En nuestro país se encuentra en la región andina entre 2000 y 3500 m de altitud.\n     Es una planta típica de los valles interandinos, es frecuente en áreas agrícolas, bosques se-\n     cundarios, en cercas junto a viviendas campesinas y en jardines urbanos. Su crecimiento es\n     óptimo en suelos profundos y con alto contenido de materia orgánica (Minga, 2000). Sus\n     flores son visitadas por varias especies de colibríes. En los márgenes de los ríos es una espe-\n     cie poco frecuente y se ha registrado en los ríos Yanuncay, en las zonas de Barabón, Sústag\n     y Soldados y en el río Tomebamba en Sayausí y San Joaquín.\n\n     Usos tradicionales: El huántug es una planta medicinal, empleada fundamentalmente para\n     realizar las denominadas limpias de espanto y mal aire. Sus hojas y flores, para curar dolen-\n     cias neurálgicas, aplicando las hojas calentadas en las partes afectadas de dolores muscula-\n     res y neuralgias (Acosta Solís, 1992). Es una planta alucinógena y altamente tóxica, los frutos\n     y semillas contienen alcaloides por lo que no se pueden tomar en infusión (Bartolomeus,\n     1990).\n\n     Propagación: Se propaga mediante semillas, las cuales deben extraerse del fruto y sembrar-\n     se directamente en semilleros o también pueden almacenarse por un periodo no mayor a\n     90 días y someterlas a remojo durante 12 horas para luego sembrarlas. Vegetativamente se\n     propaga mediante estacas de dos años que contengan seis yemas (Loján, 1992).\n","familia":"Solanaceae\n","nombre":"Guanto rojo","descripcíon":"","otros_nombres_comunes":["floripondio","huántug."],"nombre_cientifica":"Brugmansia sanguinea (Ruiz & Pav.) D. Don.","habito":" Arbusto o árbol pequeño de 2 a 6 m de altura. Tronco tortuoso, copa globosa, ra-\n     mificación alterna.","hojas":"Simples alternas, lámina lanceolada de 11 a 16 cm de largo por 5 a 6 cm de ancho\n     con margen entero sinuado, ápice acuminado. Haz verde obscuro, pubescente, envés blan-\n     quecino pubescente.","flores":"Solitarias péndulas. Corola tubular infundibuliforme de 20 cm de largo, amarilla ver-\n     dosa en la base y roja en el ápice. Androceo con 5 estambres iguales insertos en la corola.\n     Ovario bilocular, con muchos óvulos, estilo alargado (19 cm), estigma bilobulado.","fruta":"Baya con forma ovoide, que contiene numerosas semillas.","distribucion_y_ecologia":"Especie originaria de los Andes, se distribuye desde Colombia has-\n     ta Bolivia. En nuestro país se encuentra en la región andina entre 2000 y 3500 m de altitud.\n     Es una planta típica de los valles interandinos, es frecuente en áreas agrícolas, bosques se-\n     cundarios, en cercas junto a viviendas campesinas y en jardines urbanos. Su crecimiento es\n     óptimo en suelos profundos y con alto contenido de materia orgánica (Minga, 2000). Sus\n     flores son visitadas por varias especies de colibríes. En los márgenes de los ríos es una espe-\n     cie poco frecuente y se ha registrado en los ríos Yanuncay, en las zonas de Barabón, Sústag\n     y Soldados y en el río Tomebamba en Sayausí y San Joaquín.","usos_tradicionales":"El huántug es una planta medicinal, empleada fundamentalmente para\n     realizar las denominadas limpias de espanto y mal aire. Sus hojas y flores, para curar dolen-\n     cias neurálgicas, aplicando las hojas calentadas en las partes afectadas de dolores muscula-\n     res y neuralgias (Acosta Solís, 1992). Es una planta alucinógena y altamente tóxica, los frutos\n     y semillas contienen alcaloides por lo que no se pueden tomar en infusión (Bartolomeus,\n     1990).","propagacion":"Se propaga mediante semillas, las cuales deben extraerse del fruto y sembrar-\n     se directamente en semilleros o también pueden almacenarse por un periodo no mayor a\n     90 días y someterlas a remojo durante 12 horas para luego sembrarlas. Vegetativamente se\n     propaga mediante estacas de dos años que contengan seis yemas (Loján, 1992).","images":["/resources/img/arboles-91_0.jpg","/resources/img/arboles-91_1.jpg","/resources/img/arboles-91_2.jpg"],"slug":"guanto-rojo"},{"page":92,"original":"92   ÁRBOLES NATIVOS\n\n\n\n\n                                    Familia: Solanaceae\n                                        Hoja blanca\n\n                             Nombre científico: Sessea crassivenosa Bitter\n\n\n\n\n     Hábito: Árbol de 5 a 10 m de altura y 10 a 20 cm de DAP. Fuste tortuoso, ramificación alterna\n     y copa estrecha, corteza externa gris blanquecina.\n\n     Hojas: Simples, alternas de consistencia coriácea, lámina de forma lanceolada (3,5 a 7 x 1,5\n     a 3 cm), margen entero revoluto, ápice agudo y base redondeada, haz verde oscuro, envés\n     pardo blanquecino.\n\n     Flores: Dispuestas en racimos compuestos de 3 a 6 cm de largo. Flores bisexuales, regulares,\n     cáliz tubular campanulado con 5 lóbulos triangulares, corola infundibuliforme de 1 a 1,4 cm\n     de largo, de color amarillo verdoso; 5 estambres insertos en la base del tubo de la corola,\n     ovario súpero.\n\n     Fruto: Una cápsula dehiscente que contiene numerosas semillas aladas.\n\n     Distribución y ecología: Se distribuye en la región andina del Ecuador entre 2500 y 4500 m\n     de altitud. Es un árbol poco abundante, se lo encuentra fundamentalmente en bordes de\n     bosque maduro y márgenes de quebradas. En los márgenes de los ríos de Cuenca es una es-\n     pecie rara y crece fundamentalmente en las partes altas de los ríos Yanuncay y Tomebamba.\n     No presenta capacidad de rebrote y su regeneración natural es escasa. Florece en marzo y\n     abril y fructifica en mayo y junio.\n\n     Usos tradicionales: Su madera se usa para la fabricación de carbón y sus hojas son utilizadas\n     como forraje para vacas y cuyes.\n","familia":"Solanaceae\n","nombre":"Hoja blanca","descripcíon":"","otros_nombres_comunes":[],"nombre_cientifica":"Sessea crassivenosa Bitter","habito":" Árbol de 5 a 10 m de altura y 10 a 20 cm de DAP. Fuste tortuoso, ramificación alterna\n     y copa estrecha, corteza externa gris blanquecina.","hojas":"Simples, alternas de consistencia coriácea, lámina de forma lanceolada (3,5 a 7 x 1,5\n     a 3 cm), margen entero revoluto, ápice agudo y base redondeada, haz verde oscuro, envés\n     pardo blanquecino.","flores":"Dispuestas en racimos compuestos de 3 a 6 cm de largo. Flores bisexuales, regulares,\n     cáliz tubular campanulado con 5 lóbulos triangulares, corola infundibuliforme de 1 a 1,4 cm\n     de largo, de color amarillo verdoso; 5 estambres insertos en la base del tubo de la corola,\n     ovario súpero.","fruta":"Una cápsula dehiscente que contiene numerosas semillas aladas.","distribucion_y_ecologia":"Se distribuye en la región andina del Ecuador entre 2500 y 4500 m\n     de altitud. Es un árbol poco abundante, se lo encuentra fundamentalmente en bordes de\n     bosque maduro y márgenes de quebradas. En los márgenes de los ríos de Cuenca es una es-\n     pecie rara y crece fundamentalmente en las partes altas de los ríos Yanuncay y Tomebamba.\n     No presenta capacidad de rebrote y su regeneración natural es escasa. Florece en marzo y\n     abril y fructifica en mayo y junio.","usos_tradicionales":"Su madera se usa para la fabricación de carbón y sus hojas son utilizadas\n     como forraje para vacas y cuyes.","propagacion":"","images":["/resources/img/arboles-93_0.jpg","/resources/img/arboles-93_1.jpg","/resources/img/arboles-93_2.jpg"],"slug":"hoja-blanca"},{"page":94,"original":"94   ÁRBOLES NATIVOS\n\n\n\n\n                                    Familia: Solanaceae\n                                     Túrpug hembra\n\n                             Nombre científico: Solanum oblongifolium Dunal\n                       Otros nombres comunes: “allcu jambi”\n\n\n     Hábito: Árbol hasta de 7 m de alto; tronco ligeramente irregular, copa plana con ramifica-\n     ción alterna.\n\n     Hojas: Simples, alternas, con peciolo alado, lámina de oblonga a elíptica (20 a 33 x 10 a 15\n     cm), ápice agudo y margen entero a sinuado. Inflorescencias en cimas corimbiformes de 10\n     a 24 cm.\n\n     Flores: Flores bisexuales actinomorfas, fragantes; cáliz gamosépalo con 5 lóbulos con un\n     abultamiento en la parte dorsal; corola rotada de color blanco con 5 lóbulos que emergen\n     de un corto tubo; androceo conformado por 5 estambres insertos en la base de la corola\n     con anteras amarillas sostenidas por un corto filamento; gineceo con un ovario bicarpelar\n     y bilocular.\n\n     Fruto: Una baya jugosa de 1,7 a 2 cm de diámetro de color blanco verdoso al madurar.\n\n     Distribución y ecología: Especie nativa de amplia distribución en la región de los Andes del\n     Ecuador, ha sido localizada en las provincias de Pichincha, Cotopaxi, Bolívar, Cañar, Azuay y\n     Loja entre 2000 y 4500 m de altitud (Jorgensen & León-Yánez 1999). Este árbol es frecuente\n     en bosques intervenidos, bordes de quebradas y zonas agrícolas. En las riberas del Yanun-\n     cay es poco frecuente y ha sido registrada en la zona de Barabón, San Joaquín y en el río\n     Tomebamba. Se han registrado pocos individuos en el sector de la isla del Batán.\n\n     Usos tradicionales: En las comunidades de Marianza y Sayausí, sus hojas y ramas se em-\n     plean para efectuar las limpias y curar la enfermedad denominada mal de aire.\n","familia":"Solanaceae\n","nombre":"Túrpug hembra","descripcíon":"","otros_nombres_comunes":["allcu jambi"],"nombre_cientifica":"Solanum oblongifolium Dunal","habito":" Árbol hasta de 7 m de alto; tronco ligeramente irregular, copa plana con ramifica-\n     ción alterna.","hojas":"Simples, alternas, con peciolo alado, lámina de oblonga a elíptica (20 a 33 x 10 a 15\n     cm), ápice agudo y margen entero a sinuado. Inflorescencias en cimas corimbiformes de 10\n     a 24 cm.","flores":"Flores bisexuales actinomorfas, fragantes; cáliz gamosépalo con 5 lóbulos con un\n     abultamiento en la parte dorsal; corola rotada de color blanco con 5 lóbulos que emergen\n     de un corto tubo; androceo conformado por 5 estambres insertos en la base de la corola\n     con anteras amarillas sostenidas por un corto filamento; gineceo con un ovario bicarpelar\n     y bilocular.","fruta":"Una baya jugosa de 1,7 a 2 cm de diámetro de color blanco verdoso al madurar.","distribucion_y_ecologia":"Especie nativa de amplia distribución en la región de los Andes del\n     Ecuador, ha sido localizada en las provincias de Pichincha, Cotopaxi, Bolívar, Cañar, Azuay y\n     Loja entre 2000 y 4500 m de altitud (Jorgensen & León-Yánez 1999). Este árbol es frecuente\n     en bosques intervenidos, bordes de quebradas y zonas agrícolas. En las riberas del Yanun-\n     cay es poco frecuente y ha sido registrada en la zona de Barabón, San Joaquín y en el río\n     Tomebamba. Se han registrado pocos individuos en el sector de la isla del Batán.","usos_tradicionales":"En las comunidades de Marianza y Sayausí, sus hojas y ramas se em-\n     plean para efectuar las limpias y curar la enfermedad denominada mal de aire.","propagacion":"","images":["/resources/img/arboles-95_0.jpg","/resources/img/arboles-95_1.jpg","/resources/img/arboles-95_2.jpg","/resources/img/arboles-95_3.jpg"],"slug":"trpug-hembra"},{"page":96,"original":"96   ÁRBOLES NATIVOS\n\n\n\n\n                                  Familia: Verbenaceae\n                                           Zharcao\n\n                             Nombre científico: Citharexylum ilicifolium Kunth\n                       Otros nombres comunes: “casanto”, “capi”, “pintilla”\n\n\n     Hábito: Arbusto o árbol pequeño de hasta 5 m de altura. Tronco tortuoso, ramificación al-\n     terna, copa globosa o irregular, follaje de color verde lustroso.\n\n     Hojas: Simples opuestas, de textura coriácea y superficie glabra, pecíolo ensanchado en la\n     base, lámina con forma elíptica-oblonga, de 2 a 4 cm de largo por 1 a 2 cm de ancho con el\n     margen espinoso.\n\n     Flores: Fragantes, reunidas en racimos estrechos terminales de 4 a 7 cm de largo; cáliz con\n     forma de campana; corola tubular de color blanco, 5 estambres insertos en la base del tubo\n     de la corola, ovario súpero, 4 locular.\n\n     Fruto: Drupa globosa de 4 a 5 mm de diámetro, de color negro cuando está madura, el cáliz\n     es persistente y rodea al fruto en la base.\n\n     Distribución y ecología: Especie nativa de los Andes de Ecuador, Perú y Bolivia. En nuestro\n     país, es una especie silvestre y cultivada en el callejón interandino entre 2000 y 4000 m de\n     altitud. Este arbusto es rústico, se adapta bien en suelos pobres y pedregosos, es frecuente\n     encontrarlo en laderas barrancos y márgenes de quebradas. Ecológicamente es una espe-\n     cie importante, aves silvestres particularmente mirlos, consumen sus frutos y posiblemente\n     dispersan las semillas. En los márgenes de los ríos de Cuenca es una especie común y se\n     encuentra incluso dentro del casco urbano.\n\n     Usos tradicionales: Antiguamente de sus frutos se extraía tinta para escribir a pluma, no\n     obstante estos frutos son tóxicos para el hombre (Jaramillo, 2013). En la actualidad se em-\n     plea en cercas vivas como especie ornamental. Con su tallo se elaboran yugos y también\n     sirve para fabricar escobas (Jaramillo, 2013).\n","familia":"Verbenaceae\n","nombre":"Zharcao","descripcíon":"","otros_nombres_comunes":["casanto","capi","pintilla"],"nombre_cientifica":"Citharexylum ilicifolium Kunth","habito":" Arbusto o árbol pequeño de hasta 5 m de altura. Tronco tortuoso, ramificación al-\n     terna, copa globosa o irregular, follaje de color verde lustroso.","hojas":"Simples opuestas, de textura coriácea y superficie glabra, pecíolo ensanchado en la\n     base, lámina con forma elíptica-oblonga, de 2 a 4 cm de largo por 1 a 2 cm de ancho con el\n     margen espinoso.","flores":"Fragantes, reunidas en racimos estrechos terminales de 4 a 7 cm de largo; cáliz con\n     forma de campana; corola tubular de color blanco, 5 estambres insertos en la base del tubo\n     de la corola, ovario súpero, 4 locular.","fruta":"Drupa globosa de 4 a 5 mm de diámetro, de color negro cuando está madura, el cáliz\n     es persistente y rodea al fruto en la base.","distribucion_y_ecologia":"Especie nativa de los Andes de Ecuador, Perú y Bolivia. En nuestro\n     país, es una especie silvestre y cultivada en el callejón interandino entre 2000 y 4000 m de\n     altitud. Este arbusto es rústico, se adapta bien en suelos pobres y pedregosos, es frecuente\n     encontrarlo en laderas barrancos y márgenes de quebradas. Ecológicamente es una espe-\n     cie importante, aves silvestres particularmente mirlos, consumen sus frutos y posiblemente\n     dispersan las semillas. En los márgenes de los ríos de Cuenca es una especie común y se\n     encuentra incluso dentro del casco urbano.","usos_tradicionales":"Antiguamente de sus frutos se extraía tinta para escribir a pluma, no\n     obstante estos frutos son tóxicos para el hombre (Jaramillo, 2013). En la actualidad se em-\n     plea en cercas vivas como especie ornamental. Con su tallo se elaboran yugos y también\n     sirve para fabricar escobas (Jaramillo, 2013).","propagacion":"","images":["/resources/img/arboles-97_0.jpg","/resources/img/arboles-97_1.jpg","/resources/img/arboles-97_2.jpg","/resources/img/arboles-97_3.jpg","/resources/img/arboles-98_0.jpg","/resources/img/arboles-99_0.jpg"],"slug":"zharcao"},{"page":100,"original":"100   ARBUSTOS NATIVOS\n\n\n\n\n                                      Familia: Adoxaceae\n                                                Rañas\n\n                              Nombre científico: Viburnum triphyllum Benth\n                      Otros nombres comunes: “dañas”, “juanico”\n\n\n      Hábito: Arbusto o árbol pequeño de 2 a 4 m de altura; tallo cilíndrico, corteza externa de co-\n      lor café y ramificación verticilada que inicia encima de la base. Su copa es globosa o algunas\n      veces irregular, su follaje es ralo brillante y de color verde oscuro.\n\n      Hojas: Simples dispuestas en verticilos de tres, lámina elíptica, base aguda, ápice apiculado\n      y margen entero. Haz verde lustroso, envés verde claro.\n\n      Flores: Fragantes, reunidas en inflorescencias umbeladas que contienen alrededor de 90\n      flores; cáliz verde, cupuliforme adnado al ovario, corola caduca, campanulada de color blan-\n      co cremoso, compuesta por 5 pétalos oblongos. Androceo conformado por 5 estambres in-\n      sertos en la base de la corola, anteras dorsifijas, con dehiscencia longitudinal. Ovario ínfero\n      unilocular.\n\n      Fruto: Drupas ovoides de 0,8 a 1 cm de diámetro, de color negro cuando están maduros,\n      cada fruto contiene una semilla de 0,7 cm de largo por 0,4 cm de ancho.\n\n      Distribución y ecología: Se distribuye en los Andes de Venezuela, Colombia, Ecuador y\n      Perú (W Trópicos, 2015). En nuestro país crece en bosques montanos húmedos entre 1700 y\n      3400 m de altitud. En el margen de los ríos de Cuenca es una especie muy distribuida, crece\n      en sitios abiertos y matorrales secundarios. Presenta una buena capacidad de rebrote y su\n      regeneración natural es también buena. Sus frutos son consumidos por aves especialmente\n      por mirlos (Serrano, 1996).\n\n      Usos tradicionales: Antiguamente su madera se empleaba para construcciones y en usos\n      para hilar lana o algodón (Cordero, 1984). En la actualidad en comunidades como el Carmen\n      de Aguarongo y Jadán, localizadas en la provincia del Azuay, sus hojas se emplean como\n      forraje para ganado y cuyes; con su madera se elaboran cabos para herramientas manuales,\n      husos y guangos.\n\n      Propagación: Se propaga mediante semilla, para lo cual se recomienda un tratamiento pre\n      germinativo de inmersión en agua a temperatura ambiental durante 72 horas. Para los se-\n      milleros, se recomienda un sustrato suelto compuesto por tierra negra, turba y cascarilla\n      en proporción 3:2:1 en volumen, previamente desinfectado y tamizado (Suárez, 2012). La\n      germinación inicia a los 38 días después de la siembra. Al momento de la siembra se reco-\n      mienda poner las semillas en bandejas germinadoras a una profundidad no mayor a los 8 a\n      10 cm y a una distancia de 3 cm entre una y otra; se debe regar dos veces por semana hasta\n      el inicio de la germinación y luego una vez cada semana (Pérez, 2007).\n","familia":"Adoxaceae\n","nombre":"Rañas","descripcíon":"","otros_nombres_comunes":["dañas","juanico"],"nombre_cientifica":"Viburnum triphyllum Benth","habito":" Arbusto o árbol pequeño de 2 a 4 m de altura; tallo cilíndrico, corteza externa de co-\n      lor café y ramificación verticilada que inicia encima de la base. Su copa es globosa o algunas\n      veces irregular, su follaje es ralo brillante y de color verde oscuro.","hojas":"Simples dispuestas en verticilos de tres, lámina elíptica, base aguda, ápice apiculado\n      y margen entero. Haz verde lustroso, envés verde claro.","flores":"Fragantes, reunidas en inflorescencias umbeladas que contienen alrededor de 90\n      flores; cáliz verde, cupuliforme adnado al ovario, corola caduca, campanulada de color blan-\n      co cremoso, compuesta por 5 pétalos oblongos. Androceo conformado por 5 estambres in-\n      sertos en la base de la corola, anteras dorsifijas, con dehiscencia longitudinal. Ovario ínfero\n      unilocular.","fruta":"Drupas ovoides de 0,8 a 1 cm de diámetro, de color negro cuando están maduros,\n      cada fruto contiene una semilla de 0,7 cm de largo por 0,4 cm de ancho.","distribucion_y_ecologia":"Se distribuye en los Andes de Venezuela, Colombia, Ecuador y\n      Perú (W Trópicos, 2015). En nuestro país crece en bosques montanos húmedos entre 1700 y\n      3400 m de altitud. En el margen de los ríos de Cuenca es una especie muy distribuida, crece\n      en sitios abiertos y matorrales secundarios. Presenta una buena capacidad de rebrote y su\n      regeneración natural es también buena. Sus frutos son consumidos por aves especialmente\n      por mirlos (Serrano, 1996).","usos_tradicionales":"Antiguamente su madera se empleaba para construcciones y en usos\n      para hilar lana o algodón (Cordero, 1984). En la actualidad en comunidades como el Carmen\n      de Aguarongo y Jadán, localizadas en la provincia del Azuay, sus hojas se emplean como\n      forraje para ganado y cuyes; con su madera se elaboran cabos para herramientas manuales,\n      husos y guangos.","propagacion":"Se propaga mediante semilla, para lo cual se recomienda un tratamiento pre\n      germinativo de inmersión en agua a temperatura ambiental durante 72 horas. Para los se-\n      milleros, se recomienda un sustrato suelto compuesto por tierra negra, turba y cascarilla\n      en proporción 3:2:1 en volumen, previamente desinfectado y tamizado (Suárez, 2012). La\n      germinación inicia a los 38 días después de la siembra. Al momento de la siembra se reco-\n      mienda poner las semillas en bandejas germinadoras a una profundidad no mayor a los 8 a\n      10 cm y a una distancia de 3 cm entre una y otra; se debe regar dos veces por semana hasta\n      el inicio de la germinación y luego una vez cada semana (Pérez, 2007).","images":["/resources/img/arboles-101_0.jpg","/resources/img/arboles-101_1.jpg","/resources/img/arboles-101_2.jpg"],"slug":"raas"},{"page":102,"original":"102   ARBUSTOS NATIVOS\n\n\n\n\n                                     Familia: Asteraceae\n                                            Altamisa\n\n                              Nombre científico: Ambrosia arborescens Mill\n                      Otros nombres comunes: “marco”\n\n\n      Hábito: Arbusto aromático de 1 a 3 m de altura, tallos erectos o inclinados, con abundante\n      ramificación que inicia desde la base formando matas densas de 1 a 2 m de diámetro.\n\n      Hojas: Simples, alternas, pinnatidisectas de 8 (12) 18 cm de largo, peciolos de 1 a 3 cm de\n      largo; haz pubescente glanduloso de color verde oscuro, envés pubescente blanquecino.\n\n      Flores: Unisexuales dispuestas en cabezuelas separadas. Cabezuelas masculinas dispues-\n      tas en racimos espiciformes terminales, involucro en forma de copa de 0,6 a 0,8 mm de\n      diámetro, con una serie de filarias connatas; flores femeninas 40 a 50 por cabezuela, co-\n      rola cremosa de 0,4 cm de largo, anteras libres. Cabezuelas femeninas por debajo de las\n      masculinas, dispuestas en grupos axilares, filarias fusionadas espinosas, formando un in-\n      volucro duro; flores femeninas dos por cabezuela, corola ausente y ramas del estilo que\n      sobresalen de los involucros.\n\n      Fruto: Dos cipselas prismáticas incluidas en el involucro duro y espinoso, papus ausente.\n\n      Distribución y ecología: Crece en los Andes de Colombia, Ecuador, Perú y Bolivia. En nues-\n      tro país se distribuye a lo largo de la región andina entre 2000 y 3500 m de altitud (Jorgen-\n      sen & León-Yánez, 1999). Es común en los valles interandinos secos; crece profusamente\n      en terrenos sueltos y arenosos ligeramente alcalinos, en donde forma matorrales junto a\n      otras especies pioneras como Baccharis latifolia, Dodonaea viscosa, Mimosa andina y Dalea\n      coerulela. Es frecuente observarla a la vera de caminos y márgenes degradados de ríos y\n      quebradas. En los ríos de Cuenca es común en orillas abiertas y degradadas dentro de la\n      zona urbana.\n\n      Usos tradicionales: En las comunidades de San Joaquín y Sayausí, situadas en los már-\n      genes de los ríos Yanuncay y Tomebamba respectivamente, la altamisa se emplea tradi-\n      cionalmente como repelente de insectos, para lo cual se usan ramas frescas y se limpian\n      los espacios interiores de las casas. Este uso tradicional fue muy importante en el pasado;\n      así, William Jameson, botánico escocés que residió en Quito en el siglo XIX mencionó que\n      se usaba como repelente de pulgas (Ruales, 2013). También se usa para limpiar hornos de\n      leña. Medicinalmente se ha empleado para aliviar problemas de la piel, como granos y\n      salpullidos, en zumo se usa para regular la presión sanguínea y como antiparasitario.\n\n      Propagación: Puede propagarse mediante división de matas o mediante esquejes semi-\n      maduros.\n","familia":"Asteraceae\n","nombre":"Altamisa","descripcíon":"","otros_nombres_comunes":["marco"],"nombre_cientifica":"Ambrosia arborescens Mill","habito":" Arbusto aromático de 1 a 3 m de altura, tallos erectos o inclinados, con abundante\n      ramificación que inicia desde la base formando matas densas de 1 a 2 m de diámetro.","hojas":"Simples, alternas, pinnatidisectas de 8 (12) 18 cm de largo, peciolos de 1 a 3 cm de\n      largo; haz pubescente glanduloso de color verde oscuro, envés pubescente blanquecino.","flores":"Unisexuales dispuestas en cabezuelas separadas. Cabezuelas masculinas dispues-\n      tas en racimos espiciformes terminales, involucro en forma de copa de 0,6 a 0,8 mm de\n      diámetro, con una serie de filarias connatas; flores femeninas 40 a 50 por cabezuela, co-\n      rola cremosa de 0,4 cm de largo, anteras libres. Cabezuelas femeninas por debajo de las\n      masculinas, dispuestas en grupos axilares, filarias fusionadas espinosas, formando un in-\n      volucro duro; flores femeninas dos por cabezuela, corola ausente y ramas del estilo que\n      sobresalen de los involucros.","fruta":"Dos cipselas prismáticas incluidas en el involucro duro y espinoso, papus ausente.","distribucion_y_ecologia":"Crece en los Andes de Colombia, Ecuador, Perú y Bolivia. En nues-\n      tro país se distribuye a lo largo de la región andina entre 2000 y 3500 m de altitud (Jorgen-\n      sen & León-Yánez, 1999). Es común en los valles interandinos secos; crece profusamente\n      en terrenos sueltos y arenosos ligeramente alcalinos, en donde forma matorrales junto a\n      otras especies pioneras como Baccharis latifolia, Dodonaea viscosa, Mimosa andina y Dalea\n      coerulela. Es frecuente observarla a la vera de caminos y márgenes degradados de ríos y\n      quebradas. En los ríos de Cuenca es común en orillas abiertas y degradadas dentro de la\n      zona urbana.","usos_tradicionales":"En las comunidades de San Joaquín y Sayausí, situadas en los már-\n      genes de los ríos Yanuncay y Tomebamba respectivamente, la altamisa se emplea tradi-\n      cionalmente como repelente de insectos, para lo cual se usan ramas frescas y se limpian\n      los espacios interiores de las casas. Este uso tradicional fue muy importante en el pasado;\n      así, William Jameson, botánico escocés que residió en Quito en el siglo XIX mencionó que\n      se usaba como repelente de pulgas (Ruales, 2013). También se usa para limpiar hornos de\n      leña. Medicinalmente se ha empleado para aliviar problemas de la piel, como granos y\n      salpullidos, en zumo se usa para regular la presión sanguínea y como antiparasitario.","propagacion":"Puede propagarse mediante división de matas o mediante esquejes semi-\n      maduros.","images":["/resources/img/arboles-103_0.jpg","/resources/img/arboles-103_1.jpg","/resources/img/arboles-103_2.jpg"],"slug":"altamisa"},{"page":104,"original":"104   ARBUSTOS NATIVOS\n\n\n\n\n                                     Familia: Asteraceae\n                                        Virgen chilca\n\n                             Nombre científico: Aristeguietia cacalioides (Kunth)\n                                                R.M. King & H. Rob\n                      Otros nombres comunes: “urcu chilca”\n\n\n      Hábito: Arbusto de 2 a 4 m de alto, tallos cuadrangulares, ramificaciones abiertas, poco den-\n      sas, ramitas terminales teretes, nudosas; brotes tiernos resinosos verde oscuros.\n\n      Hojas: Simples, opuestas, sostenidas por peciolos de 1 a 2,5 cm de largo, lámina lanceolada\n      o elíptica lanceolada de 4 a 12 cm de largo por 1,2 a 2,7 cm de ancho, base obtusa o aguda,\n      ápice agudo y margen densamente aserrado; haz rugoso glandular resinoso, envés pálido\n      densamente pubescente, con 15 a 20 pares de venas secundarias.\n\n      Flores: Reunidas en corimbos terminales de 4 a 12 cm de ancho por 2 a 6 cm de largo; ca-\n      pítulos homógamos discoides de 8 mm de largo por 6 mm de ancho, involucro compuesto\n      por 4 a 5 series de brácteas lanceoladas, cada capítulo contiene alrededor de 16 flores; co-\n      rola azul–lila, tubular infundibuliforme de 5 mm de largo, provista de 5 dientes apicales, 5\n      estambres con las anteras con el ápice alargado, ramas del estilo alargadas y papilosas.\n\n      Fruto: Un aquenio prismático 5 costado de 3 mm de largo, con vilano compuesto por dos\n      series de cerdas blancas.\n\n      Distribución y ecología: specie endémica del Ecuador, ha sido registrada en las provincias\n      de Chimborazo, Cañar, Azuay y Loja entre 2000 y 3500 m de altitud (Robinson, 2008), crece\n      en bosques secundarios y en pastizales. En los márgenes de los ríos de Cuenca es más bien\n      una especie frecuente y ha sido registrada en los sectores de El Paraíso y El Barranco dentro\n      del casco urbano de la Ciudad. Esta especie se adapta bien a suelos poco profundos y com-\n      pactados. Florece durante todo el año y sus flores son visitadas por especies de mariposas.\n\n      Usos tradicionales: En algunas comunidades que viven alrededor del Bosque Protector\n      Aguarango sus ramas y flores se emplean para limpias del mal de aire; sus cogollos se ca-\n      lientan y se aplican en los senos cuando están infectados; en emplastos se usa para tratar\n      postemas y traumas del coxis de los niños y sus flores maceradas con trago se dan de beber\n      a las mujeres durante el parto. También sus hojas y brotes tiernos sirven de alimento para\n      ganado y cuyes.\n","familia":"Asteraceae\n","nombre":"Virgen chilca","descripcíon":"","otros_nombres_comunes":["urcu chilca"],"nombre_cientifica":"Aristeguietia cacalioides (Kunth)\n                                                R.M. King & H. Rob","habito":" Arbusto de 2 a 4 m de alto, tallos cuadrangulares, ramificaciones abiertas, poco den-\n      sas, ramitas terminales teretes, nudosas; brotes tiernos resinosos verde oscuros.","hojas":"Simples, opuestas, sostenidas por peciolos de 1 a 2,5 cm de largo, lámina lanceolada\n      o elíptica lanceolada de 4 a 12 cm de largo por 1,2 a 2,7 cm de ancho, base obtusa o aguda,\n      ápice agudo y margen densamente aserrado; haz rugoso glandular resinoso, envés pálido\n      densamente pubescente, con 15 a 20 pares de venas secundarias.","flores":"Reunidas en corimbos terminales de 4 a 12 cm de ancho por 2 a 6 cm de largo; ca-\n      pítulos homógamos discoides de 8 mm de largo por 6 mm de ancho, involucro compuesto\n      por 4 a 5 series de brácteas lanceoladas, cada capítulo contiene alrededor de 16 flores; co-\n      rola azul–lila, tubular infundibuliforme de 5 mm de largo, provista de 5 dientes apicales, 5\n      estambres con las anteras con el ápice alargado, ramas del estilo alargadas y papilosas.","fruta":"Un aquenio prismático 5 costado de 3 mm de largo, con vilano compuesto por dos\n      series de cerdas blancas.","distribucion_y_ecologia":"specie endémica del Ecuador, ha sido registrada en las provincias\n      de Chimborazo, Cañar, Azuay y Loja entre 2000 y 3500 m de altitud (Robinson, 2008), crece\n      en bosques secundarios y en pastizales. En los márgenes de los ríos de Cuenca es más bien\n      una especie frecuente y ha sido registrada en los sectores de El Paraíso y El Barranco dentro\n      del casco urbano de la Ciudad. Esta especie se adapta bien a suelos poco profundos y com-\n      pactados. Florece durante todo el año y sus flores son visitadas por especies de mariposas.","usos_tradicionales":"En algunas comunidades que viven alrededor del Bosque Protector\n      Aguarango sus ramas y flores se emplean para limpias del mal de aire; sus cogollos se ca-\n      lientan y se aplican en los senos cuando están infectados; en emplastos se usa para tratar\n      postemas y traumas del coxis de los niños y sus flores maceradas con trago se dan de beber\n      a las mujeres durante el parto. También sus hojas y brotes tiernos sirven de alimento para\n      ganado y cuyes.","propagacion":"","images":["/resources/img/arboles-105_0.jpg","/resources/img/arboles-105_1.jpg","/resources/img/arboles-105_2.jpg"],"slug":"virgen-chilca"},{"page":106,"original":"106   ARBUSTOS NATIVOS\n\n\n\n\n                                     Familia: Asteraceae\n                                              Chilca\n\n                              Nombre científico: Baccharis latifolia (Ruiz & Pav.) Pers.\n                      Otros nombres comunes: “chilca blanca”, “chilca larga”\n\n      Hábito: Arbusto de 2 a 4 m de altura, tallos cilíndricos, corteza externa escamosa de color\n      marrón obscuro; abundante ramificación que nace desde la base, follaje verde oscuro resi-\n      noso.\n\n      Hojas: Simples, alternas, esparcidas en las ramitas terminales, de textura semicoriácea,\n      sostenidas por peciolos de 1 a 3 cm de largo. Lámina lanceolada o frecuentemente ovado\n      lanceolada de 5 a 15 cm de largo por 1,5 a 6 cm de ancho, ápice de agudo a ligeramente\n      acuminado, base cuneiforme y borde aserrado, haz verde oscuro brillante, envés verde claro\n      resinoso con tres nervios sobresalientes.\n\n      Flores: Unisexuales dispuestas en individuos diferentes (plantas dioicas). Cabezuelas mas-\n      culinas discoides, que portan 20 a 30 flósculos de 0,5 cm de longitud, corola tubular cremo-\n      sa de 0,3 cm de largo provista de 5 lóbulos reflexos, 5 estambres con las anteras soldadas\n      que forman un tubo que rodea parte del estilo, filamentos delgados insertos en la base\n      de los lóbulos de la corola, estilo con pelos dispersos. Cabezuelas femeninas compuestas\n      por 30 a 40 flores de 0,4 cm de largo, corola filiforme con el limbo truncado con diminutos\n      dientes apicales; estilo compuesto con dos ramas lineares; papus uniseriado de pocos pelos\n      blanquecinos; ovario ínfero de 0,1 cm de longitud.\n\n      Fruto: Una cipsela negra con papus de pelos blancos, delgados y escabrosos.\n\n      Distribución y ecología: Se distribuye en Sudamérica desde Argentina hasta Venezuela. En\n      nuestro país crece en la región andina entre los 1000 y 3000 m de altitud. En los márgenes\n      de los ríos de Cuenca es una de las especies más abundantes en sitios abiertos y taludes\n      degradados.\n\n      Es una especie pionera que vive en variadas condiciones de clima y suelo, comportándose\n      bien en suelos arcillosos limosos donde haya ambientes húmedos (Spier & Biederbick, 1980),\n      se adapta bien en suelos pedregosos y profundos (Loján, 1992). Es frecuente en bordes de\n      caminos, cercas de terrenos agrícolas, taludes de caminos y márgenes de ríos y quebradas.\n\n      Usos tradicionales: Es una especie importante en agroforesteria, debido a su rápido cre-\n      cimiento, su capacidad de rebrote, su tolerancia a la sequía y heladas (Carlson y Añazco,\n      1990). También es una especie melífera empleada en apicultura (García & Tello, 1988). En las\n      comunidades de El Carmen y Jadán sus hojas en emplastos se emplean para aliviar golpes\n      y torceduras; mezcladas con grasa de borrego se emplea para la debilidad de los huesos.\n\n      Propagación: Su regeneración natural es muy buena, por lo cual se pueden extraer plántu-\n      las para programas de reforestación. En viveros se propaga mediante semillas.\n","familia":"Asteraceae\n","nombre":"Chilca","descripcíon":"","otros_nombres_comunes":["chilca blanca","chilca larga"],"nombre_cientifica":"Baccharis latifolia (Ruiz & Pav.) Pers.","habito":" Arbusto de 2 a 4 m de altura, tallos cilíndricos, corteza externa escamosa de color\n      marrón obscuro; abundante ramificación que nace desde la base, follaje verde oscuro resi-\n      noso.","hojas":"Simples, alternas, esparcidas en las ramitas terminales, de textura semicoriácea,\n      sostenidas por peciolos de 1 a 3 cm de largo. Lámina lanceolada o frecuentemente ovado\n      lanceolada de 5 a 15 cm de largo por 1,5 a 6 cm de ancho, ápice de agudo a ligeramente\n      acuminado, base cuneiforme y borde aserrado, haz verde oscuro brillante, envés verde claro\n      resinoso con tres nervios sobresalientes.","flores":"Unisexuales dispuestas en individuos diferentes (plantas dioicas). Cabezuelas mas-\n      culinas discoides, que portan 20 a 30 flósculos de 0,5 cm de longitud, corola tubular cremo-\n      sa de 0,3 cm de largo provista de 5 lóbulos reflexos, 5 estambres con las anteras soldadas\n      que forman un tubo que rodea parte del estilo, filamentos delgados insertos en la base\n      de los lóbulos de la corola, estilo con pelos dispersos. Cabezuelas femeninas compuestas\n      por 30 a 40 flores de 0,4 cm de largo, corola filiforme con el limbo truncado con diminutos\n      dientes apicales; estilo compuesto con dos ramas lineares; papus uniseriado de pocos pelos\n      blanquecinos; ovario ínfero de 0,1 cm de longitud.","fruta":"Una cipsela negra con papus de pelos blancos, delgados y escabrosos.","distribucion_y_ecologia":"Se distribuye en Sudamérica desde Argentina hasta Venezuela. En\n      nuestro país crece en la región andina entre los 1000 y 3000 m de altitud. En los márgenes\n      de los ríos de Cuenca es una de las especies más abundantes en sitios abiertos y taludes\n      degradados.","usos_tradicionales":"Es una especie importante en agroforesteria, debido a su rápido cre-\n      cimiento, su capacidad de rebrote, su tolerancia a la sequía y heladas (Carlson y Añazco,\n      1990). También es una especie melífera empleada en apicultura (García & Tello, 1988). En las\n      comunidades de El Carmen y Jadán sus hojas en emplastos se emplean para aliviar golpes\n      y torceduras; mezcladas con grasa de borrego se emplea para la debilidad de los huesos.","propagacion":"Su regeneración natural es muy buena, por lo cual se pueden extraer plántu-\n      las para programas de reforestación. En viveros se propaga mediante semillas.","images":["/resources/img/arboles-107_0.jpg","/resources/img/arboles-107_1.jpg","/resources/img/arboles-107_2.jpg"],"slug":"chilca"},{"page":108,"original":"108   ARBUSTOS NATIVOS\n\n\n\n\n                                     Familia: Asteraceae\n                                              Shiñán\n\n                              Nombre científico: Barnadesia arborea Kunth\n                      Otros nombres comunes: “espino”\n\n      Hábito: Arbusto de 1 a 4 m de altura, tallos cilíndricos armados, ramificación abierta con\n      espinas, corteza externa de color café glabra o tomentosa.\n\n      Hojas: Simples, subsésiles, dispuestas en fascículos, con espinas axilares de 1 a 2,5 cm de\n      largo; lámina elíptica u ovada de 1,4 a 2,5 cm de largo por 0,5 a 1,5 cm de ancho, ápice agu-\n      do mucronado o pungente, base cuneada y margen entero; haz verde oscuro glabro, envés\n      verde pálido pubescente.\n\n      Flores: Dispuestas en cabezuelas o capítulos terminales sésiles o pedunculados, agrupados\n      en cimas de 2 a 4 cabezuelas por ramita; involucro cilíndrico o campanulado con 6 a 8 hile-\n      ras de filarias espinosas de color café; flores radiales rosadas o púrpuras de 3 cm de largo,\n      estambres con sus filamentos connados que forman un tubo de 0,8 cm de largo, anteras de\n      0,5 cm de largo, papus plumoso; flores centrales aproximadamente 16 por capítulo, corola\n      bilabiada de 1,7 cm de largo, filamentos de los estambres libres, anteras de 4 mm de largo,\n      papus de cerdas; ovario ínfero bicarpelar unilocular.\n\n      Fruto: Aquenios cilíndricos o turbinados.\n\n      Distribución y ecología: Se distribuye en los Andes del Ecuador y Perú entre 1500 y 4500\n      m de altitud (Jaramillo, 2013). En los ríos de Cuenca se encuentra en las zonas altas de los\n      ríos Tomebamba, Yanuncay y Tarqui; prefiere sitios abiertos y algo secos. Crece formando\n      pequeños matorrales densos con abundante ramificación entrecruzada que impide el paso\n      de animales y el crecimiento de otros arbustos, lo cual puede ser un mecanismo de defensa\n      contra la herbivoría y la competencia interespecífica (Serrano, 1996), También es frecuen-\n      te encontrar individuos aislados en zonas de pastizal. Sus flores son visitadas por el colibrí\n      Eriocnemis lucianii (King, 1987).\n\n      Usos tradicionales: La flor se emplea para los nervios, mal de aire y sobreparto; con sus\n      hojas y flores se preparan aguas para baños del parto. También sus flores sirven para tratar\n      problemas de hígado y riñones e inflamaciones musculares (Jaramillo, 2013). La planta ha\n      sido empleada en la conformación de cercas vivas para la protección de cultivos y su made-\n      ra sirve para leña (Serrano, 1996).\n\n      Propagación: Se recomienda propagar mediante semillas, para el efecto los frutos (cabe-\n      zuelas) deben ser cosechadas cuando están maduras, y puestas en bolsas y secadas al sol\n      en mallas para no perder las semillas, luego se deben extraer las semillas (aquenios) y lim-\n      piarlas mediante tamices para luego dejarlas en reposo durante unos 15 días, finalmente se\n      procede a realizar los almácigos en suelos ricos en materia orgánica. La germinación inicia\n      alrededor de los 8 días después de la siembra.\n","familia":"Asteraceae\n","nombre":"Shiñán","descripcíon":"","otros_nombres_comunes":["espino"],"nombre_cientifica":"Barnadesia arborea Kunth","habito":" Arbusto de 1 a 4 m de altura, tallos cilíndricos armados, ramificación abierta con\n      espinas, corteza externa de color café glabra o tomentosa.","hojas":"Simples, subsésiles, dispuestas en fascículos, con espinas axilares de 1 a 2,5 cm de\n      largo; lámina elíptica u ovada de 1,4 a 2,5 cm de largo por 0,5 a 1,5 cm de ancho, ápice agu-\n      do mucronado o pungente, base cuneada y margen entero; haz verde oscuro glabro, envés\n      verde pálido pubescente.","flores":"Dispuestas en cabezuelas o capítulos terminales sésiles o pedunculados, agrupados\n      en cimas de 2 a 4 cabezuelas por ramita; involucro cilíndrico o campanulado con 6 a 8 hile-\n      ras de filarias espinosas de color café; flores radiales rosadas o púrpuras de 3 cm de largo,\n      estambres con sus filamentos connados que forman un tubo de 0,8 cm de largo, anteras de\n      0,5 cm de largo, papus plumoso; flores centrales aproximadamente 16 por capítulo, corola\n      bilabiada de 1,7 cm de largo, filamentos de los estambres libres, anteras de 4 mm de largo,\n      papus de cerdas; ovario ínfero bicarpelar unilocular.","fruta":"Aquenios cilíndricos o turbinados.","distribucion_y_ecologia":"Se distribuye en los Andes del Ecuador y Perú entre 1500 y 4500\n      m de altitud (Jaramillo, 2013). En los ríos de Cuenca se encuentra en las zonas altas de los\n      ríos Tomebamba, Yanuncay y Tarqui; prefiere sitios abiertos y algo secos. Crece formando\n      pequeños matorrales densos con abundante ramificación entrecruzada que impide el paso\n      de animales y el crecimiento de otros arbustos, lo cual puede ser un mecanismo de defensa\n      contra la herbivoría y la competencia interespecífica (Serrano, 1996), También es frecuen-\n      te encontrar individuos aislados en zonas de pastizal. Sus flores son visitadas por el colibrí\n      Eriocnemis lucianii (King, 1987).","usos_tradicionales":"La flor se emplea para los nervios, mal de aire y sobreparto; con sus\n      hojas y flores se preparan aguas para baños del parto. También sus flores sirven para tratar\n      problemas de hígado y riñones e inflamaciones musculares (Jaramillo, 2013). La planta ha\n      sido empleada en la conformación de cercas vivas para la protección de cultivos y su made-\n      ra sirve para leña (Serrano, 1996).","propagacion":"Se recomienda propagar mediante semillas, para el efecto los frutos (cabe-\n      zuelas) deben ser cosechadas cuando están maduras, y puestas en bolsas y secadas al sol\n      en mallas para no perder las semillas, luego se deben extraer las semillas (aquenios) y lim-\n      piarlas mediante tamices para luego dejarlas en reposo durante unos 15 días, finalmente se\n      procede a realizar los almácigos en suelos ricos en materia orgánica. La germinación inicia\n      alrededor de los 8 días después de la siembra.","images":["/resources/img/arboles-109_0.jpg","/resources/img/arboles-109_1.jpg","/resources/img/arboles-109_2.jpg"],"slug":"shin"},{"page":110,"original":"110   ARBUSTOS NATIVOS\n\n\n\n\n                                     Familia: Asteraceae\n                                               Cótag\n\n                              Nombre científico: Ferreyranthus verbascifolius (Kunth)\n                                                 H. Rob. & Brettell\n\n\n\n\n      Hábito: Arbusto o árbol pequeño de 2 a 6 m de alto, ramificación abierta. Ramitas cuadran-\n      gulares, con la superficie blanca lanada, nudos visibles e internodios de 3 a 6 cm de largo.\n\n      Hojas: Simples, opuestas con sus bases fusionadas en una vaina de 1 cm de largo; lámina\n      ovada u oblongo-ovada de 6 a 20 cm de largo por 3 a 9 cm de ancho con el margen serru-\n      lado, ápice de agudo a estrechamente redondeado, haz bulloso, envés blanco tomentoso-\n      lanoso.\n\n      Flores: Reunidas en una panícula terminal de 10 a 30 cm de largo, compuesta por cabezue-\n      las de 6 a 8 mm de alto; involucro ampliamente campanulado conformado por 5 series de\n      brácteas. Flósculos radiales (10 a 12) de 4 mm de largo, flósculos centrales (10 a 25) de 5 mm\n      de largo, corolas amarillas.\n\n      Fruto: Una cipsela de 1,5 a 2 mm de largo provista de papus de 3 a 4 mm de largo.\n\n      Distribución y ecología: Esta especie está ampliamente distribuida en bosques andinos del\n      sur del Ecuador y norte del Perú entre 1000 y 3500 m de altitud. Crece bien en pendientes,\n      barrancos y se adapta bien a terrenos secos y pedregosos. Es un arbusto pionero con alta\n      producción de hojarasca por lo cual es recomendable en labores de conservación y recupe-\n      ración de suelos degradados. En las riberas del Yanuncay es una especie común aunque al\n      parecer no es una especie típica de ribera.\n\n      Usos tradicionales: Sus ramas y tallos se usan para leña y sus flores son asiduamente visita-\n      das por abejas, por lo que tiene un uso apícola (De la Torre et al, 2008).\n\n      Propagación: No se conoce sobre su propagación, pero su regeneración natural es buena.\n","familia":"Asteraceae\n","nombre":"Cótag","descripcíon":"","otros_nombres_comunes":[],"nombre_cientifica":"Ferreyranthus verbascifolius (Kunth)\n                                                 H. Rob. & Brettell","habito":" Arbusto o árbol pequeño de 2 a 6 m de alto, ramificación abierta. Ramitas cuadran-\n      gulares, con la superficie blanca lanada, nudos visibles e internodios de 3 a 6 cm de largo.","hojas":"Simples, opuestas con sus bases fusionadas en una vaina de 1 cm de largo; lámina\n      ovada u oblongo-ovada de 6 a 20 cm de largo por 3 a 9 cm de ancho con el margen serru-\n      lado, ápice de agudo a estrechamente redondeado, haz bulloso, envés blanco tomentoso-\n      lanoso.","flores":"Reunidas en una panícula terminal de 10 a 30 cm de largo, compuesta por cabezue-\n      las de 6 a 8 mm de alto; involucro ampliamente campanulado conformado por 5 series de\n      brácteas. Flósculos radiales (10 a 12) de 4 mm de largo, flósculos centrales (10 a 25) de 5 mm\n      de largo, corolas amarillas.","fruta":"Una cipsela de 1,5 a 2 mm de largo provista de papus de 3 a 4 mm de largo.","distribucion_y_ecologia":"Esta especie está ampliamente distribuida en bosques andinos del\n      sur del Ecuador y norte del Perú entre 1000 y 3500 m de altitud. Crece bien en pendientes,\n      barrancos y se adapta bien a terrenos secos y pedregosos. Es un arbusto pionero con alta\n      producción de hojarasca por lo cual es recomendable en labores de conservación y recupe-\n      ración de suelos degradados. En las riberas del Yanuncay es una especie común aunque al\n      parecer no es una especie típica de ribera.","usos_tradicionales":"Sus ramas y tallos se usan para leña y sus flores son asiduamente visita-\n      das por abejas, por lo que tiene un uso apícola (De la Torre et al, 2008).","propagacion":"No se conoce sobre su propagación, pero su regeneración natural es buena.","images":["/resources/img/arboles-111_0.jpg","/resources/img/arboles-111_1.jpg","/resources/img/arboles-111_2.jpg"],"slug":"ctag"},{"page":112,"original":"112   ARBUSTOS NATIVOS\n\n\n\n\n                                     Familia: Asteraceae\n                                               Nega\n\n                              Nombre científico: Liabum floribundum Less\n                      Otros nombres comunes: “niga”\n\n\n      Hábito: Arbusto o subarbusto de 2 a 4 m de alto, tallos hexagonales densamente ramifica-\n      dos, cubiertos por pelos suaves y densos.\n\n      Hojas: Simples opuestas, de base connada, peciolos ligeramente alados de 1 a 4 cm de lar-\n      go, lámina ovada o deltoide de 4 a 12 cm de largo por 2 a 8 cm de ancho, base de cuneada\n      a truncada, ápice acuminado y margen serrulado, haz verde oscuro rugoso y áspero, envés\n      plateado tomentoso lanado, con tres nervios prominentes que emergen cerca a la base.\n\n      Flores: Arregladas en capítulos que conforma cimas terminales densas, pedicelos de 1 a 4\n      cm de largo, capítulos heterógamos radiales, campanulados, involucro conformado por 4\n      a 5 series de brácteas lanceoladas de color verde, tomentosas en la base; 25 a 30 flósculos\n      radiales de corola tubular amarilla con pelos suaves en la base; 20 a 30 flores centrales de\n      corola infundibuliforme amarilla, anteras fimbriadas en la base, ramas del estilo largas.\n\n      Fruto: Aquenio 10 – costado de 1 mm de largo, vilano de 2 series de cerdas blancas.\n\n      Distribución y ecología: Se distribuye en los Andes del Ecuador y Perú, entre 600 y 3000 m\n      de altitud. En nuestro país ha sido registrada en las provincias de Pichincha, Tungurahua,\n      Bolívar, Chimborazo, Cañar, Azuay, Loja y Pastaza (W TRÓPICOS, 2014). En los márgenes de\n      los ríos de Cuenca es poco frecuente, y ha sido localizada en los sectores de Barabón, San\n      Joaquín y Sayausí. Crece en sitios húmedos y protegidos, en bordes de quebradas y ríos\n      pequeños. Sus flores son visitadas por varias especies de mariposas, las mismas que depo-\n      sitan sus huevos en sus hojas, que luego sirven de alimento para las larvas que a veces los\n      defolian completamente.\n\n      Usos tradicionales: Se usa como forraje para cuyes y vacas.\n\n      Propagación: Se recomienda propagarlo mediante división de matas y semillas.\n","familia":"Asteraceae\n","nombre":"Nega","descripcíon":"","otros_nombres_comunes":["niga"],"nombre_cientifica":"Liabum floribundum Less","habito":" Arbusto o subarbusto de 2 a 4 m de alto, tallos hexagonales densamente ramifica-\n      dos, cubiertos por pelos suaves y densos.","hojas":"Simples opuestas, de base connada, peciolos ligeramente alados de 1 a 4 cm de lar-\n      go, lámina ovada o deltoide de 4 a 12 cm de largo por 2 a 8 cm de ancho, base de cuneada\n      a truncada, ápice acuminado y margen serrulado, haz verde oscuro rugoso y áspero, envés\n      plateado tomentoso lanado, con tres nervios prominentes que emergen cerca a la base.","flores":"Arregladas en capítulos que conforma cimas terminales densas, pedicelos de 1 a 4\n      cm de largo, capítulos heterógamos radiales, campanulados, involucro conformado por 4\n      a 5 series de brácteas lanceoladas de color verde, tomentosas en la base; 25 a 30 flósculos\n      radiales de corola tubular amarilla con pelos suaves en la base; 20 a 30 flores centrales de\n      corola infundibuliforme amarilla, anteras fimbriadas en la base, ramas del estilo largas.","fruta":"Aquenio 10 – costado de 1 mm de largo, vilano de 2 series de cerdas blancas.","distribucion_y_ecologia":"Se distribuye en los Andes del Ecuador y Perú, entre 600 y 3000 m\n      de altitud. En nuestro país ha sido registrada en las provincias de Pichincha, Tungurahua,\n      Bolívar, Chimborazo, Cañar, Azuay, Loja y Pastaza (W TRÓPICOS, 2014). En los márgenes de\n      los ríos de Cuenca es poco frecuente, y ha sido localizada en los sectores de Barabón, San\n      Joaquín y Sayausí. Crece en sitios húmedos y protegidos, en bordes de quebradas y ríos\n      pequeños. Sus flores son visitadas por varias especies de mariposas, las mismas que depo-\n      sitan sus huevos en sus hojas, que luego sirven de alimento para las larvas que a veces los\n      defolian completamente.","usos_tradicionales":"Se usa como forraje para cuyes y vacas.","propagacion":"Se recomienda propagarlo mediante división de matas y semillas.","images":["/resources/img/arboles-113_0.jpg","/resources/img/arboles-113_1.jpg","/resources/img/arboles-113_2.jpg"],"slug":"nega"},{"page":114,"original":"114   ARBUSTOS NATIVOS\n\n\n\n\n                                     Familia: Asteraceae\n                                              Bayán\n\n                              Nombre científico: Monactis holwayae (S.F. Blake) H. Rob\n                      Otros nombres comunes: “vallalín”\n\n\n      Hábito: Arbusto o árbol pequeño de 3 a 5 m de alto, tallo café ligeramente aristado, ramifi-\n      cación abierta en zig-zag, ramitas puberulentas.\n\n      Hojas: Simples, alternas, peciolos de 1 a 2 cm de largo; lámina de ovada a ovado-lanceolada\n      de 7,5 a 19,5 cm de largo por 2,8 a 8 cm de ancho, base decurrente o estrechamente aguda,\n      ápice acuminado y margen entero o serrulado; haz verde oscuro escabroso, envés verde\n      oliva tomentoso con 3 nervios principales que emergen encima de la base.\n\n      Flores: Dispuestas en capítulos que conforman cimas terminales compuestas; capítulos he-\n      terógamos radiados de 0,7 cm de alto, involucro con 10 a 12 brácteas dispuestas en dos\n      series, brácteas oblongas de 0,4 cm de largo por 0,1 cm de ancho; flósculos centrales de\n      6 a 12 por capítulo, corola verde cremosa, tubular campanulada de 0,4 cm de largo, con 5\n      lóbulos reflexos; anteras de color negro; estilo inmerso en el nectario, estilo con dos ramas\n      estigmáticas.\n\n      Fruto: Un aquenio fusiforme de 3 mm de largo, papus con una escama.\n\n      Distribución y ecología: Especie endémica de los Andes del sur del Ecuador, localizada en\n      las provincias de Azuay, Cañar y Loja, entre 2500 y 3200 m de altitud. En los ríos de Cuenca\n      es una especie rara, registrándose pocos individuos en el río Tomebamba dentro de la zona\n      urbana de Cuenca. Esta especie crece en bosques secundarios, áreas disturbadas y bordes\n      de quebradas. Sus fragantes flores atraen a una gran variedad de insectos que ayudan en\n      su polinización.\n\n      Usos tradicionales: Sus ramas y flores en decocción son empleadas para baños calientes\n      para las mujeres después del parto.\n\n      Propagación: Se recomienda propagarla mediante semillas.\n","familia":"Asteraceae\n","nombre":"Bayán","descripcíon":"","otros_nombres_comunes":["vallalín"],"nombre_cientifica":"Monactis holwayae (S.F. Blake) H. Rob","habito":" Arbusto o árbol pequeño de 3 a 5 m de alto, tallo café ligeramente aristado, ramifi-\n      cación abierta en zig-zag, ramitas puberulentas.","hojas":"Simples, alternas, peciolos de 1 a 2 cm de largo; lámina de ovada a ovado-lanceolada\n      de 7,5 a 19,5 cm de largo por 2,8 a 8 cm de ancho, base decurrente o estrechamente aguda,\n      ápice acuminado y margen entero o serrulado; haz verde oscuro escabroso, envés verde\n      oliva tomentoso con 3 nervios principales que emergen encima de la base.","flores":"Dispuestas en capítulos que conforman cimas terminales compuestas; capítulos he-\n      terógamos radiados de 0,7 cm de alto, involucro con 10 a 12 brácteas dispuestas en dos\n      series, brácteas oblongas de 0,4 cm de largo por 0,1 cm de ancho; flósculos centrales de\n      6 a 12 por capítulo, corola verde cremosa, tubular campanulada de 0,4 cm de largo, con 5\n      lóbulos reflexos; anteras de color negro; estilo inmerso en el nectario, estilo con dos ramas\n      estigmáticas.","fruta":"Un aquenio fusiforme de 3 mm de largo, papus con una escama.","distribucion_y_ecologia":"Especie endémica de los Andes del sur del Ecuador, localizada en\n      las provincias de Azuay, Cañar y Loja, entre 2500 y 3200 m de altitud. En los ríos de Cuenca\n      es una especie rara, registrándose pocos individuos en el río Tomebamba dentro de la zona\n      urbana de Cuenca. Esta especie crece en bosques secundarios, áreas disturbadas y bordes\n      de quebradas. Sus fragantes flores atraen a una gran variedad de insectos que ayudan en\n      su polinización.","usos_tradicionales":"Sus ramas y flores en decocción son empleadas para baños calientes\n      para las mujeres después del parto.","propagacion":"Se recomienda propagarla mediante semillas.","images":["/resources/img/arboles-115_0.jpg","/resources/img/arboles-115_1.jpg","/resources/img/arboles-115_2.jpg"],"slug":"bayn"},{"page":116,"original":"116   ARBUSTOS NATIVOS\n\n\n\n\n                                    Familia: Cleomaceae\n                                          Borreguito\n\n                              Nombre científico: Cleome anomala Kunth\n\n\n\n\n      Hábito: Arbusto o arbolito de hasta 4 m de altura, tallos cilíndricos de madera suave, con\n      ramificación laxa.\n\n      Hojas: Largamente pecioladas, palmaticompuestas con 5 foliolos de forma elíptica oblonga\n      de 5 a 15 cm de largo por 2 a 5 cm de ancho, con abundante indumento de pelos estrellados.\n\n      Flores: Dispuestas en racimos alargados de hasta 40 cm de longitud, subtendidas por brac-\n      téolas foliáceas redondeadas, cáliz con 4 sépalos pequeños de forma ovada, corola con 4\n      pétalos libres blancos y caedizos, androceo compuesto por 6 estambres con filamentos muy\n      largos y delgados, ovario súpero con dos lóculos.\n\n      Fruto: Silicua estipitada con numerosas semillas.\n\n      Distribución y ecología: Esta especie se distribuye en la región andina de Venezuela, Co-\n      lombia y Ecuador, entre 1500 y 3500 m de altitud. En el Ecuador ha sido registrada en to-\n      das las provincias andinas. Es una especie que crece formando colonias en los bordes de\n      quebradas y sitios húmedos. En las riberas del río Yanuncay, es más bien una especie rara\n      registrándose únicamente dos individuos en la zona urbana de Cuenca. También existen al-\n      gunos individuos cultivados en el jardín etnobotánico de Pumapungo. Presenta una buena\n      capacidad de rebrote y su regeneración natural es muy escasa.\n\n      Usos tradicionales: Sus hojas muestran propiedades rubefacientes y sus semillas se em-\n      plean para tratar problemas de encías, para el efecto éstas deben ser amarradas a las mis-\n      mas; también ha sido empleada para tratar los espasmos (De la Torre et al, 2008).\n\n      Propagación: Puede propagarse mediante esquejes.\n","familia":"Cleomaceae\n","nombre":"Borreguito","descripcíon":"","otros_nombres_comunes":[],"nombre_cientifica":"Cleome anomala Kunth","habito":" Arbusto o arbolito de hasta 4 m de altura, tallos cilíndricos de madera suave, con\n      ramificación laxa.","hojas":"Largamente pecioladas, palmaticompuestas con 5 foliolos de forma elíptica oblonga\n      de 5 a 15 cm de largo por 2 a 5 cm de ancho, con abundante indumento de pelos estrellados.","flores":"Dispuestas en racimos alargados de hasta 40 cm de longitud, subtendidas por brac-\n      téolas foliáceas redondeadas, cáliz con 4 sépalos pequeños de forma ovada, corola con 4\n      pétalos libres blancos y caedizos, androceo compuesto por 6 estambres con filamentos muy\n      largos y delgados, ovario súpero con dos lóculos.","fruta":"Silicua estipitada con numerosas semillas.","distribucion_y_ecologia":"Esta especie se distribuye en la región andina de Venezuela, Co-\n      lombia y Ecuador, entre 1500 y 3500 m de altitud. En el Ecuador ha sido registrada en to-\n      das las provincias andinas. Es una especie que crece formando colonias en los bordes de\n      quebradas y sitios húmedos. En las riberas del río Yanuncay, es más bien una especie rara\n      registrándose únicamente dos individuos en la zona urbana de Cuenca. También existen al-\n      gunos individuos cultivados en el jardín etnobotánico de Pumapungo. Presenta una buena\n      capacidad de rebrote y su regeneración natural es muy escasa.","usos_tradicionales":"Sus hojas muestran propiedades rubefacientes y sus semillas se em-\n      plean para tratar problemas de encías, para el efecto éstas deben ser amarradas a las mis-\n      mas; también ha sido empleada para tratar los espasmos (De la Torre et al, 2008).","propagacion":"Puede propagarse mediante esquejes.","images":["/resources/img/arboles-117_0.jpg","/resources/img/arboles-117_1.jpg","/resources/img/arboles-117_2.jpg","/resources/img/arboles-117_3.jpg"],"slug":"borreguito"},{"page":118,"original":"118   ARBUSTOS NATIVOS\n\n\n\n\n                                    Familia: Coriariaceae\n                                                Piñán\n\n                              Nombre científico: Coriaria ruscifolia L.\n                      Otros nombres comunes: “shanshi”, “tinta”\n\n      Hábito: Arbusto rastrero, con raíces fibrosas provistas de nódulos fijadores de nitrógeno,\n      tallos cuadrangulares con ramas principales alargadas de 4 m o más de longitud; de cada\n      rama principal emergen numerosas ramitas laterales cortas, provistas de abundante folla-\n      je de hojas pequeñas que en conjunto conforman una mata robusta y densa.\n\n      Hojas: Simples, opuestas de textura semicoriácea; lámina ovada en la hojas de los ejes prin-\n      cipales y de elíptica a lanceolada en las hojas de las ramas laterales de 0,5 a 3,1 cm de largo\n      por 0,2 a 1,6 cm de ancho, ápice de agudo a mucronado, base cordada, margen entero, haz\n      verde oscuro, envés verde pálido con 3 nervios principales basales.\n\n      Flores: Agrupadas en racimos laterales de 6 a 15 cm de longitud, raquis aristado pubescente\n      de color rojizo. Flores bisexuales, regulares de 0,2 cm de diámetro, sostenida por pedicelos\n      de 0,3 a 0,6 cm de longitud, con pequeñas brácteas lanceoladas de 0,2 cm de largo por\n      0,1 cm, de ancho; cáliz con sépalos ovados verde rojizos de 0,15 a 0,2 cm de largo por 0,1 a\n      0,15 cm de ancho, corola con 5 pétalos ovados de 0,08 a 0,1 cm de largo por 0,06 a 0,08 cm\n      de ancho; androceo constituido por 10 estambres dispuestos en dos verticilos, filamentos\n      filiformes, anteras oblongas verde amarillentas; gineceo conformado por 5 pistilos simples,\n      estilos fasciculados de color púrpura, óvulos solitarios pendientes.\n\n      Fruto: Pseudodrupa de color púrpura con los pétalos acrescentes, engrosados y carnosos.\n\n      Distribución y ecología: Especie de amplia distribución desde México hasta Perú, Nueva\n      Guinea y Nueva Zelandia. En nuestro país está ampliamente distribuida en la sierra entre\n      1000 y 4500 m de altitud (Skog, 1987). En la región interandina es una especie muy común\n      especialmente en hábitats abiertos, se adapta a variados tipos de suelo; pero prefiere suelos\n      areno limosos. Es abundante en taludes de carreteras, cárcavas y márgenes de quebradas y\n      ríos. En las riberas de los ríos de Cuenca ha sido observada en barrancos y taludes crecien-\n      do junto a otras especies arbustivas como Baccharis latifolia, Dodonaea viscosa y Spartium\n      junceum.\n\n      Usos tradicionales: De sus frutos se obtiene una tinta de color violáceo que da en negro y\n      tiene la fama de ser indeleble (Cordero, 1984). Debido a su alto contenido de glucósidos, se\n      usa como alucinógeno; pero puede causar envenenamiento y muerte. Debido a su rápido\n      crecimiento y su capacidad de fijar nitrógeno, es una especie idónea para programas de\n      recuperación de suelos y control de la erosión. En algunas comunidades campesinas de la\n      provincia del Azuay sus ramas y hojas se emplean como alimento para cuyes y ovejas.\n\n      Propagación: Se propaga mediante semillas, para el efecto se deben recolectar los frutos\n      maduros, secarlos de 6 a 8 días y sembrarlos directamente en el almácigo. La germinación\n      inicia luego de 3 a 4 semanas.\n","familia":"Coriariaceae\n","nombre":"Piñán","descripcíon":"","otros_nombres_comunes":["shanshi","tinta"],"nombre_cientifica":"Coriaria ruscifolia L.","habito":" Arbusto rastrero, con raíces fibrosas provistas de nódulos fijadores de nitrógeno,\n      tallos cuadrangulares con ramas principales alargadas de 4 m o más de longitud; de cada\n      rama principal emergen numerosas ramitas laterales cortas, provistas de abundante folla-\n      je de hojas pequeñas que en conjunto conforman una mata robusta y densa.","hojas":"Simples, opuestas de textura semicoriácea; lámina ovada en la hojas de los ejes prin-\n      cipales y de elíptica a lanceolada en las hojas de las ramas laterales de 0,5 a 3,1 cm de largo\n      por 0,2 a 1,6 cm de ancho, ápice de agudo a mucronado, base cordada, margen entero, haz\n      verde oscuro, envés verde pálido con 3 nervios principales basales.","flores":"Agrupadas en racimos laterales de 6 a 15 cm de longitud, raquis aristado pubescente\n      de color rojizo. Flores bisexuales, regulares de 0,2 cm de diámetro, sostenida por pedicelos\n      de 0,3 a 0,6 cm de longitud, con pequeñas brácteas lanceoladas de 0,2 cm de largo por\n      0,1 cm, de ancho; cáliz con sépalos ovados verde rojizos de 0,15 a 0,2 cm de largo por 0,1 a\n      0,15 cm de ancho, corola con 5 pétalos ovados de 0,08 a 0,1 cm de largo por 0,06 a 0,08 cm\n      de ancho; androceo constituido por 10 estambres dispuestos en dos verticilos, filamentos\n      filiformes, anteras oblongas verde amarillentas; gineceo conformado por 5 pistilos simples,\n      estilos fasciculados de color púrpura, óvulos solitarios pendientes.","fruta":"Pseudodrupa de color púrpura con los pétalos acrescentes, engrosados y carnosos.","distribucion_y_ecologia":"Especie de amplia distribución desde México hasta Perú, Nueva\n      Guinea y Nueva Zelandia. En nuestro país está ampliamente distribuida en la sierra entre\n      1000 y 4500 m de altitud (Skog, 1987). En la región interandina es una especie muy común\n      especialmente en hábitats abiertos, se adapta a variados tipos de suelo; pero prefiere suelos\n      areno limosos. Es abundante en taludes de carreteras, cárcavas y márgenes de quebradas y\n      ríos. En las riberas de los ríos de Cuenca ha sido observada en barrancos y taludes crecien-\n      do junto a otras especies arbustivas como Baccharis latifolia, Dodonaea viscosa y Spartium\n      junceum.","usos_tradicionales":"De sus frutos se obtiene una tinta de color violáceo que da en negro y\n      tiene la fama de ser indeleble (Cordero, 1984). Debido a su alto contenido de glucósidos, se\n      usa como alucinógeno; pero puede causar envenenamiento y muerte. Debido a su rápido\n      crecimiento y su capacidad de fijar nitrógeno, es una especie idónea para programas de\n      recuperación de suelos y control de la erosión. En algunas comunidades campesinas de la\n      provincia del Azuay sus ramas y hojas se emplean como alimento para cuyes y ovejas.","propagacion":"Se propaga mediante semillas, para el efecto se deben recolectar los frutos\n      maduros, secarlos de 6 a 8 días y sembrarlos directamente en el almácigo. La germinación\n      inicia luego de 3 a 4 semanas.","images":["/resources/img/arboles-119_0.jpg","/resources/img/arboles-119_1.jpg","/resources/img/arboles-119_2.jpg"],"slug":"pin"},{"page":120,"original":"120   ARBUSTOS NATIVOS\n\n\n\n\n                                      Familia: Fabaceae\n                                           Guarango\n\n                              Nombre científico: Mimosa andina Benth.\n\n\n\n\n      Hábito: Arbusto o árbol pequeño de 3 a 6 m de alto, tronco cilíndrico tortuoso con abun-\n      dante ramificación alterna, con espinas curvadas de 1 cm de largo, copa globosa a irregular;\n      follaje de color verde oliva.\n\n      Hojas: Compuestas, con 2 a 4 pares de pinnas, cada pinna contiene entre 6 y 8 pares de\n      foliolos oblongos, sésiles de 0,6–1,2 cm de largo x 0,2–0,4 de ancho; estípulas lineares pre-\n      sentes, ejes primarios y secundarios pulvinulados, con pequeños pelos blancos dispersos.\n\n      Flores: Dispuestas en racimos terminales de 4 a 12 cm de largo, compuestos por cabezuelas\n      globosas de 0,8–1,2 cm de diámetro. Flores pequeñas, cáliz inconspicuo cupuliforme de 1\n      mm de largo; corola cremosa, tubular- campanulada de 0,25 a 0,35 cm de largo con 5 lóbu-\n      los valvados; androceo conformado por 10 estambres de 0,3 a 0,6 cm de largo, filamentos\n      blancos connados en la base, anteras dorsifijas café amarillentas; ovario con un carpelo y un\n      lóculo, estilo y estigma terminal.\n\n      Fruto: Una legumbre plana ligeramente curvada, de 3,5–6 cm de largo, de color café verdo-\n      sa cuando está madura; cada legumbre contiene entre 4 a 10 semillas ovoides de 0,6 x 0,5\n      cm, de color café marrón.\n\n      Distribución y ecología: Especie endémica del Ecuador, se encuentra en los valles inte-\n      randinos desde Chimborazo hasta Azuay, es muy común en los valles de Cuenca-Azogues\n      y Paute-Gualaceo (Neill & Ulloa, 2011). En Cuenca es abundante en los sectores de Chau-\n      llabamba, Nulti, Pacha, Llacao y Machángara en la parte oriental de la ciudad. La Mimosa\n      andina es una especie propia de los valles secos interandinos, se adapta bien a terrenos\n      pobres y pedregosos, es frecuente observarla en taludes de carretera, barrancos y márge-\n      nes de caminos, quebradas y bajo plantaciones de eucaliptos. Posee capacidad de rebrote\n      y su regeneración natural es buena; sus flores son visitadas por abejas y colibríes. Debido\n      a su limitado rango de distribución geográfica esta especie ha sido catalogada como vul-\n      nerable a la extinción (León – Yánez et al, 2011).\n\n      Usos tradicionales: Sus ramas y troncos sirven para leña, sus hojas se emplean como forraje\n      para ovejas y chivos, y la planta se usa como cerca viva. Medicinalmente sus flores en infu-\n      sión se emplean para la tos (De la Torre et al, 2008).\n\n      Propagación: Se puede propagar mediante semillas, para lo cual es necesario un tratamien-\n      to pregerminativo de inmersión de las semillas en agua hirviente durante 5 minutos, luego\n      dejarla en remojo durante 48 horas en agua fría, la germinación inicia alrededor de los 20\n      días después de la siembra.\n","familia":"Fabaceae\n","nombre":"Guarango","descripcíon":"","otros_nombres_comunes":[],"nombre_cientifica":"Mimosa andina Benth.","habito":" Arbusto o árbol pequeño de 3 a 6 m de alto, tronco cilíndrico tortuoso con abun-\n      dante ramificación alterna, con espinas curvadas de 1 cm de largo, copa globosa a irregular;\n      follaje de color verde oliva.","hojas":"Compuestas, con 2 a 4 pares de pinnas, cada pinna contiene entre 6 y 8 pares de\n      foliolos oblongos, sésiles de 0,6–1,2 cm de largo x 0,2–0,4 de ancho; estípulas lineares pre-\n      sentes, ejes primarios y secundarios pulvinulados, con pequeños pelos blancos dispersos.","flores":"Dispuestas en racimos terminales de 4 a 12 cm de largo, compuestos por cabezuelas\n      globosas de 0,8–1,2 cm de diámetro. Flores pequeñas, cáliz inconspicuo cupuliforme de 1\n      mm de largo; corola cremosa, tubular- campanulada de 0,25 a 0,35 cm de largo con 5 lóbu-\n      los valvados; androceo conformado por 10 estambres de 0,3 a 0,6 cm de largo, filamentos\n      blancos connados en la base, anteras dorsifijas café amarillentas; ovario con un carpelo y un\n      lóculo, estilo y estigma terminal.","fruta":"Una legumbre plana ligeramente curvada, de 3,5–6 cm de largo, de color café verdo-\n      sa cuando está madura; cada legumbre contiene entre 4 a 10 semillas ovoides de 0,6 x 0,5\n      cm, de color café marrón.","distribucion_y_ecologia":"Especie endémica del Ecuador, se encuentra en los valles inte-\n      randinos desde Chimborazo hasta Azuay, es muy común en los valles de Cuenca-Azogues\n      y Paute-Gualaceo (Neill & Ulloa, 2011). En Cuenca es abundante en los sectores de Chau-\n      llabamba, Nulti, Pacha, Llacao y Machángara en la parte oriental de la ciudad. La Mimosa\n      andina es una especie propia de los valles secos interandinos, se adapta bien a terrenos\n      pobres y pedregosos, es frecuente observarla en taludes de carretera, barrancos y márge-\n      nes de caminos, quebradas y bajo plantaciones de eucaliptos. Posee capacidad de rebrote\n      y su regeneración natural es buena; sus flores son visitadas por abejas y colibríes. Debido\n      a su limitado rango de distribución geográfica esta especie ha sido catalogada como vul-\n      nerable a la extinción (León – Yánez et al, 2011).","usos_tradicionales":"Sus ramas y troncos sirven para leña, sus hojas se emplean como forraje\n      para ovejas y chivos, y la planta se usa como cerca viva. Medicinalmente sus flores en infu-\n      sión se emplean para la tos (De la Torre et al, 2008).","propagacion":"Se puede propagar mediante semillas, para lo cual es necesario un tratamien-\n      to pregerminativo de inmersión de las semillas en agua hirviente durante 5 minutos, luego\n      dejarla en remojo durante 48 horas en agua fría, la germinación inicia alrededor de los 20\n      días después de la siembra.","images":["/resources/img/arboles-121_0.jpg","/resources/img/arboles-121_1.jpg","/resources/img/arboles-121_2.jpg","/resources/img/arboles-121_3.jpg"],"slug":"guarango"},{"page":122,"original":"122   ARBUSTOS NATIVOS\n\n\n\n\n                                      Familia: Lamiaceae\n                                              Salviar\n\n                              Nombre científico: Salvia corrugata Vahl\n                      Otros nombres comunes: “matico”, “chilca azul”, “salvia real”\n\n\n      Hábito: Arbusto de 2 a 3 m de altura, tallos leñosos cuadrangulares, con abundante ramifi-\n      cación opuesta desde la base.\n\n      Hojas: Simples, opuestas de textura coriácea, lámina oblongo – lanceolada de 4 (7) 11 cm\n      de largo por 1 (1,5) 2,5 cm de ancho, margen dentado y ápice acuminado; haz verde claro\n      rugoso, envés de color café claro pubescente.\n\n      Flores: Reunidas en racimos verticilados de 3 a 7 cm de largo, con un promedio 10 flores\n      por inflorescencia. Flores zigomorfas, cáliz persistente, tubular campanulado, bilabiado de\n      color verde con manchas púrpuras; corola azul violeta, fuertemente bilabiada, tubo curva-\n      do, labio superior galeado entero, labio inferior triobado. Androceo conformado por dos\n      estambres epipétalos; ovario súpero provisto de un largo estilo y un estigma bífido.\n\n      Fruto: Conformado por 4 pequeñas nueces de color café.\n\n      Distribución y ecología: Se distribuye en los Andes de Colombia, Ecuador y Perú entre 1000\n      y 3500 m de altitud. En nuestro país ha sido registrada en las provincias de Bolívar, Tungu-\n      rahua, Chimborazo, Cañar, Azuay y Loja entre 900 y 3500 m de altitud (W Tropicos, 2014). Es\n      una especie común en matorrales húmedos andinos. En las riberas de los ríos de Cuenca ha\n      sido localizada en las partes altas de los ríos Tomebamba, Yanuncay, Tarqui y Machángara,\n      se establece bien en suelos pedregosos y sueltos. Sus flores son visitadas por varias especies\n      de colibríes. Las poblaciones locales de Salvia corrugata, producen flores durante todo el\n      año con mayor intensidad durante los meses de marzo, abril y mayo.\n\n      Usos tradicionales: En las comunidades cercanas al Bosque Protector Aguarongo esta es-\n      pecie se usa para limpias de mal de aire y en baños para el sobreparto; sus hojas se usan\n      como alimento de cuyes y sus ramas se usan como leña. Debido a su capacidad de rebrote\n      y crecimiento rápido se recomienda usarla en setos vivos, linderos y cortinas rompevientos\n      (Serrano, 1996).\n\n      Propagación: Se puede propagarla mediante esquejes semimaduros y división de matas,\n      que deben ser plantadas en un sustrato de tierra negra, materia orgánica y arena en propor-\n      ciones de 50 % 30 % y 20 % respectivamente.\n","familia":"Lamiaceae\n","nombre":"Salviar","descripcíon":"","otros_nombres_comunes":["matico","chilca azul","salvia real"],"nombre_cientifica":"Salvia corrugata Vahl","habito":" Arbusto de 2 a 3 m de altura, tallos leñosos cuadrangulares, con abundante ramifi-\n      cación opuesta desde la base.","hojas":"Simples, opuestas de textura coriácea, lámina oblongo – lanceolada de 4 (7) 11 cm\n      de largo por 1 (1,5) 2,5 cm de ancho, margen dentado y ápice acuminado; haz verde claro\n      rugoso, envés de color café claro pubescente.","flores":"Reunidas en racimos verticilados de 3 a 7 cm de largo, con un promedio 10 flores\n      por inflorescencia. Flores zigomorfas, cáliz persistente, tubular campanulado, bilabiado de\n      color verde con manchas púrpuras; corola azul violeta, fuertemente bilabiada, tubo curva-\n      do, labio superior galeado entero, labio inferior triobado. Androceo conformado por dos\n      estambres epipétalos; ovario súpero provisto de un largo estilo y un estigma bífido.","fruta":"Conformado por 4 pequeñas nueces de color café.","distribucion_y_ecologia":"Se distribuye en los Andes de Colombia, Ecuador y Perú entre 1000\n      y 3500 m de altitud. En nuestro país ha sido registrada en las provincias de Bolívar, Tungu-\n      rahua, Chimborazo, Cañar, Azuay y Loja entre 900 y 3500 m de altitud (W Tropicos, 2014). Es\n      una especie común en matorrales húmedos andinos. En las riberas de los ríos de Cuenca ha\n      sido localizada en las partes altas de los ríos Tomebamba, Yanuncay, Tarqui y Machángara,\n      se establece bien en suelos pedregosos y sueltos. Sus flores son visitadas por varias especies\n      de colibríes. Las poblaciones locales de Salvia corrugata, producen flores durante todo el\n      año con mayor intensidad durante los meses de marzo, abril y mayo.","usos_tradicionales":"En las comunidades cercanas al Bosque Protector Aguarongo esta es-\n      pecie se usa para limpias de mal de aire y en baños para el sobreparto; sus hojas se usan\n      como alimento de cuyes y sus ramas se usan como leña. Debido a su capacidad de rebrote\n      y crecimiento rápido se recomienda usarla en setos vivos, linderos y cortinas rompevientos\n      (Serrano, 1996).","propagacion":"Se puede propagarla mediante esquejes semimaduros y división de matas,\n      que deben ser plantadas en un sustrato de tierra negra, materia orgánica y arena en propor-\n      ciones de 50 % 30 % y 20 % respectivamente.","images":["/resources/img/arboles-123_0.jpg","/resources/img/arboles-123_1.jpg","/resources/img/arboles-123_2.jpg"],"slug":"salviar"},{"page":124,"original":"124   ARBUSTOS NATIVOS\n\n\n\n\n                                     Familia: Lamiaceae\n                                     Quinde sungana\n\n                              Nombre científico: Salvia hirta Kunth\n                      Otros nombres comunes: “salvia roja”, “urcu quinde sungana”\n\n\n      Hábito: Arbusto de 1 a 3 m de altura, tallos nudosos cuadrangulares, ramificación opuesta y\n      abierta, ramitas terminales verdosas, con pubescencia blanquecina.\n\n      Hojas: Simples, opuesto-decusadas, peciolo acanalado de 1,5–3,5 cm de largo; lámina ova-\n      do-lanceolada de 4,2–0,4 cm de largo x 1,2–3,4 cm de ancho, base truncada, ápice acumina-\n      do y margen aserrado en la base y dentado en la parte apical; haz verde brillante ligeramen-\n      te áspero, envés verde pálido con pubescencia blanquecina dispersa.\n\n      Flores: Arregladas en racimos terminales de 4–12 cm de largo. Flores bisexuales, bilabiadas,\n      cáliz campanulado bilabiado de 0,9–1,2 cm de largo, verde oscuro; corola tubular bilabiada\n      de 2,5 – 3,8 cm de largo, de color rojo cubierta de pelos blanquecinos suaves; dos estam-\n      bres que sobresalen del tubo de la corola y que se disponen paralelos al labio superior de la\n      misma; ovario con la ginobase que forman un nectario, estilo largo y delgado con el ápice\n      bífido.\n\n      Fruto: Formado por 4 pequeñas nueces unidas en la base.\n\n      Distribución y ecología: Se distribuye en los Andes desde el Sur de Colombia hasta el norte\n      del Perú. En nuestro país ha sido registrada en las provincias de Tungurahua, Bolívar, Chim-\n      borazo, Cañar, Azuay, Loja y Guayas (Jorgensen y León-Yánez, 1999). En los márgenes de los\n      ríos de Cuenca se encuentra en las zonas altas de los ríos Yanuncay, Tomebamba y Tarqui,\n      crece en bordes de bosque y en vegetación secundaria; se establece bien en sitios húme-\n      dos con suelos sueltos y profundos; florece durante todo el año y sus flores son un recurso\n      fundamental para ciertas especies de colibríes como: Metallura tyrianthina, Rhamphomicron\n      microrhynchum, Colibrí coruscans y Lafresnaya labresnayi (Serrano, 1996). Sus nectarios pro-\n      ducen un líquido con una concentración de 23,4 % de néctar, el cual tiene un contenido de\n      azúcar de 3,04 mg (King, 1987).\n\n      Usos tradicionales: Sus flores en infusión son excelentes estimulantes, tónicos y antiespas-\n      módicos (Serrano, 1996).\n\n      Propagación: Se recomienda propagarla mediante esquejes semileñosos, para el efecto se\n      deben cortar esquejes de 20 a 25 cm de largo y 0,5 a 1 cm de diámetro. Para el transporte se\n      recomienda envolverlos en papel mojado y ponerlos en fundas plásticas y dejarlos reposar\n      doce horas, luego antes de plantarlos se recomienda untarles la base con miel de abeja para\n      estimular su enraizamiento.\n","familia":"Lamiaceae\n","nombre":"Quinde sungana","descripcíon":"","otros_nombres_comunes":["salvia roja","urcu quinde sungana"],"nombre_cientifica":"Salvia hirta Kunth","habito":" Arbusto de 1 a 3 m de altura, tallos nudosos cuadrangulares, ramificación opuesta y\n      abierta, ramitas terminales verdosas, con pubescencia blanquecina.","hojas":"Simples, opuesto-decusadas, peciolo acanalado de 1,5–3,5 cm de largo; lámina ova-\n      do-lanceolada de 4,2–0,4 cm de largo x 1,2–3,4 cm de ancho, base truncada, ápice acumina-\n      do y margen aserrado en la base y dentado en la parte apical; haz verde brillante ligeramen-\n      te áspero, envés verde pálido con pubescencia blanquecina dispersa.","flores":"Arregladas en racimos terminales de 4–12 cm de largo. Flores bisexuales, bilabiadas,\n      cáliz campanulado bilabiado de 0,9–1,2 cm de largo, verde oscuro; corola tubular bilabiada\n      de 2,5 – 3,8 cm de largo, de color rojo cubierta de pelos blanquecinos suaves; dos estam-\n      bres que sobresalen del tubo de la corola y que se disponen paralelos al labio superior de la\n      misma; ovario con la ginobase que forman un nectario, estilo largo y delgado con el ápice\n      bífido.","fruta":"Formado por 4 pequeñas nueces unidas en la base.","distribucion_y_ecologia":"Se distribuye en los Andes desde el Sur de Colombia hasta el norte\n      del Perú. En nuestro país ha sido registrada en las provincias de Tungurahua, Bolívar, Chim-\n      borazo, Cañar, Azuay, Loja y Guayas (Jorgensen y León-Yánez, 1999). En los márgenes de los\n      ríos de Cuenca se encuentra en las zonas altas de los ríos Yanuncay, Tomebamba y Tarqui,\n      crece en bordes de bosque y en vegetación secundaria; se establece bien en sitios húme-\n      dos con suelos sueltos y profundos; florece durante todo el año y sus flores son un recurso\n      fundamental para ciertas especies de colibríes como: Metallura tyrianthina, Rhamphomicron\n      microrhynchum, Colibrí coruscans y Lafresnaya labresnayi (Serrano, 1996). Sus nectarios pro-\n      ducen un líquido con una concentración de 23,4 % de néctar, el cual tiene un contenido de\n      azúcar de 3,04 mg (King, 1987).","usos_tradicionales":"Sus flores en infusión son excelentes estimulantes, tónicos y antiespas-\n      módicos (Serrano, 1996).","propagacion":"Se recomienda propagarla mediante esquejes semileñosos, para el efecto se\n      deben cortar esquejes de 20 a 25 cm de largo y 0,5 a 1 cm de diámetro. Para el transporte se\n      recomienda envolverlos en papel mojado y ponerlos en fundas plásticas y dejarlos reposar\n      doce horas, luego antes de plantarlos se recomienda untarles la base con miel de abeja para\n      estimular su enraizamiento.","images":["/resources/img/arboles-125_0.jpg","/resources/img/arboles-125_1.jpg","/resources/img/arboles-125_2.jpg"],"slug":"quinde-sungana"},{"page":126,"original":"126   ARBUSTOS NATIVOS\n\n\n\n\n                               Familia: Melastomataceae\n                                              Cérrag\n\n                              Nombre científico: Miconia aspergillaris (Bonpl.) Naudin\n                      Otros nombres comunes: “sírac”\n\n\n      Hábito: Arbusto o árbol pequeño de 3 a 4 m de altura, copa irregular.\n\n      Hojas: Simples opuestas, peciolos de 0,4–0,6 cm de longitud; lámina de elíptica a oblongo-\n      elíptica de 1,5–3 cm de largo x 1–2 cm de ancho, margen dentado, ápice agudo y base de\n      aguda a obtusa; haz verde brillante glabro a ligeramente puberulento, envés verde amari-\n      llento, pubescente con 3 nervios principales.\n\n      Flores: Agrupadas en panículas terminales de 2 a 7 cm de longitud. Flores bisexuales acti-\n      nomorfas, sostenidas por peciolos de 0,5 a 0,8 cm de largo, con bractéolas lineares. Hipanto\n      de 0,2 a 0,3 mm, densamente puberulento; cáliz persistente pubescente, corola compuesta\n      por 5 pétalos suborbiculares, libres de color blanco. Androceo compuesto por 10 estambres\n      libres dimórficos en tamaño, anteras de color amarillo que se abren mediante poros. Ovario,\n      semiínfero provisto de un estilo alargado y un estigma capitado.\n\n      Fruto: Una baya de color rosado que contiene numerosas semillas.\n\n      Distribución y ecología: Se distribuye en los Andes del Ecuador y Perú (Wurdack, 1988). En\n      nuestro país crece en la región andina y cubre un rango altitudinal entre 1800 y 3800 m. En\n      los márgenes de los ríos de Cuenca es una especie común en los sectores de Barabón, Solda-\n      dos y San Joaquín, esporádicamente se han encontrado individuos de esta especie dentro\n      de la zona urbana de la ciudad. Es una especie pionera, frecuente en bosques secundarios.\n      Se adapta a una gran variedad de suelos y es importante ecológicamente porque sus frutos\n      constituyen un recurso valioso para una gran variedad de aves silvestres.\n\n      Usos tradicionales: Su madera es muy buena para leña y carbón, para construcciones pe-\n      queñas y para elaborar estacas. Medicinalmente sus hojas y flores se emplean para baños\n      del cinco y dieta. Sus frutos son comestibles.\n\n      Propagación: Se desconoce su propagación, pero su regeneración natural es buena.\n","familia":"Melastomataceae\n","nombre":"Cérrag","descripcíon":"","otros_nombres_comunes":["sírac"],"nombre_cientifica":"Miconia aspergillaris (Bonpl.) Naudin","habito":" Arbusto o árbol pequeño de 3 a 4 m de altura, copa irregular.","hojas":"Simples opuestas, peciolos de 0,4–0,6 cm de longitud; lámina de elíptica a oblongo-\n      elíptica de 1,5–3 cm de largo x 1–2 cm de ancho, margen dentado, ápice agudo y base de\n      aguda a obtusa; haz verde brillante glabro a ligeramente puberulento, envés verde amari-\n      llento, pubescente con 3 nervios principales.","flores":"Agrupadas en panículas terminales de 2 a 7 cm de longitud. Flores bisexuales acti-\n      nomorfas, sostenidas por peciolos de 0,5 a 0,8 cm de largo, con bractéolas lineares. Hipanto\n      de 0,2 a 0,3 mm, densamente puberulento; cáliz persistente pubescente, corola compuesta\n      por 5 pétalos suborbiculares, libres de color blanco. Androceo compuesto por 10 estambres\n      libres dimórficos en tamaño, anteras de color amarillo que se abren mediante poros. Ovario,\n      semiínfero provisto de un estilo alargado y un estigma capitado.","fruta":"Una baya de color rosado que contiene numerosas semillas.","distribucion_y_ecologia":"Se distribuye en los Andes del Ecuador y Perú (Wurdack, 1988). En\n      nuestro país crece en la región andina y cubre un rango altitudinal entre 1800 y 3800 m. En\n      los márgenes de los ríos de Cuenca es una especie común en los sectores de Barabón, Solda-\n      dos y San Joaquín, esporádicamente se han encontrado individuos de esta especie dentro\n      de la zona urbana de la ciudad. Es una especie pionera, frecuente en bosques secundarios.\n      Se adapta a una gran variedad de suelos y es importante ecológicamente porque sus frutos\n      constituyen un recurso valioso para una gran variedad de aves silvestres.","usos_tradicionales":"Su madera es muy buena para leña y carbón, para construcciones pe-\n      queñas y para elaborar estacas. Medicinalmente sus hojas y flores se emplean para baños\n      del cinco y dieta. Sus frutos son comestibles.","propagacion":"Se desconoce su propagación, pero su regeneración natural es buena.","images":["/resources/img/arboles-127_0.jpg","/resources/img/arboles-127_1.jpg","/resources/img/arboles-127_2.jpg"],"slug":"crrag"},{"page":128,"original":"128   ARBUSTOS NATIVOS\n\n\n\n\n                                     Familia: Myricaceae\n                                        Laurel de cera\n\n                              Nombre científico: Morella parvifolia (Benth.) Parra-O.\n                      Otros nombres comunes: “laurel de cerro”, “urcu laurel”\n\n\n      Hábito: Arbusto aromático de 2 a 7 m de altura, con abundante ramificación. Tallos cilíndri-\n      cos, retorcidos, nudosos ramitas jóvenes de color verde amarillento.\n\n      Hojas: Simples, alternas, peciolos 0,9–1,2 cm de largo. Lámina de forma elíptica u oblanceo-\n      lada de 1,5–6 cm de largo x 0,5–2 cm de ancho, margen entero, ápice agudo y base cuneada\n      o aguda. Haz glabro verde claro, envés pubescente verde amarillento.\n\n      Flores: Unisexuales agrupadas en pequeños ramilletes (amentos). Amentos femeninos de\n      0,9 a 2,9 cm de largo, amentos masculinos de 0,8 a 2,5 cm de largo. Flores femeninas pro-\n      vistas de un ovario con 2 carpelos, flores masculinas con 5 a 10 estambres que producen\n      abundante polen.\n\n      Fruto: Una drupa esférica u ovalada, 0,7–5 mm de diámetro, glabra, con protuberancias ve-\n      rrugosas. Semilla 1–2.5 mm de largo.\n\n      Distribución y ecología: Se distribuye en los Andes de Venezuela, Colombia y Ecuador (Pa-\n      rra, 2003). En nuestro país ha sido registrada en las provincias de Azuay, Cañar, Carchi, Chim-\n      borazo, Cotopaxi, El Oro, Loja, Pichincha y Tungurahua (Jorgensen & León-Yánez, 1999). En\n      las riberas de los ríos de Cuenca, es más bien una especie rara y está localizada en los secto-\n      res de Soldados, Barabón, Marianza y Sayausí. Es una especie de sucesión inicial, se adapta\n      bien en terrenos pobres y degradados, crece generalmente en bordes de quebradas, ríos,\n      taludes de carreteras y barrancos. Es un componente importante de la vegetación secun-\n      daria. Debido a su capacidad de fijar nitrógeno es una planta recomendada para la recupe-\n      ración de suelos degradados. Sus frutos constituyen un recurso importante para algunas\n      especies de aves como tórtolas (Zenaida auriculata) y torcazas (Columba fasciata).\n\n      Usos tradicionales: En las comunidades de Jadán y El Carmen de Aguarongo (provincia del\n      Azuay), se usa para limpias de aire y espanto y para baños calientes. El aceite de sus frutos\n      junto con la enjundia de gallina (grasa que cubre algunos órganos internos de las aves) sirve\n      para el reumatismo. Sus ramas se hacen bendecir en domingo de ramos. Sus hojas se em-\n      plean para condimentar las comidas.\n\n      Propagación: Se puede propagar mediante semillas, para el efecto se recomienda secar los\n      frutos al sol y antes de la germinación proceder a escarificarlos mediante un tratamiento\n      con agua caliente y dejarlos reposar durante 24 horas. Para la siembra, las semillas deben\n      ser enterradas a 1 cm de profundidad. La germinación ocurre en un lapso de dos meses y a\n      los cinco meses las plántulas deben ser trasplantadas en fundas.\n","familia":"Myricaceae\n","nombre":"Laurel de cera","descripcíon":"","otros_nombres_comunes":["laurel de cerro","urcu laurel"],"nombre_cientifica":"Morella parvifolia (Benth.) Parra-O.","habito":" Arbusto aromático de 2 a 7 m de altura, con abundante ramificación. Tallos cilíndri-\n      cos, retorcidos, nudosos ramitas jóvenes de color verde amarillento.","hojas":"Simples, alternas, peciolos 0,9–1,2 cm de largo. Lámina de forma elíptica u oblanceo-\n      lada de 1,5–6 cm de largo x 0,5–2 cm de ancho, margen entero, ápice agudo y base cuneada\n      o aguda. Haz glabro verde claro, envés pubescente verde amarillento.","flores":"Unisexuales agrupadas en pequeños ramilletes (amentos). Amentos femeninos de\n      0,9 a 2,9 cm de largo, amentos masculinos de 0,8 a 2,5 cm de largo. Flores femeninas pro-\n      vistas de un ovario con 2 carpelos, flores masculinas con 5 a 10 estambres que producen\n      abundante polen.","fruta":"Una drupa esférica u ovalada, 0,7–5 mm de diámetro, glabra, con protuberancias ve-\n      rrugosas. Semilla 1–2.5 mm de largo.","distribucion_y_ecologia":"Se distribuye en los Andes de Venezuela, Colombia y Ecuador (Pa-\n      rra, 2003). En nuestro país ha sido registrada en las provincias de Azuay, Cañar, Carchi, Chim-\n      borazo, Cotopaxi, El Oro, Loja, Pichincha y Tungurahua (Jorgensen & León-Yánez, 1999). En\n      las riberas de los ríos de Cuenca, es más bien una especie rara y está localizada en los secto-\n      res de Soldados, Barabón, Marianza y Sayausí. Es una especie de sucesión inicial, se adapta\n      bien en terrenos pobres y degradados, crece generalmente en bordes de quebradas, ríos,\n      taludes de carreteras y barrancos. Es un componente importante de la vegetación secun-\n      daria. Debido a su capacidad de fijar nitrógeno es una planta recomendada para la recupe-\n      ración de suelos degradados. Sus frutos constituyen un recurso importante para algunas\n      especies de aves como tórtolas (Zenaida auriculata) y torcazas (Columba fasciata).","usos_tradicionales":"En las comunidades de Jadán y El Carmen de Aguarongo (provincia del\n      Azuay), se usa para limpias de aire y espanto y para baños calientes. El aceite de sus frutos\n      junto con la enjundia de gallina (grasa que cubre algunos órganos internos de las aves) sirve\n      para el reumatismo. Sus ramas se hacen bendecir en domingo de ramos. Sus hojas se em-\n      plean para condimentar las comidas.","propagacion":"Se puede propagar mediante semillas, para el efecto se recomienda secar los\n      frutos al sol y antes de la germinación proceder a escarificarlos mediante un tratamiento\n      con agua caliente y dejarlos reposar durante 24 horas. Para la siembra, las semillas deben\n      ser enterradas a 1 cm de profundidad. La germinación ocurre en un lapso de dos meses y a\n      los cinco meses las plántulas deben ser trasplantadas en fundas.","images":["/resources/img/arboles-129_0.jpg","/resources/img/arboles-129_1.jpg","/resources/img/arboles-129_2.jpg"],"slug":"laurel-de-cera"},{"page":130,"original":"130   ARBUSTOS NATIVOS\n\n\n\n\n                                      Familia: Myrtaceae\n                                         Palo de fierro\n\n                              Nombre científico: Myrrhinium atropurpureum Schott\n\n\n\n\n      Hábito: Arbusto o árbol pequeño aromático, de 2 a 5 m de altura. Tronco tortuoso con rami-\n      ficación alterna que se origina desde la base.\n\n      Hojas: Simples, opuestas de textura coriácea, sostenidas por un peciolo corto; lámina elíp-\n      tica de 1,2–3,5 cm de largo x 0,8–2 cm de ancho; haz verde lustroso brillante, envés verde\n      claro.\n\n      Flores: Reunidas en inflorescencias cimosas, caulifloras, cada cima contiene entre 3 y 6 flo-\n      res; cáliz con 4 lóbulos, corola con 4 pétalos carnosos de color púrpura claro; androceo con\n      8 estambres con filamentos de 1,5 a 2 cm de largo con anteras de color crema; ovario ínfero\n      con 2 lóculos.\n\n      Fruto: Baya con forma elipsoide de 3 a 5 mm de largo, de color negro al madurar.\n\n      Distribución y ecología: Especie nativa distribuida en bosques húmedos montanos entre\n      2000 y 2500 m de altitud. En nuestro país ha sido registrada en las provincias de Azuay y Loja\n      entre 2000 y 2500 m de altitud. En la región es una especie rara y restringida a las riberas de\n      quebradas y ríos como el Yanuncay, en donde se han registrado alrededor de 10 individuos,\n      todos en el área urbana de Cuenca.\n\n      Usos tradicionales: Su madera es dura, por lo cual es empleada para elaborar carbón; tam-\n      bién tiene un gran potencial para emplearla como especie ornamental por la vistosidad de\n      sus flores y su follaje aromático.\n\n      Propagación: Se propaga mediante semillas, para el efecto es necesario recolectar frutos\n      maduros, extraer sus semillas y luego secarlas al ambiente antes de realizar el semillero.\n","familia":"Myrtaceae\n","nombre":"Palo de fierro","descripcíon":"","otros_nombres_comunes":[],"nombre_cientifica":"Myrrhinium atropurpureum Schott","habito":" Arbusto o árbol pequeño aromático, de 2 a 5 m de altura. Tronco tortuoso con rami-\n      ficación alterna que se origina desde la base.","hojas":"Simples, opuestas de textura coriácea, sostenidas por un peciolo corto; lámina elíp-\n      tica de 1,2–3,5 cm de largo x 0,8–2 cm de ancho; haz verde lustroso brillante, envés verde\n      claro.","flores":"Reunidas en inflorescencias cimosas, caulifloras, cada cima contiene entre 3 y 6 flo-\n      res; cáliz con 4 lóbulos, corola con 4 pétalos carnosos de color púrpura claro; androceo con\n      8 estambres con filamentos de 1,5 a 2 cm de largo con anteras de color crema; ovario ínfero\n      con 2 lóculos.","fruta":"Baya con forma elipsoide de 3 a 5 mm de largo, de color negro al madurar.","distribucion_y_ecologia":"Especie nativa distribuida en bosques húmedos montanos entre\n      2000 y 2500 m de altitud. En nuestro país ha sido registrada en las provincias de Azuay y Loja\n      entre 2000 y 2500 m de altitud. En la región es una especie rara y restringida a las riberas de\n      quebradas y ríos como el Yanuncay, en donde se han registrado alrededor de 10 individuos,\n      todos en el área urbana de Cuenca.","usos_tradicionales":"Su madera es dura, por lo cual es empleada para elaborar carbón; tam-\n      bién tiene un gran potencial para emplearla como especie ornamental por la vistosidad de\n      sus flores y su follaje aromático.","propagacion":"Se propaga mediante semillas, para el efecto es necesario recolectar frutos\n      maduros, extraer sus semillas y luego secarlas al ambiente antes de realizar el semillero.","images":["/resources/img/arboles-131_0.jpg","/resources/img/arboles-131_1.jpg","/resources/img/arboles-131_2.jpg","/resources/img/arboles-131_3.jpg"],"slug":"palo-de-fierro"},{"page":132,"original":"132   ARBUSTOS NATIVOS\n\n\n\n\n                                     Familia: Onagraceae\n                                            Pena pena\n\n                               Nombre científico: Fuchsia loxensis Kunth\n                       Otros nombres comunes: “zarcillo sacha”, “arete del inca”\n\n\n      Hábito: Arbusto de 1 a 2 m de altura, tallos flexibles nudosos, a veces escandentes, ramifica-\n      ción opuesta, ramitas y brotes tiernos rojizos puberulentos.\n\n      Hojas: Simples, opuestas, ternadas, sostenidas por peciolos delgados de 1–3 cm de largo;\n      lámina elíptica o elíptica-oblonga de 3–6 cm de largo x 1,5–2,5 cm de ancho, base redon-\n      deada, ápice agudo y margen dentado. Haz verde oscuro glabro, envés ligeramente piloso.\n\n      Flores: Bisexuales, solitarias, axilares, péndulas, sostenidas por pedicelos delgados de 1 – 2\n      cm de largo; hipanto rojo, prolongado sobre el ovario de 2–2,5 cm de largo, cáliz conforma-\n      do por 4 sépalos oblongo-lanceolados, de color rojo escarlata; corola con 4 pétalos ovados\n      rojos de 6–9 cm de largo x 5–6 cm de ancho; androceo con 7 a 8 estambres de 0,5 cm de\n      largo, anteras con tecas adnadas, ovario ínfero con el estigma lobulado de 0,2 cm de ancho.\n\n      Fruto: Baya elipsoide de 0,8–1,5 cm de largo x 0,5–0,6 mm de ancho, de color púrpura cuan-\n      do está madura.\n\n      Distribución y ecología: Especie endémica del Ecuador, se distribuye a lo largo de la región\n      andina entre 2000 y 4000 m de altitud. En los márgenes de los ríos de Cuenca es una especie\n      rara y se localiza en los sectores de Barabón y Soldados en el río Yanuncay y en Sayausí y\n      Marianza en el río Tomebamba. Crece en remanentes de bosque y áreas intervenidas, cerca\n      de caminos y riachuelos en pastizales y páramo arbustivo (León- Yánez, 2011). Sus flores po-\n      seen un alto contenido de néctar y azúcares: alrededor de 20,7 % de néctar por flor (Serrano,\n      1996) y 0,67 mg de azúcar por flor (King, 1987), por lo cual es un recurso importante para va-\n      rias especies de colibríes y pinchaflores especialmente Diglossa cyanea y Diglossa humeralis.\n\n      Usos tradicionales: En ciertas comunidades campesinas de la provincia del Azuay, sus flo-\n      res junto con las de ñachig (Bidens andicola) y alverjilla (Vicia andicola), se emplean para las\n      penas, nervios y problemas de corazón. White (1976), menciona que sus flores en infusión se\n      emplean para obtener efectos sedativos y cardiotónicos.\n\n      Propagación: Se puede propagar vegetativamente mediante estacas de 15 a 20 cm de lon-\n      gitud, considerando que contengan yemas jóvenes; para el efecto las yemas se envuelven\n      en una funda que a su vez se enrolla en papel húmedo y se coloca en el refrigerador (2 °C)\n      durante 24 horas para inducir las yemas (Caranqui, 2011).\n","familia":"Onagraceae\n","nombre":"Pena pena","descripcíon":"","otros_nombres_comunes":["zarcillo sacha","arete del inca"],"nombre_cientifica":"Fuchsia loxensis Kunth","habito":" Arbusto de 1 a 2 m de altura, tallos flexibles nudosos, a veces escandentes, ramifica-\n      ción opuesta, ramitas y brotes tiernos rojizos puberulentos.","hojas":"Simples, opuestas, ternadas, sostenidas por peciolos delgados de 1–3 cm de largo;\n      lámina elíptica o elíptica-oblonga de 3–6 cm de largo x 1,5–2,5 cm de ancho, base redon-\n      deada, ápice agudo y margen dentado. Haz verde oscuro glabro, envés ligeramente piloso.","flores":"Bisexuales, solitarias, axilares, péndulas, sostenidas por pedicelos delgados de 1 – 2\n      cm de largo; hipanto rojo, prolongado sobre el ovario de 2–2,5 cm de largo, cáliz conforma-\n      do por 4 sépalos oblongo-lanceolados, de color rojo escarlata; corola con 4 pétalos ovados\n      rojos de 6–9 cm de largo x 5–6 cm de ancho; androceo con 7 a 8 estambres de 0,5 cm de\n      largo, anteras con tecas adnadas, ovario ínfero con el estigma lobulado de 0,2 cm de ancho.","fruta":"Baya elipsoide de 0,8–1,5 cm de largo x 0,5–0,6 mm de ancho, de color púrpura cuan-\n      do está madura.","distribucion_y_ecologia":"Especie endémica del Ecuador, se distribuye a lo largo de la región\n      andina entre 2000 y 4000 m de altitud. En los márgenes de los ríos de Cuenca es una especie\n      rara y se localiza en los sectores de Barabón y Soldados en el río Yanuncay y en Sayausí y\n      Marianza en el río Tomebamba. Crece en remanentes de bosque y áreas intervenidas, cerca\n      de caminos y riachuelos en pastizales y páramo arbustivo (León- Yánez, 2011). Sus flores po-\n      seen un alto contenido de néctar y azúcares: alrededor de 20,7 % de néctar por flor (Serrano,\n      1996) y 0,67 mg de azúcar por flor (King, 1987), por lo cual es un recurso importante para va-\n      rias especies de colibríes y pinchaflores especialmente Diglossa cyanea y Diglossa humeralis.","usos_tradicionales":"En ciertas comunidades campesinas de la provincia del Azuay, sus flo-\n      res junto con las de ñachig (Bidens andicola) y alverjilla (Vicia andicola), se emplean para las\n      penas, nervios y problemas de corazón. White (1976), menciona que sus flores en infusión se\n      emplean para obtener efectos sedativos y cardiotónicos.","propagacion":"Se puede propagar vegetativamente mediante estacas de 15 a 20 cm de lon-\n      gitud, considerando que contengan yemas jóvenes; para el efecto las yemas se envuelven\n      en una funda que a su vez se enrolla en papel húmedo y se coloca en el refrigerador (2 °C)\n      durante 24 horas para inducir las yemas (Caranqui, 2011).","images":["/resources/img/arboles-133_0.jpg","/resources/img/arboles-133_1.jpg","/resources/img/arboles-133_2.jpg"],"slug":"pena-pena"},{"page":134,"original":"134   ARBUSTOS NATIVOS\n\n\n\n\n                                  Familia: Polemoniaceae\n                                          Flor del Inca\n\n                              Nombre científico: Cantua pyrifolia Juss. ex Lam.\n\n\n\n\n      Hábito: Arbusto de hasta de 3 a 4 m de alto, tallo cilíndrico retorcido, ramificación alterna y\n      difusa.\n\n      Hojas: Simples, alternas, arregladas en forma de espiral en las ramas, lámina oblongo-elípti-\n      ca de 3 a 6 cm de largo por 0,6 a 2 cm de ancho, de margen entero.\n\n      Flores: Dispuestas en racimos terminales densos. Flores sostenidas por peciolos de 0,8 a 1,2\n      cm, cáliz tubular de color verde - púrpura, corola tubular de 2 cm de largo y color amarillo -\n      cremoso; estambres largos, que se salen del tubo de la corola; ovario súpero con 3 lóculos.\n\n      Fruto: Una cápsula loculicida con forma elíptica de color amarillo cuando está madura.\n\n      Distribución y ecología: Especie originaria de América del Sur, crece comúnmente en re-\n      giones montañosas del norte del Perú y sur del Ecuador. En nuestro país ha sido registrada\n      en los valles interandinos de las provincias del Azuay, Cañar, Cotopaxi, Loja y Tungurahua\n      entre 2000 y 3500 m de altitud. Crece en una gran variedad de suelos, con la condición de\n      que sean bien drenados. Debido a la destrucción de su hábitat original (bosques y mato-\n      rrales interandinos), en la actualidad está restringida a barrancos y márgenes de pequeñas\n      quebradas y ríos. En los ríos de Cuenca se han registrado siete individuos en las riberas del\n      río Yanuncay.\n\n      Usos tradicionales: Sus flores son visitadas por abejas, por lo que es una especie potencial-\n      mente melífera.\n\n      Propagación: Se propaga mediante semillas, las mismas que deben ser colectadas directa-\n      mente de la planta cuando las cápsulas estén maduras (amarillas).\n","familia":"Polemoniaceae\n","nombre":"Flor del Inca","descripcíon":"","otros_nombres_comunes":[],"nombre_cientifica":"Cantua pyrifolia Juss. ex Lam.","habito":" Arbusto de hasta de 3 a 4 m de alto, tallo cilíndrico retorcido, ramificación alterna y\n      difusa.","hojas":"Simples, alternas, arregladas en forma de espiral en las ramas, lámina oblongo-elípti-\n      ca de 3 a 6 cm de largo por 0,6 a 2 cm de ancho, de margen entero.","flores":"Dispuestas en racimos terminales densos. Flores sostenidas por peciolos de 0,8 a 1,2\n      cm, cáliz tubular de color verde - púrpura, corola tubular de 2 cm de largo y color amarillo -\n      cremoso; estambres largos, que se salen del tubo de la corola; ovario súpero con 3 lóculos.","fruta":"Una cápsula loculicida con forma elíptica de color amarillo cuando está madura.","distribucion_y_ecologia":"Especie originaria de América del Sur, crece comúnmente en re-\n      giones montañosas del norte del Perú y sur del Ecuador. En nuestro país ha sido registrada\n      en los valles interandinos de las provincias del Azuay, Cañar, Cotopaxi, Loja y Tungurahua\n      entre 2000 y 3500 m de altitud. Crece en una gran variedad de suelos, con la condición de\n      que sean bien drenados. Debido a la destrucción de su hábitat original (bosques y mato-\n      rrales interandinos), en la actualidad está restringida a barrancos y márgenes de pequeñas\n      quebradas y ríos. En los ríos de Cuenca se han registrado siete individuos en las riberas del\n      río Yanuncay.","usos_tradicionales":"Sus flores son visitadas por abejas, por lo que es una especie potencial-\n      mente melífera.","propagacion":"Se propaga mediante semillas, las mismas que deben ser colectadas directa-\n      mente de la planta cuando las cápsulas estén maduras (amarillas).","images":["/resources/img/arboles-135_0.jpg","/resources/img/arboles-135_1.jpg","/resources/img/arboles-135_2.jpg"],"slug":"flor-del-inca"},{"page":136,"original":"136   ARBUSTOS NATIVOS\n\n\n\n\n                                   Familia: Polygalaceae\n                                              Higüila\n\n                              Nombre científico: Monnina ligustrina (Bonpl.) B. Eriksen\n                      Otros nombres comunes: “azulina”, “higüilán”\n\n\n      Hábito: Arbusto o árbol pequeño de 2 a 5 m de altura, tallos cilíndricos suaves, ramificación\n      alterna y apretada en el ápice.\n\n      Hojas: Simples, alternas, de textura cartácea, estipuladas, sostenidas por peciolos de 0,2–0,4\n      cm de largo; lámina elíptica a estrechamente elíptica de 1,5–5,5 cm de largo x 0,6–1,8 cm\n      de ancho, base atenuada, ápice de agudo a ligeramente acuminado y margen entero; haz\n      verde oscuro ligeramente pubescente, envés verde claro.\n\n      Flores: Reunidas en racimos terminales de 2–6 cm de largo, con el raquis nudoso y piloso.\n      Flores bisexuales zigomorfas, sostenidas por pedicelos de 0,1 cm de diámetro, brácteas\n      ovadas a lanceoladas de 2–4 mm x 1–1,5 mm, cáliz conformado por 5 sépalos cóncavos, los\n      3 externos connados en la base y 2 internos petaloides, corola conformada por 5 pétalos\n      azules o lilas, 3 externos unidos que forman un tubo con el ápice amarillo y 2 pétalos latera-\n      les pequeños, estambres; pétalo estaminal densamente piloso que porta 8 estambres con\n      sus filamentos fusionados un 60 % de su longitud, anteras dehiscentes por medio de poros;\n      ovario súpero, unilocular; estilo simple curvado, estigma bilobado.\n\n      Fruto: Drupa jugosa elipsoide de 0,5–0,6 cm de largo x 0,3–0,4 cm de ancho, morada o ne-\n      gra cuando está madura.\n\n      Distribución y ecología: En los Andes del centro y sur del Ecuador hasta el norte del Perú\n      entre 2000 y 3500 m de altitud (Eriksen et al, 2000). En los márgenes de los ríos de Cuenca es\n      una especie común. En algunos sitios de pastizales abandonados, se comporta como una\n      especie pionera y forma pequeños matorrales y permitiendo la colonización de otras espe-\n      cies leñosas. Se adapta bien en suelos pobres y ácidos. Sus frutos son un recursos valiosos\n      para algunas especies de aves silvestres, particularmente Pheucticus chrysogaster, conocido\n      localmente como chugo.\n\n      Usos tradicionales: Sus hojas sirven de alimento para el ganado y cuyes, y sus raíces macha-\n      cadas se emplean para limpiar el cabello y prevenir la caspa (Minga, 2000).\n\n      Propagación: No se conoce sobre métodos de reproducción sexual, pero tiene una alta\n      regeneración natural\n","familia":"Polygalaceae\n","nombre":"Higüila","descripcíon":"","otros_nombres_comunes":["azulina","higüilán"],"nombre_cientifica":"Monnina ligustrina (Bonpl.) B. Eriksen","habito":" Arbusto o árbol pequeño de 2 a 5 m de altura, tallos cilíndricos suaves, ramificación\n      alterna y apretada en el ápice.","hojas":"Simples, alternas, de textura cartácea, estipuladas, sostenidas por peciolos de 0,2–0,4\n      cm de largo; lámina elíptica a estrechamente elíptica de 1,5–5,5 cm de largo x 0,6–1,8 cm\n      de ancho, base atenuada, ápice de agudo a ligeramente acuminado y margen entero; haz\n      verde oscuro ligeramente pubescente, envés verde claro.","flores":"Reunidas en racimos terminales de 2–6 cm de largo, con el raquis nudoso y piloso.\n      Flores bisexuales zigomorfas, sostenidas por pedicelos de 0,1 cm de diámetro, brácteas\n      ovadas a lanceoladas de 2–4 mm x 1–1,5 mm, cáliz conformado por 5 sépalos cóncavos, los\n      3 externos connados en la base y 2 internos petaloides, corola conformada por 5 pétalos\n      azules o lilas, 3 externos unidos que forman un tubo con el ápice amarillo y 2 pétalos latera-\n      les pequeños, estambres; pétalo estaminal densamente piloso que porta 8 estambres con\n      sus filamentos fusionados un 60 % de su longitud, anteras dehiscentes por medio de poros;\n      ovario súpero, unilocular; estilo simple curvado, estigma bilobado.","fruta":"Drupa jugosa elipsoide de 0,5–0,6 cm de largo x 0,3–0,4 cm de ancho, morada o ne-\n      gra cuando está madura.","distribucion_y_ecologia":"En los Andes del centro y sur del Ecuador hasta el norte del Perú\n      entre 2000 y 3500 m de altitud (Eriksen et al, 2000). En los márgenes de los ríos de Cuenca es\n      una especie común. En algunos sitios de pastizales abandonados, se comporta como una\n      especie pionera y forma pequeños matorrales y permitiendo la colonización de otras espe-\n      cies leñosas. Se adapta bien en suelos pobres y ácidos. Sus frutos son un recursos valiosos\n      para algunas especies de aves silvestres, particularmente Pheucticus chrysogaster, conocido\n      localmente como chugo.","usos_tradicionales":"Sus hojas sirven de alimento para el ganado y cuyes, y sus raíces macha-\n      cadas se emplean para limpiar el cabello y prevenir la caspa (Minga, 2000).","propagacion":"No se conoce sobre métodos de reproducción sexual, pero tiene una alta\n      regeneración natural","images":["/resources/img/arboles-137_0.jpg","/resources/img/arboles-137_1.jpg","/resources/img/arboles-137_2.jpg"],"slug":"higila"},{"page":138,"original":"138   ARBUSTOS NATIVOS\n\n\n\n\n                                       Familia: Rosaceae\n                                                Mora\n\n                              Nombre científico: Rubus floribundus Weihe\n                      Otros nombres comunes: “mora silvestre”, “zarzamora”\n\n\n      Hábito: Arbusto robusto, erecto o escandente armado de espinas, tallos angulados glabros\n      o ligeramente tomentosos, espinas curvadas de 3–5 mm de largo.\n\n      Hojas: Alternas, compuestas, 5 foliadas, sostenidas por peciolos tomentosos de 3 -7 cm de\n      largo; foliolos de forma ovado-elíptica, de 7–11 cm de largo x 3–7 cm de ancho, base re-\n      dondeada, ápice agudo y margen serrado, haz esparcidamente piloso, envés piloso o viloso,\n      ambas superficies con glándulas; en la base de las hojas crece un par de estípulas lanceola-\n      das de 1,2–1,4 cm de largo.\n\n      Flores: Reunidas en panículas abiertas de 10–20 cm de largo, que contienen entre 15 a 50\n      flores, cada flor sostenida por pedicelos de 4 a 8 mm de largo. Flores actinomorfas bisexua-\n      les de 1,7 cm de diámetro; cáliz conformado por 5 sépalos ovados de 6 x 4 mm; corola con\n      5 pétalos blanco rosados, redondeados de 8–12 mm de largo por 6–8 mm de ancho; andro-\n      ceo conformado por numerosos estambres de filamentos blancos y anteras glabras; pistilo\n      compuesto por numerosos carpelos libres, cada carpelo contiene 2 óvulos.\n\n      Fruto: Un agregado de pequeñas drupas, negras cuando están maduras, cada drupa con-\n      tiene una semilla.\n\n      Distribución y ecología: Se distribuye en los Andes del Ecuador y Perú entre 1900 y 3400 m\n      de altitud (Romolerux, 1996). En nuestro país ha sido registrada en las provincias de Chim-\n      borazo, Cañar, Azuay, Loja, El Oro y Zamora Chinchipe. Es muy común en áreas intervenidas\n      de bosques montanos y valles interandinos, crece formando matorrales densos en cercas,\n      bordes de caminos y márgenes de quebradas. Muestra una alta regeneración natural y una\n      buena capacidad de rebrote. Esta especie constituye un importante recurso para una gran\n      variedad de aves silvestres las cuales dispersan sus semillas.\n\n      Usos tradicionales: En las comunidades de El Carmen y Jadán, sus frutos se consumen di-\n      rectos o en jugos y mermeladas; sus flores en infusión sirven para tratar resfríos, y sus hojas\n      en emplastos para dolor de cabeza. Sus flores son visitadas por abejas, y se emplea como\n      cercas vivas para resguardar los sembríos (De la Torre et al, 2008).\n\n      Propagación: Vegetativamente se puede propagar por medio de estacas de 2 años de\n      edad. La regeneración natural es buena.\n","familia":"Rosaceae\n","nombre":"Mora","descripcíon":"","otros_nombres_comunes":["mora silvestre","zarzamora"],"nombre_cientifica":"Rubus floribundus Weihe","habito":" Arbusto robusto, erecto o escandente armado de espinas, tallos angulados glabros\n      o ligeramente tomentosos, espinas curvadas de 3–5 mm de largo.","hojas":"Alternas, compuestas, 5 foliadas, sostenidas por peciolos tomentosos de 3 -7 cm de\n      largo; foliolos de forma ovado-elíptica, de 7–11 cm de largo x 3–7 cm de ancho, base re-\n      dondeada, ápice agudo y margen serrado, haz esparcidamente piloso, envés piloso o viloso,\n      ambas superficies con glándulas; en la base de las hojas crece un par de estípulas lanceola-\n      das de 1,2–1,4 cm de largo.","flores":"Reunidas en panículas abiertas de 10–20 cm de largo, que contienen entre 15 a 50\n      flores, cada flor sostenida por pedicelos de 4 a 8 mm de largo. Flores actinomorfas bisexua-\n      les de 1,7 cm de diámetro; cáliz conformado por 5 sépalos ovados de 6 x 4 mm; corola con\n      5 pétalos blanco rosados, redondeados de 8–12 mm de largo por 6–8 mm de ancho; andro-\n      ceo conformado por numerosos estambres de filamentos blancos y anteras glabras; pistilo\n      compuesto por numerosos carpelos libres, cada carpelo contiene 2 óvulos.","fruta":"Un agregado de pequeñas drupas, negras cuando están maduras, cada drupa con-\n      tiene una semilla.","distribucion_y_ecologia":"Se distribuye en los Andes del Ecuador y Perú entre 1900 y 3400 m\n      de altitud (Romolerux, 1996). En nuestro país ha sido registrada en las provincias de Chim-\n      borazo, Cañar, Azuay, Loja, El Oro y Zamora Chinchipe. Es muy común en áreas intervenidas\n      de bosques montanos y valles interandinos, crece formando matorrales densos en cercas,\n      bordes de caminos y márgenes de quebradas. Muestra una alta regeneración natural y una\n      buena capacidad de rebrote. Esta especie constituye un importante recurso para una gran\n      variedad de aves silvestres las cuales dispersan sus semillas.","usos_tradicionales":"En las comunidades de El Carmen y Jadán, sus frutos se consumen di-\n      rectos o en jugos y mermeladas; sus flores en infusión sirven para tratar resfríos, y sus hojas\n      en emplastos para dolor de cabeza. Sus flores son visitadas por abejas, y se emplea como\n      cercas vivas para resguardar los sembríos (De la Torre et al, 2008).","propagacion":"Vegetativamente se puede propagar por medio de estacas de 2 años de\n      edad. La regeneración natural es buena.","images":["/resources/img/arboles-139_0.jpg","/resources/img/arboles-139_1.jpg","/resources/img/arboles-139_2.jpg"],"slug":"mora"},{"page":140,"original":"140   ARBUSTOS NATIVOS\n\n\n\n\n                                     Familia: Solanaceae\n                                          Sauco negro\n\n                         Nombre científico: Cestrum peruvianum Willd. ex Roem. & Schult\n               Otros nombres comunes: “sauco”\n\n\n      Hábito: Arbusto de 2 a 4 m de alto, con hojas de olor fétido; tallos cilíndricos nudosos, cor-\n      teza externa café blanquecina, con abundante ramificación que emerge desde la base; ra-\n      mitas terminales verde oscuras.\n\n      Hojas: Simples, alternas, peciolos de cortos acanalados de 0,4–1,4 cm de longitud; lámina\n      elíptico – oblonga de 4,5–12 cm de largo x 1,5–3,5 cm de ancho, ápice agudo, base obtusa\n      o ligeramente cuneada y margen entero levemente revoluto; haz verde oscuro brillante,\n      envés glabro verde claro.\n\n      Flores: Reunidas en pequeños ramilletes axilares de 1–3 cm de largo, que portan de 3 a 7\n      flores. Flores regulares, cáliz cupuliforme de 0,4–0,5 cm de largo; corola tubular hipocrateri-\n      forme, verde amarillenta con manchas marrones, tubo alargado con 5 lóbulos triangulares\n      ligeramente recurvados; androceo conformado por 5 estambres insertos en el tubo de la\n      corola, ovario súpero sobre un pequeño disco.\n\n      Fruto: Una baya jugosa de forma oblonga de 0,4–0,6 x 0,8–1,4 cm, negra cuando está ma-\n      dura.\n\n      Distribución y ecología: En la región andina desde el sur de Colombia hasta el norte del\n      Perú. En nuestro país ha sido registrada en las provincias de Azuay, Bolívar, Cañar, Carchi,\n      Chimborazo, Cotopaxi, Imbabura, Loja, Napo y Pichincha entre 1500 y 4000 m de altitud\n      (Jorgensen & León-Yánez, 1999). En los márgenes de los ríos de Cuenca ha sido localizada en\n      los sectores de El Paraíso, San Joaquín y Barabón de río Yanuncay y en el Barranco, Sayausí y\n      Marianza del río Tomebamba. Crece en suelo profundo y suelto, es tolerante a la sombra por\n      lo que se puede encontrar bajo el dosel de vegetación nativa. Sus frutos son consumidos\n      por algunas especies de aves como el mirlo común Turdus fuscater.\n\n      Usos tradicionales: Sus flores junto a las de chuquiragua se emplean para la tos, y sus ramas\n      para baños medicinales. La planta es fuerte para limpias y baños de mal aire. La infusión de\n      sus hojas se emplea para tratar problemas de los riñones, sus flores y hojas en infusión se\n      emplean para tratar la inflamación de las amígdalas (De la Torre et al, 2008). En emplastos\n      sus hojas se aplican para aliviar dolores musculares y articulares (De la Torre et al, 2008).\n\n      Propagación: Se puede propagar mediante esquejes semileñosos, para el efecto se reco-\n      mienda usar un sustrato compuesto por arena, pomina y tierra negra en proporciones de 20\n      %, 10 % y 50 % respectivamente (Gallardo, 2011).\n","familia":"Solanaceae\n","nombre":"Sauco negro","descripcíon":"","otros_nombres_comunes":["sauco"],"nombre_cientifica":"Cestrum peruvianum Willd. ex Roem. & Schult","habito":" Arbusto de 2 a 4 m de alto, con hojas de olor fétido; tallos cilíndricos nudosos, cor-\n      teza externa café blanquecina, con abundante ramificación que emerge desde la base; ra-\n      mitas terminales verde oscuras.","hojas":"Simples, alternas, peciolos de cortos acanalados de 0,4–1,4 cm de longitud; lámina\n      elíptico – oblonga de 4,5–12 cm de largo x 1,5–3,5 cm de ancho, ápice agudo, base obtusa\n      o ligeramente cuneada y margen entero levemente revoluto; haz verde oscuro brillante,\n      envés glabro verde claro.","flores":"Reunidas en pequeños ramilletes axilares de 1–3 cm de largo, que portan de 3 a 7\n      flores. Flores regulares, cáliz cupuliforme de 0,4–0,5 cm de largo; corola tubular hipocrateri-\n      forme, verde amarillenta con manchas marrones, tubo alargado con 5 lóbulos triangulares\n      ligeramente recurvados; androceo conformado por 5 estambres insertos en el tubo de la\n      corola, ovario súpero sobre un pequeño disco.","fruta":"Una baya jugosa de forma oblonga de 0,4–0,6 x 0,8–1,4 cm, negra cuando está ma-\n      dura.","distribucion_y_ecologia":"En la región andina desde el sur de Colombia hasta el norte del\n      Perú. En nuestro país ha sido registrada en las provincias de Azuay, Bolívar, Cañar, Carchi,\n      Chimborazo, Cotopaxi, Imbabura, Loja, Napo y Pichincha entre 1500 y 4000 m de altitud\n      (Jorgensen & León-Yánez, 1999). En los márgenes de los ríos de Cuenca ha sido localizada en\n      los sectores de El Paraíso, San Joaquín y Barabón de río Yanuncay y en el Barranco, Sayausí y\n      Marianza del río Tomebamba. Crece en suelo profundo y suelto, es tolerante a la sombra por\n      lo que se puede encontrar bajo el dosel de vegetación nativa. Sus frutos son consumidos\n      por algunas especies de aves como el mirlo común Turdus fuscater.","usos_tradicionales":"Sus flores junto a las de chuquiragua se emplean para la tos, y sus ramas\n      para baños medicinales. La planta es fuerte para limpias y baños de mal aire. La infusión de\n      sus hojas se emplea para tratar problemas de los riñones, sus flores y hojas en infusión se\n      emplean para tratar la inflamación de las amígdalas (De la Torre et al, 2008). En emplastos\n      sus hojas se aplican para aliviar dolores musculares y articulares (De la Torre et al, 2008).","propagacion":"Se puede propagar mediante esquejes semileñosos, para el efecto se reco-\n      mienda usar un sustrato compuesto por arena, pomina y tierra negra en proporciones de 20\n      %, 10 % y 50 % respectivamente (Gallardo, 2011).","images":["/resources/img/arboles-141_0.jpg","/resources/img/arboles-141_1.jpg","/resources/img/arboles-141_2.jpg"],"slug":"sauco-negro"},{"page":142,"original":"142   ARBUSTOS NATIVOS\n\n\n\n\n                                     Familia: Solanaceae\n                                         Huántugsillo\n\n                              Nombre científico: Iochroma fuchsioides (Bonpl.) Miers\n\n\n\n\n      Hábito: Arbusto de 1 a 2 m de alto, tallos cilíndricos, flexibles, ramificación alterna laxa.\n\n      Hojas: Simples, alternas de textura suave, lámina nítidamente elíptica de margen entero,\n      ápice obtuso y base cuneada.\n\n      Flores: Dispuestas en cimas terminales y laterales con 4 a 10 flores por inflorescencia. Flores\n      bisexuales, péndulas, sostenidas por pedicelos de 3,2 cm de largo, cáliz tubular persistente,\n      corola tubular de 3,4 a 3,6 cm de longitud, de color rojo a ligeramente anaranjado; androceo\n      conformado por 5 estambres insertos en la base del tubo de la corola; ovario súpero con dos\n      lóculos, estilo capitado.\n\n      Fruto: Una baya de forma ovada, con el cáliz acrescente, verde cuando está tierna y amarilla\n      al madurar.\n\n      Distribución y ecología: Especie nativa, distribuida desde el Sur de Colombia hasta el sur\n      del Ecuador. En nuestro país ha sido registrada en las provincias de Azuay, Cañar, Chimbo-\n      razo, Tungurahua, Pichincha y Napo entre 1500 y 3500 m de altitud (W3 TRÓPICOS, 2014).\n      Es común encontrarla en márgenes de quebradas y barrancos a lo largo del callejón inte-\n      randino. Crece bien en zonas subhúmedas y se adapta a suelos pobres y pedregosos. En las\n      riberas del Yanuncay es una especie rara; se registra en tres sitios dentro del casco urbano\n      de Cuenca. Ecológicamente es una especie importante porque sus vistosas flores son un\n      recurso valioso para los colibríes.\n\n      Usos tradicionales: En el sur de Colombia es usada como especie alucinógena (Kvist & Mo-\n      raes, 2006).\n\n      Propagación: Se recomienda propagarla mediante semillas, las cuales luego de ser extraí-\n      das de los frutos maduros, deben secárselas al sol durante 15 días y luego sembrarlas en\n      almácigos.\n","familia":"Solanaceae\n","nombre":"Huántugsillo","descripcíon":"","otros_nombres_comunes":[],"nombre_cientifica":"Iochroma fuchsioides (Bonpl.) Miers","habito":" Arbusto de 1 a 2 m de alto, tallos cilíndricos, flexibles, ramificación alterna laxa.","hojas":"Simples, alternas de textura suave, lámina nítidamente elíptica de margen entero,\n      ápice obtuso y base cuneada.","flores":"Dispuestas en cimas terminales y laterales con 4 a 10 flores por inflorescencia. Flores\n      bisexuales, péndulas, sostenidas por pedicelos de 3,2 cm de largo, cáliz tubular persistente,\n      corola tubular de 3,4 a 3,6 cm de longitud, de color rojo a ligeramente anaranjado; androceo\n      conformado por 5 estambres insertos en la base del tubo de la corola; ovario súpero con dos\n      lóculos, estilo capitado.","fruta":"Una baya de forma ovada, con el cáliz acrescente, verde cuando está tierna y amarilla\n      al madurar.","distribucion_y_ecologia":"Especie nativa, distribuida desde el Sur de Colombia hasta el sur\n      del Ecuador. En nuestro país ha sido registrada en las provincias de Azuay, Cañar, Chimbo-\n      razo, Tungurahua, Pichincha y Napo entre 1500 y 3500 m de altitud (W3 TRÓPICOS, 2014).\n      Es común encontrarla en márgenes de quebradas y barrancos a lo largo del callejón inte-\n      randino. Crece bien en zonas subhúmedas y se adapta a suelos pobres y pedregosos. En las\n      riberas del Yanuncay es una especie rara; se registra en tres sitios dentro del casco urbano\n      de Cuenca. Ecológicamente es una especie importante porque sus vistosas flores son un\n      recurso valioso para los colibríes.","usos_tradicionales":"En el sur de Colombia es usada como especie alucinógena (Kvist & Mo-\n      raes, 2006).","propagacion":"Se recomienda propagarla mediante semillas, las cuales luego de ser extraí-\n      das de los frutos maduros, deben secárselas al sol durante 15 días y luego sembrarlas en\n      almácigos.","images":["/resources/img/arboles-143_0.jpg","/resources/img/arboles-143_1.jpg","/resources/img/arboles-143_2.jpg"],"slug":"huntugsillo"},{"page":144,"original":"144   ARBUSTOS NATIVOS\n\n\n\n\n                                   Familia: Verbenaceae\n                                                Udur\n                              Nombre científico: Duranta mutisii L.f.\n                      Otros nombres comunes: “espino”, “mote casa”\n\n      Hábito: Arbusto o árbol pequeño espinoso, tallos erectos cuando jóvenes e inclinados\n      cuando están viejos, ramificación abierta y difusa, brotes tiernos y ramitas terminales ver-\n      de oscuras o moradas.\n\n      Hojas: Simples, dispuestas en verticilos con una espina en la parte inmediata superior al\n      punto de inserción, peciolo de 0,2 a 0,4 cm de largo. Lámina elíptica de 3–6 cm de largo x\n      1–3 cm de ancho, ápice obtuso, base atenuada y margen entero (algunas veces aserrado en\n      la parte superior), haz verde oscuro brillante, envés verde claro glabro.\n\n      Flores: Dispuestas en racimos terminales y axilares de 4–10 cm de largo. Flores bisexuales\n      zigomorfas, cáliz morado, tubular 5 costado, cada costa termina en un diente; corola tu-\n      bular hipocrateriforme de azul pálida o blanquecina de 1,4–1,7 cm de largo, con 5 lóbulos\n      desiguales que se abren oblicuamente; androceo conformado por 4 estambres didínamos,\n      insertos en la parte media del tubo de la corola, filamentos cortos y carnosos, anteras sagi-\n      tadas, dorsifijas con dehiscencia longitudinal; ovario súpero con 4 lóculos divididos, estilo\n      corto y estigma capitado.\n\n      Fruto: Drupa carnosa de 1,5 cm de diámetro, cubierta por el cáliz persistente, amarilla cuan-\n      do está madura. Cada fruto contiene 4 pirenos cada uno con dos semillas.\n\n      Distribución y ecología: Se distribuye en bosques montanos y áreas disturbadas de Ve-\n      nezuela, Colombia, Ecuador y Perú entre 1500 y 3000 m de altitud (Pennington et al, 2004).\n      En nuestro país ha sido registrada en las provincias de Azuay, Bolívar, Cañar, Cotopaxi, Ga-\n      lápagos, Loja y Los Ríos (Jorgensen & León-Yánez, 1999). En los márgenes de los ríos de\n      Cuenca ha sido registrada en el sector de El Paraíso, el Barranco dentro del casco urbano de\n      la Ciudad. Es una especie de rápido crecimiento y es frecuente en remanentes de vegeta-\n      ción secundaria, prefiere sitios húmedos como bordes de quebradas. Sus vistosas flores son\n      visitadas por la especie de colibrí Metallura baroni y sus drupas carnosas sirven de alimento\n      para la pava andina (Penelope montagnii).\n\n      Usos tradicionales: Con sus tallos se elaboran husos y guangos para hilar, sus frutos se em-\n      plean para lavar la cabeza; su madera se usa como leña y sus hojas sirven de alimento para\n      cabras.\n\n      Propagación: Se puede propagar mediante semillas, para el efecto, se deben recolectar los\n      frutos maduros (color amarillo), luego se deben extraer las semillas de los frutos y secarlas\n      al sol. Antes de sembrarlas se recomienda ponerlas en remojo durante 24 horas, con este\n      tratamiento se alcanza porcentajes de germinación entre 10 y 20 %. Acero y Cortés (2014)\n      indican que la germinación de Duranta mutisii en siembra directa, inicia a los 15 días y con-\n      tinúa hasta los 71 días, con este método alcanzan un porcentaje de germinación del 20 %.\n","familia":"Verbenaceae\n\n                              Nombre científico: Duranta mutisii L.f.\n                      Otros nombres comunes: “espino”, “mote casa”","nombre":"Verbenaceae\n                                                Udur","descripcíon":"","otros_nombres_comunes":["espino","mote casa"],"nombre_cientifica":"Duranta mutisii L.f.","habito":" Arbusto o árbol pequeño espinoso, tallos erectos cuando jóvenes e inclinados\n      cuando están viejos, ramificación abierta y difusa, brotes tiernos y ramitas terminales ver-\n      de oscuras o moradas.","hojas":"Simples, dispuestas en verticilos con una espina en la parte inmediata superior al\n      punto de inserción, peciolo de 0,2 a 0,4 cm de largo. Lámina elíptica de 3–6 cm de largo x\n      1–3 cm de ancho, ápice obtuso, base atenuada y margen entero (algunas veces aserrado en\n      la parte superior), haz verde oscuro brillante, envés verde claro glabro.","flores":"Dispuestas en racimos terminales y axilares de 4–10 cm de largo. Flores bisexuales\n      zigomorfas, cáliz morado, tubular 5 costado, cada costa termina en un diente; corola tu-\n      bular hipocrateriforme de azul pálida o blanquecina de 1,4–1,7 cm de largo, con 5 lóbulos\n      desiguales que se abren oblicuamente; androceo conformado por 4 estambres didínamos,\n      insertos en la parte media del tubo de la corola, filamentos cortos y carnosos, anteras sagi-\n      tadas, dorsifijas con dehiscencia longitudinal; ovario súpero con 4 lóculos divididos, estilo\n      corto y estigma capitado.","fruta":"Drupa carnosa de 1,5 cm de diámetro, cubierta por el cáliz persistente, amarilla cuan-\n      do está madura. Cada fruto contiene 4 pirenos cada uno con dos semillas.","distribucion_y_ecologia":"Se distribuye en bosques montanos y áreas disturbadas de Ve-\n      nezuela, Colombia, Ecuador y Perú entre 1500 y 3000 m de altitud (Pennington et al, 2004).\n      En nuestro país ha sido registrada en las provincias de Azuay, Bolívar, Cañar, Cotopaxi, Ga-\n      lápagos, Loja y Los Ríos (Jorgensen & León-Yánez, 1999). En los márgenes de los ríos de\n      Cuenca ha sido registrada en el sector de El Paraíso, el Barranco dentro del casco urbano de\n      la Ciudad. Es una especie de rápido crecimiento y es frecuente en remanentes de vegeta-\n      ción secundaria, prefiere sitios húmedos como bordes de quebradas. Sus vistosas flores son\n      visitadas por la especie de colibrí Metallura baroni y sus drupas carnosas sirven de alimento\n      para la pava andina (Penelope montagnii).","usos_tradicionales":"Con sus tallos se elaboran husos y guangos para hilar, sus frutos se em-\n      plean para lavar la cabeza; su madera se usa como leña y sus hojas sirven de alimento para\n      cabras.","propagacion":"Se puede propagar mediante semillas, para el efecto, se deben recolectar los\n      frutos maduros (color amarillo), luego se deben extraer las semillas de los frutos y secarlas\n      al sol. Antes de sembrarlas se recomienda ponerlas en remojo durante 24 horas, con este\n      tratamiento se alcanza porcentajes de germinación entre 10 y 20 %. Acero y Cortés (2014)\n      indican que la germinación de Duranta mutisii en siembra directa, inicia a los 15 días y con-\n      tinúa hasta los 71 días, con este método alcanzan un porcentaje de germinación del 20 %.","images":["/resources/img/arboles-145_0.jpg","/resources/img/arboles-145_1.jpg","/resources/img/arboles-145_2.jpg","/resources/img/arboles-145_3.jpg","/resources/img/arboles-146_0.jpg","/resources/img/arboles-147_0.jpg"],"slug":"verbenaceae-udur"},{"page":148,"original":"148   ÁRBOLES Y ARBUSTOS INTRODUCIDOS\n\n\n\n\n                                     Familia: Adoxaceae\n                                                 Tilo\n\n                              Nombre científico: Sambucus mexicana C. Presl ex DC.\n                      Otros nombres comunes: “sauco” (México)\n\n      Descripción: Arbusto originario de México y Centro américa. En el Ecuador es ampliamen-\n      te distribuido y cultivado por su fácil propagación y el rápido crecimiento, razón por la cual\n      es común encontrar en los viveros regionales. Localmente forma parte de la vegetación de\n      ribera de nuestros ríos.\n","familia":"Adoxaceae\n","nombre":"Tilo","descripcíon":"Arbusto originario de México y Centro américa. En el Ecuador es ampliamen-\n      te distribuido y cultivado por su fácil propagación y el rápido crecimiento, razón por la cual\n      es común encontrar en los viveros regionales. Localmente forma parte de la vegetación de\n      ribera de nuestros ríos.","otros_nombres_comunes":["sauco (México)"],"nombre_cientifica":"Sambucus mexicana C. Presl ex DC.","habito":"","hojas":"","flores":"","fruta":"","distribucion_y_ecologia":"","usos_tradicionales":"","propagacion":"","images":["/resources/img/arboles-148_0.jpg","/resources/img/arboles-148_1.jpg","/resources/img/arboles-148_2.jpg"],"slug":"tilo"},{"page":149,"original":"                                                                    UNIVERSIDAD DEL AZUAY   149\n\n\n\n\n                           Familia: Anacardiaceae\n                                       Molle\n\n                       Nombre científico: Schhus molle L.\n               Otros nombres comunes: “falso pimentero”, “pimienta del Perú”\n\nDescripción: Árbol originario de Sudamérica, el primer espécimen registrado en el Ecua-\ndor fue en la provincia del Azuay en 1971 (W TROPICOS, 2014), desde entonces se lo puede\nencontrar en varias provincias de los Andes desde los 0 hasta los 3000 m de altura. En\nnuestra región se utiliza como árbol ornamental en parterres de avenidas y en los parques\nlineales de la ciudad.\n","familia":"Anacardiaceae\n","nombre":"Molle","descripcíon":"Árbol originario de Sudamérica, el primer espécimen registrado en el Ecua-\ndor fue en la provincia del Azuay en 1971 (W TROPICOS, 2014), desde entonces se lo puede\nencontrar en varias provincias de los Andes desde los 0 hasta los 3000 m de altura. En\nnuestra región se utiliza como árbol ornamental en parterres de avenidas y en los parques\nlineales de la ciudad.","otros_nombres_comunes":["falso pimentero","pimienta del Perú"],"nombre_cientifica":"Schhus molle L.","habito":"","hojas":"","flores":"","fruta":"","distribucion_y_ecologia":"","usos_tradicionales":"","propagacion":"","images":["/resources/img/arboles-149_0.jpg","/resources/img/arboles-149_1.jpg","/resources/img/arboles-149_2.jpg"],"slug":"molle"},{"page":150,"original":"150   ÁRBOLES Y ARBUSTOS INTRODUCIDOS\n\n\n\n\n                                   Familia: Apocynaceae\n                                               Laurel\n                              Nombre científico: Nerium oleander L.\n                      Otros nombres comunes: “adelfa”, “laurel de flor”\n\n\n      Descripción: Arbusto originario de la cuenca del mar Mediterráneo hasta China. Hoy en\n      día ha sido introducida a varios países de clima cálido árido. En nuestra región es común\n      encontrar tanto en jardines privados como en públicos. Planta considerada muy tóxica, sus\n      flores son fuente de alimento para polillas, y las hojas son consumidas por las orugas sin ser\n      afectadas por sus sustancias tóxicas.\n","familia":"Apocynaceae\n\n                              Nombre científico: Nerium oleander L.\n                      Otros nombres comunes: “adelfa”, “laurel de flor”","nombre":"Apocynaceae\n                                               Laurel","descripcíon":"Arbusto originario de la cuenca del mar Mediterráneo hasta China. Hoy en\n      día ha sido introducida a varios países de clima cálido árido. En nuestra región es común\n      encontrar tanto en jardines privados como en públicos. Planta considerada muy tóxica, sus\n      flores son fuente de alimento para polillas, y las hojas son consumidas por las orugas sin ser\n      afectadas por sus sustancias tóxicas.","otros_nombres_comunes":["adelfa","laurel de flor"],"nombre_cientifica":"Nerium oleander L.","habito":"","hojas":"","flores":"","fruta":"","distribucion_y_ecologia":"","usos_tradicionales":"","propagacion":"","images":["/resources/img/arboles-150_0.jpg","/resources/img/arboles-150_1.jpg","/resources/img/arboles-150_2.jpg"],"slug":"apocynaceae-laurel"},{"page":151,"original":"                                                                     UNIVERSIDAD DEL AZUAY    151\n\n\n\n\n                            Familia: Asparagaceae\n                                Ramo de novia\n                       Nombre científico: Yucca guatemalensis Baker\n                Otros nombres comunes: “izote” (El Salvador y Guatemala),\n                                       “yucca” (España), “itabo” (Costa Rica)\n\nDescripción: Árbol originario de Centroamérica. Se distribuye en México, Guatemala y El\nSalvador en donde se le considera la flor nacional. Introducida a nuestro país y registrada\nen las provincias de Azuay, Guayas y Los Ríos. Localmente se emplea como ornamental.\n","familia":"Asparagaceae\n\n                       Nombre científico: Yucca guatemalensis Baker\n                Otros nombres comunes: “izote” (El Salvador y Guatemala),\n                                       “yucca” (España), “itabo” (Costa Rica)","nombre":"Asparagaceae\n                                Ramo de novia","descripcíon":"Árbol originario de Centroamérica. Se distribuye en México, Guatemala y El\nSalvador en donde se le considera la flor nacional. Introducida a nuestro país y registrada\nen las provincias de Azuay, Guayas y Los Ríos. Localmente se emplea como ornamental.","otros_nombres_comunes":["izote (El Salvador y Guatemala)","yucca (España)","itabo (Costa Rica)"],"nombre_cientifica":"Yucca guatemalensis Baker","habito":"","hojas":"","flores":"","fruta":"","distribucion_y_ecologia":"","usos_tradicionales":"","propagacion":"","images":["/resources/img/arboles-151_0.jpg","/resources/img/arboles-151_1.jpg","/resources/img/arboles-151_2.jpg","/resources/img/arboles-152_0.jpg"],"slug":"asparagaceae-ramo-de-novia"},{"page":153,"original":"                                                                      UNIVERSIDAD DEL AZUAY    153\n\n\n\n\n                             Familia: Bignoniaceae\n                                     Jacaranda\n\n                        Nombre científico: Jacaranda mimosifolia D. Don\n                Otros nombres comunes: “jacarandá”, “tarco”\n\nDescripción: El nombre de jacarandá proviene de su nombre nativo guaraní y significa\nfragante. Árbol originario de Sudamérica, se distribuye en Brasil, Bolivia, Paraguay y en el\nNoreste de Argentina. En nuestro país ha sido registrada en las provincias de Azuay, Gua-\nyas, Chimborazo, Loja, Pichincha y Tungurahua. Localmente se emplea como ornamental\nen los cementerios, parterres de las avenidas y en los parques y jardines de la ciudad.\n","familia":"Bignoniaceae\n","nombre":"Jacaranda","descripcíon":"El nombre de jacarandá proviene de su nombre nativo guaraní y significa\nfragante. Árbol originario de Sudamérica, se distribuye en Brasil, Bolivia, Paraguay y en el\nNoreste de Argentina. En nuestro país ha sido registrada en las provincias de Azuay, Gua-\nyas, Chimborazo, Loja, Pichincha y Tungurahua. Localmente se emplea como ornamental\nen los cementerios, parterres de las avenidas y en los parques y jardines de la ciudad.","otros_nombres_comunes":["jacarandá","tarco"],"nombre_cientifica":"Jacaranda mimosifolia D. Don","habito":"","hojas":"","flores":"","fruta":"","distribucion_y_ecologia":"","usos_tradicionales":"","propagacion":"","images":["/resources/img/arboles-153_0.jpg","/resources/img/arboles-153_1.jpg","/resources/img/arboles-153_2.jpg"],"slug":"jacaranda"},{"page":154,"original":"154   ÁRBOLES Y ARBUSTOS INTRODUCIDOS\n\n\n\n\n                                  Familia: Bignoniaceae\n                                             Fresno\n\n                             Nombre científico: Tecoma stans (L.) Juss. ex Kunth\n                      Otros nombres comunes: “cholán”, “vainillo”\n\n      Descripción: Árbol que se distribuye desde Argentina hasta el sudeste de los Estados Uni-\n      dos. En nuestro país se ha registrado en las provincias de Azuay, Cañar, Carchi, Chimbora-\n      zo, Imbabura, Loja, Pichincha y Tungurahua sin embargo no están en estado silvestre. Lo-\n      calmente se emplea como ornamental; sus flores son muy visitadas por abejas y colibríes.\n      La facilidad de la dispersión de las semillas la convierte en una planta invasora.\n","familia":"Bignoniaceae\n","nombre":"Fresno","descripcíon":"Árbol que se distribuye desde Argentina hasta el sudeste de los Estados Uni-\n      dos. En nuestro país se ha registrado en las provincias de Azuay, Cañar, Carchi, Chimbora-\n      zo, Imbabura, Loja, Pichincha y Tungurahua sin embargo no están en estado silvestre. Lo-\n      calmente se emplea como ornamental; sus flores son muy visitadas por abejas y colibríes.\n      La facilidad de la dispersión de las semillas la convierte en una planta invasora.","otros_nombres_comunes":["cholán","vainillo"],"nombre_cientifica":"Tecoma stans (L.) Juss. ex Kunth","habito":"","hojas":"","flores":"","fruta":"","distribucion_y_ecologia":"","usos_tradicionales":"","propagacion":"","images":["/resources/img/arboles-154_0.jpg","/resources/img/arboles-154_1.jpg","/resources/img/arboles-154_2.jpg","/resources/img/arboles-155_0.jpg"],"slug":"fresno"},{"page":156,"original":"156   ÁRBOLES Y ARBUSTOS INTRODUCIDOS\n\n\n\n\n                                  Familia: Casuarinaceae\n                                           Casuarina\n\n                     Nombre científico: Casuarina equisetifolia L.\n              Otros nombres comunes: “pino australiano”, “casuarina cola de caballo”\n\n      Descripción: Árbol endémico de Australia, Malasia y Polinesia. En el Ecuador se ha registra-\n      do en las provincias de Guayas, Tungurahua, Galápagos, Azuay, Imbabura y Chimborazo.\n      Especie maderable, soporta suelos pobres y es capaz de fijar nitrógeno atmosférico. Lo-\n      calmente se utiliza como árbol ornamental y se encuentra en los parques de la ciudad de\n      Cuenca y de los cantones de la provincia.\n","familia":"Casuarinaceae\n","nombre":"Casuarina","descripcíon":"Árbol endémico de Australia, Malasia y Polinesia. En el Ecuador se ha registra-\n      do en las provincias de Guayas, Tungurahua, Galápagos, Azuay, Imbabura y Chimborazo.\n      Especie maderable, soporta suelos pobres y es capaz de fijar nitrógeno atmosférico. Lo-\n      calmente se utiliza como árbol ornamental y se encuentra en los parques de la ciudad de\n      Cuenca y de los cantones de la provincia.","otros_nombres_comunes":["pino australiano","casuarina cola de caballo"],"nombre_cientifica":"Casuarina equisetifolia L.","habito":"","hojas":"","flores":"","fruta":"","distribucion_y_ecologia":"","usos_tradicionales":"","propagacion":"","images":["/resources/img/arboles-156_0.jpg","/resources/img/arboles-156_1.jpg","/resources/img/arboles-156_2.jpg"],"slug":"casuarina"},{"page":157,"original":"                                                                     UNIVERSIDAD DEL AZUAY    157\n\n\n\n\n                            Familia: Cupressaceae\n                                        Ciprés\n\n                       Nombre científico: Cupressus macrocarpa Hartw\n                Otros nombres comunes: “ciprés de Monterrey” (Estados Unidos)\n\nDescripción: Árbol originario de la Bahía de Monterrey en California, Estados Unidos. En el\nEcuador se distribuye en las provincias de Pichincha, Azuay, Carchi, Chimborazo, Imbabura.\nSe ha visto rodales de esta especie hasta los 3200 m de altitud. Su tronco es maderable y\npor su follaje denso se utiliza en cortinas rompevientos. Localmente es común encontrar\nen la orilla de los ríos de la ciudad de Cuenca.\n","familia":"Cupressaceae\n","nombre":"Ciprés","descripcíon":"Árbol originario de la Bahía de Monterrey en California, Estados Unidos. En el\nEcuador se distribuye en las provincias de Pichincha, Azuay, Carchi, Chimborazo, Imbabura.\nSe ha visto rodales de esta especie hasta los 3200 m de altitud. Su tronco es maderable y\npor su follaje denso se utiliza en cortinas rompevientos. Localmente es común encontrar\nen la orilla de los ríos de la ciudad de Cuenca.","otros_nombres_comunes":["ciprés de Monterrey (Estados Unidos)"],"nombre_cientifica":"Cupressus macrocarpa Hartw","habito":"","hojas":"","flores":"","fruta":"","distribucion_y_ecologia":"","usos_tradicionales":"","propagacion":"","images":["/resources/img/arboles-157_0.jpg","/resources/img/arboles-157_1.jpg","/resources/img/arboles-157_2.jpg","/resources/img/arboles-158_0.jpg"],"slug":"ciprs"},{"page":159,"original":"                                                                       UNIVERSIDAD DEL AZUAY    159\n\n\n\n\n                            Familia: Euphorbiaceae\n                                     Higuerilla\n\n                        Nombre científico: Ricinus communis L.\n                Otros nombres comunes: “ricino”\n\nDescripción: Arbusto originario de África tropical y actualmente naturalizado en los climas\ntemplados de todo el mundo. Localmente tiende a invadir hábitats perturbados, sobre\ntodo los bordes de las carreteras, las orillas de los ríos y terrenos agrícolas. Con frecuen-\ncia compite con la vegetación autóctona en los cursos de agua hasta sustituirla. La planta\nentera se utiliza para la elaboración de abono verde y por la forma y color de sus hojas se\nutiliza en ornamentación. También el aceite extraído de su semilla es un potente laxante.\n","familia":"Euphorbiaceae\n","nombre":"Higuerilla","descripcíon":"Arbusto originario de África tropical y actualmente naturalizado en los climas\ntemplados de todo el mundo. Localmente tiende a invadir hábitats perturbados, sobre\ntodo los bordes de las carreteras, las orillas de los ríos y terrenos agrícolas. Con frecuen-\ncia compite con la vegetación autóctona en los cursos de agua hasta sustituirla. La planta\nentera se utiliza para la elaboración de abono verde y por la forma y color de sus hojas se\nutiliza en ornamentación. También el aceite extraído de su semilla es un potente laxante.","otros_nombres_comunes":["ricino"],"nombre_cientifica":"Ricinus communis L.","habito":"","hojas":"","flores":"","fruta":"","distribucion_y_ecologia":"","usos_tradicionales":"","propagacion":"","images":["/resources/img/arboles-159_0.jpg","/resources/img/arboles-159_1.jpg","/resources/img/arboles-159_2.jpg"],"slug":"higuerilla"},{"page":160,"original":"160   ÁRBOLES Y ARBUSTOS INTRODUCIDOS\n\n\n\n\n                                        Familia: Fabaceae\n                                             Acacia\n\n                             Nombre científico: Acacia dealbata Link\n                      Otros nombres comunes: “mimosa”, “acacia Australiana”\n\n      Descripción: Árbol originario de Australia y Tasmania. En el Ecuador ha sido introducida\n      con fines ornamentales, sin embargo por la fácil propagación y su dureza para el estableci-\n      miento inicial en suelos degradados se ha utilizado en programas de revegetación. Local-\n      mente se encuentra formando agregados monoespecíficos en los taludes de las carreteras\n      y ríos, poniendo en riesgo la vegetación nativa.\n","familia":"Fabaceae\n","nombre":"Acacia","descripcíon":"Árbol originario de Australia y Tasmania. En el Ecuador ha sido introducida\n      con fines ornamentales, sin embargo por la fácil propagación y su dureza para el estableci-\n      miento inicial en suelos degradados se ha utilizado en programas de revegetación. Local-\n      mente se encuentra formando agregados monoespecíficos en los taludes de las carreteras\n      y ríos, poniendo en riesgo la vegetación nativa.","otros_nombres_comunes":["mimosa","acacia Australiana"],"nombre_cientifica":"Acacia dealbata Link","habito":"","hojas":"","flores":"","fruta":"","distribucion_y_ecologia":"","usos_tradicionales":"","propagacion":"","images":["/resources/img/arboles-160_0.jpg","/resources/img/arboles-160_1.jpg","/resources/img/arboles-160_2.jpg"],"slug":"acacia"},{"page":161,"original":"                                                                       UNIVERSIDAD DEL AZUAY    161\n\n\n\n\n                                Familia: Fabaceae\n                                        Acacia\n\n                        Nombre científico: Acacia melanoxylon R. Br.\n                Otros nombres comunes: “madera negra de Tasmania”\n\nDescripción: Árbol originario de Australia. El nombre de la especie es melanoxylon, epíteto\nlatino que significa madera negra. Árbol de hoja perenne, soporta varios ambientes, espe-\ncialmente los fríos. Ha sido introducida a varios países del mundo y en muchos de ellos, de-\nbido a su capacidad invasiva se ha convertido en especie plaga. Localmente es abundante\nen parterres y taludes de las vías así como en los parques y jardines de la ciudad de Cuenca.\n","familia":"Fabaceae\n","nombre":"Acacia","descripcíon":"Árbol originario de Australia. El nombre de la especie es melanoxylon, epíteto\nlatino que significa madera negra. Árbol de hoja perenne, soporta varios ambientes, espe-\ncialmente los fríos. Ha sido introducida a varios países del mundo y en muchos de ellos, de-\nbido a su capacidad invasiva se ha convertido en especie plaga. Localmente es abundante\nen parterres y taludes de las vías así como en los parques y jardines de la ciudad de Cuenca.","otros_nombres_comunes":["madera negra de Tasmania"],"nombre_cientifica":"Acacia melanoxylon R. Br.","habito":"","hojas":"","flores":"","fruta":"","distribucion_y_ecologia":"","usos_tradicionales":"","propagacion":"","images":["/resources/img/arboles-161_0.jpg","/resources/img/arboles-161_1.jpg","/resources/img/arboles-161_2.jpg","/resources/img/arboles-162_0.jpg"],"slug":"acacia"},{"page":163,"original":"                                                                    UNIVERSIDAD DEL AZUAY   163\n\n\n\n\n                               Familia: Fabaceae\n                                      Acacia\n\n                       Nombre científico: Acacia retinodes Schltdl\n               Otros nombres comunes: “acacia plateada”, acacia amarilla”\n\nDescripción: Especie originaria de Australia. Árbol perenne distribuido en todo el mundo\npor su resistencia a condiciones de clima y suelo. Introducido al Ecuador con fines neta-\nmente ornamentales debido a su capacidad de mantener su floración por periodos largos.\nLocalmente es rara y no ha demostrado su capacidad invasiva como las otras especies de\nacacias citadas anteriormente.\n","familia":"Fabaceae\n","nombre":"Acacia","descripcíon":"Especie originaria de Australia. Árbol perenne distribuido en todo el mundo\npor su resistencia a condiciones de clima y suelo. Introducido al Ecuador con fines neta-\nmente ornamentales debido a su capacidad de mantener su floración por periodos largos.\nLocalmente es rara y no ha demostrado su capacidad invasiva como las otras especies de\nacacias citadas anteriormente.","otros_nombres_comunes":["acacia plateada","acacia amarilla"],"nombre_cientifica":"Acacia retinodes Schltdl","habito":"","hojas":"","flores":"","fruta":"","distribucion_y_ecologia":"","usos_tradicionales":"","propagacion":"","images":["/resources/img/arboles-163_0.jpg","/resources/img/arboles-163_1.jpg","/resources/img/arboles-163_2.jpg"],"slug":"acacia"},{"page":164,"original":"164   ÁRBOLES Y ARBUSTOS INTRODUCIDOS\n\n\n\n\n                                        Familia: Fabaceae\n                                           Pedorrea\n                Nombre científico: Albizia lophantha (Willd.) Benth\n        Otros nombres comunes: “albicia amarilla”, “acacia plumosa”, “albizia de\n                               plumas”, “peorrilla o peo alemán” (Chile).\n      Descripción: Especie originaria de Sudamérica. En Chile se la conoce con el nombre de\n      Peorrilla o Peo alemán por el olor de sus semillas al abrirse. El nombre de la especie es\n      lophantha, epíteto latino que significa flor con cresta. Árbol perenne, crece naturalmente\n      en varios ambientes. Localmente es común encontrarla en las riberas de los ríos de la Ciu-\n      dad de Cuenca. Sus flores son visitadas por abejas.\n","familia":"Fabaceae\n\n                Nombre científico: Albizia lophantha (Willd.) Benth\n        Otros nombres comunes: “albicia amarilla”, “acacia plumosa”, “albizia de\n                               plumas”, “peorrilla o peo alemán” (Chile).\n      Descripción: Especie originaria de Sudamérica. En Chile se la conoce con el nombre de\n      Peorrilla o Peo alemán por el olor de sus semillas al abrirse. El nombre de la especie es\n      lophantha, epíteto latino que significa flor con cresta. Árbol perenne, crece naturalmente\n      en varios ambientes. Localmente es común encontrarla en las riberas de los ríos de la Ciu-\n      dad de Cuenca. Sus flores son visitadas por abejas.","nombre":"Fabaceae\n                                           Pedorrea","descripcíon":"Especie originaria de Sudamérica. En Chile se la conoce con el nombre de\n      Peorrilla o Peo alemán por el olor de sus semillas al abrirse. El nombre de la especie es\n      lophantha, epíteto latino que significa flor con cresta. Árbol perenne, crece naturalmente\n      en varios ambientes. Localmente es común encontrarla en las riberas de los ríos de la Ciu-\n      dad de Cuenca. Sus flores son visitadas por abejas.","otros_nombres_comunes":["albicia amarilla","acacia plumosa","albizia de\n                               plumas","peorrilla o peo alemán (Chile)."],"nombre_cientifica":"Albizia lophantha (Willd.) Benth","habito":"","hojas":"","flores":"","fruta":"","distribucion_y_ecologia":"","usos_tradicionales":"","propagacion":"","images":["/resources/img/arboles-164_0.jpg","/resources/img/arboles-164_1.jpg","/resources/img/arboles-164_2.jpg"],"slug":"fabaceae-pedorrea"},{"page":165,"original":"                                                                        UNIVERSIDAD DEL AZUAY     165\n\n\n\n\n                                 Familia: Fabaceae\n                                Retama amarilla\n           Nombre científico: Genista monspessulana (L.) L.A.S. Johnson\n   Otros nombres comunes: “retamilla”.\n\nDescripción: Especie originaria del Mediterráneo. En el Ecuador este arbusto ha sido regis-\ntrado en Chimborazo, Cotopaxi, Azuay, Imbabura y Pichincha. Prefiere suelos pobres en\ndonde compite con la flora nativa. Localmente se encuentra en los bordes de las carreteras\no en las riberas de los ríos en donde el suelo fértil ha sido retirado. Por su alta invasividad\nno se recomienda en programas de revegetación.\n","familia":"Fabaceae\n\n           Nombre científico: Genista monspessulana (L.) L.A.S. Johnson\n   Otros nombres comunes: “retamilla”.","nombre":"Fabaceae\n                                Retama amarilla","descripcíon":"Especie originaria del Mediterráneo. En el Ecuador este arbusto ha sido regis-\ntrado en Chimborazo, Cotopaxi, Azuay, Imbabura y Pichincha. Prefiere suelos pobres en\ndonde compite con la flora nativa. Localmente se encuentra en los bordes de las carreteras\no en las riberas de los ríos en donde el suelo fértil ha sido retirado. Por su alta invasividad\nno se recomienda en programas de revegetación.","otros_nombres_comunes":["retamilla."],"nombre_cientifica":"Genista monspessulana (L.) L.A.S. Johnson","habito":"","hojas":"","flores":"","fruta":"","distribucion_y_ecologia":"","usos_tradicionales":"","propagacion":"","images":["/resources/img/arboles-165_0.jpg","/resources/img/arboles-165_1.jpg","/resources/img/arboles-165_2.jpg"],"slug":"fabaceae-retama-amarilla"},{"page":166,"original":"166   ÁRBOLES Y ARBUSTOS INTRODUCIDOS\n\n\n\n\n                                        Familia: Fabaceae\n                                              Retama\n                              Nombre científico: Spartium junceum L.\n                      Otros nombres comunes: “retama de olor” (España)\n\n      Descripción: Arbusto originario del Mediterráneo. En el Ecuador crece desde los 2000 has-\n      ta los 2800 m de altura en las provincias de Azuay, Bolívar, Carchi, Imbabura, Loja, Pichincha\n      y Tungurahua. En nuestra región se encuentra compitiendo con la vegetación nativa de\n      suelos pobres y rocosos. Localmente es utilizado como forraje de cuyes, adorno en fiestas\n      religiosas; con las ramas se elaboran escobas, además es utilizado como combustible.\n","familia":"Fabaceae\n\n                              Nombre científico: Spartium junceum L.\n                      Otros nombres comunes: “retama de olor” (España)","nombre":"Fabaceae\n                                              Retama","descripcíon":"Arbusto originario del Mediterráneo. En el Ecuador crece desde los 2000 has-\n      ta los 2800 m de altura en las provincias de Azuay, Bolívar, Carchi, Imbabura, Loja, Pichincha\n      y Tungurahua. En nuestra región se encuentra compitiendo con la vegetación nativa de\n      suelos pobres y rocosos. Localmente es utilizado como forraje de cuyes, adorno en fiestas\n      religiosas; con las ramas se elaboran escobas, además es utilizado como combustible.","otros_nombres_comunes":["retama de olor (España)"],"nombre_cientifica":"Spartium junceum L.","habito":"","hojas":"","flores":"","fruta":"","distribucion_y_ecologia":"","usos_tradicionales":"","propagacion":"","images":["/resources/img/arboles-166_0.jpg","/resources/img/arboles-166_1.jpg","/resources/img/arboles-166_2.jpg"],"slug":"fabaceae-retama"},{"page":167,"original":"                                                                        UNIVERSIDAD DEL AZUAY     167\n\n\n\n\n                                 Familia: Fabaceae\n                                       Palo rosa\n                        Nombre científico: Tipuana tipu (Benth.) Kuntze\n                Otros nombres comunes: “tipa”, “tipa blanca”, “tipuana”\n\nDescripción: Especie originaria de Argentina y Bolivia, introducida al Ecuador con fines\nornamentales. En la ciudad de Cuenca es un elemento importante en el paisaje de las áreas\nverdes de la ciudad, se encuentra en parterres de las avenidas, en las riberas de los ríos y en\nlos centros universitarios. Un individuo de esta especie que se encuentra en la Universidad\ndel Azuay fue nominado árbol patrimonial de la ciudad en el año 2013.\n","familia":"Fabaceae\n\n                        Nombre científico: Tipuana tipu (Benth.) Kuntze\n                Otros nombres comunes: “tipa”, “tipa blanca”, “tipuana”","nombre":"Fabaceae\n                                       Palo rosa","descripcíon":"Especie originaria de Argentina y Bolivia, introducida al Ecuador con fines\nornamentales. En la ciudad de Cuenca es un elemento importante en el paisaje de las áreas\nverdes de la ciudad, se encuentra en parterres de las avenidas, en las riberas de los ríos y en\nlos centros universitarios. Un individuo de esta especie que se encuentra en la Universidad\ndel Azuay fue nominado árbol patrimonial de la ciudad en el año 2013.","otros_nombres_comunes":["tipa","tipa blanca","tipuana"],"nombre_cientifica":"Tipuana tipu (Benth.) Kuntze","habito":"","hojas":"","flores":"","fruta":"","distribucion_y_ecologia":"","usos_tradicionales":"","propagacion":"","images":["/resources/img/arboles-167_0.jpg","/resources/img/arboles-167_1.jpg","/resources/img/arboles-167_2.jpg","/resources/img/arboles-167_3.jpg","/resources/img/arboles-167_4.jpg"],"slug":"fabaceae-palo-rosa"},{"page":168,"original":"168   ÁRBOLES Y ARBUSTOS INTRODUCIDOS\n\n\n\n\n                                        Familia: Fabaceae\n                                    Retama espinosa\n\n                         Nombre científico: Ulex europaeus L.\n                 Otros nombres comunes: “retamillo”, “retamo espinoso”, “espinillo”\n\n      Descripción: Arbusto originario del oeste y centro de Europa. Está considerado como pla-\n      ga de la agricultura y la silvicultura, porque forma matorrales densos que reducen el pas-\n      to. Está incluido en la lista 100 de las especies exóticas invasoras más dañinas del mundo\n      (Lowe et al, 2004). Localmente se encuentra formando agregados monoespecíficos en va-\n      rios sitios del río Yanuncay.\n","familia":"Fabaceae\n","nombre":"Retama espinosa","descripcíon":"Arbusto originario del oeste y centro de Europa. Está considerado como pla-\n      ga de la agricultura y la silvicultura, porque forma matorrales densos que reducen el pas-\n      to. Está incluido en la lista 100 de las especies exóticas invasoras más dañinas del mundo\n      (Lowe et al, 2004). Localmente se encuentra formando agregados monoespecíficos en va-\n      rios sitios del río Yanuncay.","otros_nombres_comunes":["retamillo","retamo espinoso","espinillo"],"nombre_cientifica":"Ulex europaeus L.","habito":"","hojas":"","flores":"","fruta":"","distribucion_y_ecologia":"","usos_tradicionales":"","propagacion":"","images":["/resources/img/arboles-168_0.jpg","/resources/img/arboles-168_1.jpg","/resources/img/arboles-168_2.jpg"],"slug":"retama-espinosa"},{"page":169,"original":"                                                                       UNIVERSIDAD DEL AZUAY    169\n\n\n\n\n                               Familia: Malvaceae\n                                       Cucarda\n\n                        Nombre científico: Hibiscus rosa-sinensis L.\n                Otros nombres comunes: “hibisco”, “rosa de China”\n\nDescripción: Arbusto originario de Asia oriental, es considerado la flor nacional de Malasia,\nllamado Bunga Raya en malayo. Asimismo la flor se encuentra impresa en los billetes y\nmonedas del ringgit malayo. Sus hermosas flores son utilizadas en ornamentación en los\ntrópicos y subtrópicos. Localmente es muy común encontrarla en los parques lineales de\nnuestra ciudad. Sus vistosas flores son visitadas por los colibríes.\n","familia":"Malvaceae\n","nombre":"Cucarda","descripcíon":"Arbusto originario de Asia oriental, es considerado la flor nacional de Malasia,\nllamado Bunga Raya en malayo. Asimismo la flor se encuentra impresa en los billetes y\nmonedas del ringgit malayo. Sus hermosas flores son utilizadas en ornamentación en los\ntrópicos y subtrópicos. Localmente es muy común encontrarla en los parques lineales de\nnuestra ciudad. Sus vistosas flores son visitadas por los colibríes.","otros_nombres_comunes":["hibisco","rosa de China"],"nombre_cientifica":"Hibiscus rosa-sinensis L.","habito":"","hojas":"","flores":"","fruta":"","distribucion_y_ecologia":"","usos_tradicionales":"","propagacion":"","images":["/resources/img/arboles-169_0.jpg","/resources/img/arboles-169_1.jpg","/resources/img/arboles-169_2.jpg"],"slug":"cucarda"},{"page":170,"original":"170   ÁRBOLES Y ARBUSTOS INTRODUCIDOS\n\n\n\n\n                                     Familia: Myrtaceae\n                                             Cepillo\n\n                             Nombre científico: Callistemon lanceolatus (Sm.)\n                      Otros nombres comunes: “árbol del cepillo”\n\n      Descripción: Árbol originario de Australia. Etimológicamente Callistemon nombre genéri-\n      co que proviene del griego y significa de estambres hermosos, por aludir a lo espectacular\n      de sus inflorescencias. Introducido al Ecuador por sus características ornamentales. Local-\n      mente es un elemento importante del ornato de la ciudad. Sus vistosas flores son visitadas\n      por abejas y colibríes.\n","familia":"Myrtaceae\n","nombre":"Cepillo","descripcíon":"Árbol originario de Australia. Etimológicamente Callistemon nombre genéri-\n      co que proviene del griego y significa de estambres hermosos, por aludir a lo espectacular\n      de sus inflorescencias. Introducido al Ecuador por sus características ornamentales. Local-\n      mente es un elemento importante del ornato de la ciudad. Sus vistosas flores son visitadas\n      por abejas y colibríes.","otros_nombres_comunes":["árbol del cepillo"],"nombre_cientifica":"Callistemon lanceolatus (Sm.)","habito":"","hojas":"","flores":"","fruta":"","distribucion_y_ecologia":"","usos_tradicionales":"","propagacion":"","images":["/resources/img/arboles-170_0.jpg","/resources/img/arboles-170_1.jpg","/resources/img/arboles-170_2.jpg"],"slug":"cepillo"},{"page":171,"original":"                                                                     UNIVERSIDAD DEL AZUAY    171\n\n\n\n\n                               Familia: Myrtaceae\n                                 Cepillo blanco\n\n                       Nombre científico: Callistemon salignus (Sm.) Sweet\n                Otros nombres comunes: “limpia tubos de flor blanca”\n\nDescripción: Árbol originario de la costa este de Australia, introducida al Ecuador con fi-\nnes ornamentales. Actualmente es común encontrar en los parques lineales de los ríos de\nCuenca. Sus vistosas flores son visitadas por abejas y colibríes.\n","familia":"Myrtaceae\n","nombre":"Cepillo blanco","descripcíon":"Árbol originario de la costa este de Australia, introducida al Ecuador con fi-\nnes ornamentales. Actualmente es común encontrar en los parques lineales de los ríos de\nCuenca. Sus vistosas flores son visitadas por abejas y colibríes.","otros_nombres_comunes":["limpia tubos de flor blanca"],"nombre_cientifica":"Callistemon salignus (Sm.) Sweet","habito":"","hojas":"","flores":"","fruta":"","distribucion_y_ecologia":"","usos_tradicionales":"","propagacion":"","images":["/resources/img/arboles-171_0.jpg","/resources/img/arboles-171_1.jpg","/resources/img/arboles-171_2.jpg"],"slug":"cepillo-blanco"},{"page":172,"original":"172   ÁRBOLES Y ARBUSTOS INTRODUCIDOS\n\n\n\n\n                                    Familia: Myrtaceae\n                                 Eucalipto aromático\n                       Nombre científico: Eucalyptus citriodora Hook\n                Otros nombres comunes: “eucalipto olor de limón”, “eucalipto limón”,\n                                       “eucalipto moteado”\n      Descripción: Especie originaria de Australia, introducida al Ecuador como árbol maderable,\n      sin embargo no existe plantaciones comerciales de esta especie. Por otro lado su denso\n      follaje y abundancia de flores hace de este árbol un potencial ornamental y productor de\n      miel. En el río Yanuncay se registró un solo individuo en el sector de Monay.\n","familia":"Myrtaceae\n\n                       Nombre científico: Eucalyptus citriodora Hook\n                Otros nombres comunes: “eucalipto olor de limón”, “eucalipto limón”,\n                                       “eucalipto moteado”\n      Descripción: Especie originaria de Australia, introducida al Ecuador como árbol maderable,\n      sin embargo no existe plantaciones comerciales de esta especie. Por otro lado su denso\n      follaje y abundancia de flores hace de este árbol un potencial ornamental y productor de\n      miel. En el río Yanuncay se registró un solo individuo en el sector de Monay.","nombre":"Myrtaceae\n                                 Eucalipto aromático","descripcíon":"Especie originaria de Australia, introducida al Ecuador como árbol maderable,\n      sin embargo no existe plantaciones comerciales de esta especie. Por otro lado su denso\n      follaje y abundancia de flores hace de este árbol un potencial ornamental y productor de\n      miel. En el río Yanuncay se registró un solo individuo en el sector de Monay.","otros_nombres_comunes":["eucalipto olor de limón","eucalipto limón","eucalipto moteado"],"nombre_cientifica":"Eucalyptus citriodora Hook","habito":"","hojas":"","flores":"","fruta":"","distribucion_y_ecologia":"","usos_tradicionales":"","propagacion":"","images":["/resources/img/arboles-172_0.jpg","/resources/img/arboles-172_1.jpg","/resources/img/arboles-172_2.jpg"],"slug":"myrtaceae-eucalipto-aromtico"},{"page":173,"original":"                                                                    UNIVERSIDAD DEL AZUAY   173\n\n\n\n\n                              Familia: Myrtaceae\n                                    Eucalipto\n         Nombre científico: Eucalyptus globulus Labill\n Otros nombres comunes: “eucalipto blanco”, “eucalipto común”, “eucalipto azul”\n\n\nDescripción: Árbol originario de Australia y Tasmania. Se introdujo en los países andinos\nhace más de 200 años entre las alturas de 2200 y 3200 m con fines maderables, desde en-\ntonces ha sido plantado en forma masiva por lo que representa una de las especies más co-\nmunes en nuestros paisajes. En las riberas de los ríos de Cuenca es una especie dominante\ne invasora, la misma que ha reemplazado la vegetación nativa.\n","familia":"Myrtaceae\n\n         Nombre científico: Eucalyptus globulus Labill\n Otros nombres comunes: “eucalipto blanco”, “eucalipto común”, “eucalipto azul”","nombre":"Myrtaceae\n                                    Eucalipto","descripcíon":"Árbol originario de Australia y Tasmania. Se introdujo en los países andinos\nhace más de 200 años entre las alturas de 2200 y 3200 m con fines maderables, desde en-\ntonces ha sido plantado en forma masiva por lo que representa una de las especies más co-\nmunes en nuestros paisajes. En las riberas de los ríos de Cuenca es una especie dominante\ne invasora, la misma que ha reemplazado la vegetación nativa.","otros_nombres_comunes":["eucalipto blanco","eucalipto común","eucalipto azul"],"nombre_cientifica":"Eucalyptus globulus Labill","habito":"","hojas":"","flores":"","fruta":"","distribucion_y_ecologia":"","usos_tradicionales":"","propagacion":"","images":["/resources/img/arboles-173_0.jpg","/resources/img/arboles-173_1.jpg","/resources/img/arboles-173_2.jpg"],"slug":"myrtaceae-eucalipto"},{"page":174,"original":"174   ÁRBOLES Y ARBUSTOS INTRODUCIDOS\n\n\n\n\n                                    Familia: Myrtaceae\n                                     Cereza magenta\n\n                             Nombre científico: Syzygium paniculatum (Lam.) DC.\n                      Otros nombres comunes: “eugenia”\n\n      Descripción: Árbol originario de Australia. Introducido al Ecuador para programas de orna-\n      mentación. En nuestra región son parte de las plantas ornamentales de parque y jardines.\n      Las flores son visitadas por abejas, y sus frutos son comestibles.\n","familia":"Myrtaceae\n","nombre":"Cereza magenta","descripcíon":"Árbol originario de Australia. Introducido al Ecuador para programas de orna-\n      mentación. En nuestra región son parte de las plantas ornamentales de parque y jardines.\n      Las flores son visitadas por abejas, y sus frutos son comestibles.","otros_nombres_comunes":["eugenia"],"nombre_cientifica":"Syzygium paniculatum (Lam.) DC.","habito":"","hojas":"","flores":"","fruta":"","distribucion_y_ecologia":"","usos_tradicionales":"","propagacion":"","images":["/resources/img/arboles-174_0.jpg","/resources/img/arboles-174_1.jpg","/resources/img/arboles-174_2.jpg"],"slug":"cereza-magenta"},{"page":175,"original":"                                                                  UNIVERSIDAD DEL AZUAY   175\n\n\n\n\n                              Familia: Oleaceae\n                                     Urapán\n                      Nombre científico: Fraxinus excelsior L.\n               Otros nombres comunes: “fresno norteño”, “fresno común”,\n                                      “fresno grande”.\n\nDescripción: Especie originaria de Europa. Árbol de excelente madera, sin embargo en el\nEcuador no existe plantaciones con fines comerciales sino más bien utilizados en orna-\nmentación. A pesar de la producción abundante de semillas no se registrado regeneración\nnatural. Localmente es común encontrarlo formando parte de la vegetación de ribera de\nlos ríos de Cuenca.\n","familia":"Oleaceae\n\n                      Nombre científico: Fraxinus excelsior L.\n               Otros nombres comunes: “fresno norteño”, “fresno común”,\n                                      “fresno grande”.","nombre":"Oleaceae\n                                     Urapán","descripcíon":"Especie originaria de Europa. Árbol de excelente madera, sin embargo en el\nEcuador no existe plantaciones con fines comerciales sino más bien utilizados en orna-\nmentación. A pesar de la producción abundante de semillas no se registrado regeneración\nnatural. Localmente es común encontrarlo formando parte de la vegetación de ribera de\nlos ríos de Cuenca.","otros_nombres_comunes":["fresno norteño","fresno común","fresno grande."],"nombre_cientifica":"Fraxinus excelsior L.","habito":"","hojas":"","flores":"","fruta":"","distribucion_y_ecologia":"","usos_tradicionales":"","propagacion":"","images":["/resources/img/arboles-175_0.jpg","/resources/img/arboles-175_1.jpg","/resources/img/arboles-175_2.jpg"],"slug":"oleaceae-urapn"},{"page":176,"original":"176   ÁRBOLES Y ARBUSTOS INTRODUCIDOS\n\n\n\n\n                                        Familia: Oleaceae\n                                              Mirto\n\n                             Nombre científico: Ligustrum japonicum Thunb.\n                      Otros nombres comunes: “ligustro”\n\n      Descripción: Arbusto originario de Japón. La denominación científica del género tiene\n      como derivado del verbo latino Ligare, que significa atar y el nombre específico hace alu-\n      sión a su lugar de origen. Introducida al Ecuador con fines netamente ornamentales. En\n      nuestra región es un elemento importante dentro del paisaje urbano, generalmente for-\n      mando setos. Sus flores blancas y ligeramente fragantes son visitadas por las abejas.\n","familia":"Oleaceae\n","nombre":"Mirto","descripcíon":"Arbusto originario de Japón. La denominación científica del género tiene\n      como derivado del verbo latino Ligare, que significa atar y el nombre específico hace alu-\n      sión a su lugar de origen. Introducida al Ecuador con fines netamente ornamentales. En\n      nuestra región es un elemento importante dentro del paisaje urbano, generalmente for-\n      mando setos. Sus flores blancas y ligeramente fragantes son visitadas por las abejas.","otros_nombres_comunes":["ligustro"],"nombre_cientifica":"Ligustrum japonicum Thunb.","habito":"","hojas":"","flores":"","fruta":"","distribucion_y_ecologia":"","usos_tradicionales":"","propagacion":"","images":["/resources/img/arboles-176_0.jpg","/resources/img/arboles-176_1.jpg","/resources/img/arboles-176_2.jpg"],"slug":"mirto"},{"page":177,"original":"                                                                        UNIVERSIDAD DEL AZUAY    177\n\n\n\n\n                              Familia: Onagraceae\n                                     Pena pena\n\n                        Nombre científico: Fuchsia boliviana Carrière\n                Otros nombres comunes: “fuchsia”, “zarcillo”, “bailarinas”\n\nDescripción: Especie originaria del sur del Perú, Bolivia y norte de Argentina. Arbusto intro-\nducido al Ecuador únicamente con el fin ornamental, sin embargo este arbusto se puede\nencontrar compitiendo con la flora nativa; esto se debe a que las semillas son dispersadas\npor aves. También sus vistosas flores son visitadas por colibríes.\n","familia":"Onagraceae\n","nombre":"Pena pena","descripcíon":"Especie originaria del sur del Perú, Bolivia y norte de Argentina. Arbusto intro-\nducido al Ecuador únicamente con el fin ornamental, sin embargo este arbusto se puede\nencontrar compitiendo con la flora nativa; esto se debe a que las semillas son dispersadas\npor aves. También sus vistosas flores son visitadas por colibríes.","otros_nombres_comunes":["fuchsia","zarcillo","bailarinas"],"nombre_cientifica":"Fuchsia boliviana Carrière","habito":"","hojas":"","flores":"","fruta":"","distribucion_y_ecologia":"","usos_tradicionales":"","propagacion":"","images":["/resources/img/arboles-177_0.jpg","/resources/img/arboles-177_1.jpg","/resources/img/arboles-177_2.jpg"],"slug":"pena-pena"},{"page":178,"original":"178   ÁRBOLES Y ARBUSTOS INTRODUCIDOS\n\n\n\n\n                                        Familia: Pinaceae\n                                               Pino\n\n                          Nombre científico: Pinus radiata D. Don\n                  Otros nombres comunes: “pino de Monterrey”, “pino de California”\n\n      Descripción: Especie originaria del suroeste de los Estados Unidos, principalmente Califor-\n      nia. Fue introducida en el Ecuador en 1905 y la primera plantación a gran escala se realizó\n      en el páramo del volcán Cotopaxi, y su uso se extendió a partir de 1960. Es la segunda es-\n      pecie forestal más plantada en la sierra después del eucalipto. Es común encontrar árboles\n      aislados en la ribera del río Yanuncay.\n","familia":"Pinaceae\n","nombre":"Pino","descripcíon":"Especie originaria del suroeste de los Estados Unidos, principalmente Califor-\n      nia. Fue introducida en el Ecuador en 1905 y la primera plantación a gran escala se realizó\n      en el páramo del volcán Cotopaxi, y su uso se extendió a partir de 1960. Es la segunda es-\n      pecie forestal más plantada en la sierra después del eucalipto. Es común encontrar árboles\n      aislados en la ribera del río Yanuncay.","otros_nombres_comunes":["pino de Monterrey","pino de California"],"nombre_cientifica":"Pinus radiata D. Don","habito":"","hojas":"","flores":"","fruta":"","distribucion_y_ecologia":"","usos_tradicionales":"","propagacion":"","images":["/resources/img/arboles-178_0.jpg","/resources/img/arboles-178_1.jpg","/resources/img/arboles-178_2.jpg"],"slug":"pino"},{"page":179,"original":"                                                                     UNIVERSIDAD DEL AZUAY    179\n\n\n\n\n                           Familia: Pittosporaceae\n                                      Huesito\n\n                       Nombre científico: Pittosporum undulatum Vent.\n                Otros nombres comunes: “pittosporum dulce”\n\nDescripción: Especie originaria de la costa este de Australia, por su crecimiento rápido se\nha convertido en invasora en el mismo lugar de origen así como en otras regiones donde\nha sido introducida. En nuestra región el crecimiento es lento y no se ha registrado rege-\nneración natural. Las flores emiten un agradable olor que puede ser percibido con mayor\nintensidad en las noches.\n","familia":"Pittosporaceae\n","nombre":"Huesito","descripcíon":"Especie originaria de la costa este de Australia, por su crecimiento rápido se\nha convertido en invasora en el mismo lugar de origen así como en otras regiones donde\nha sido introducida. En nuestra región el crecimiento es lento y no se ha registrado rege-\nneración natural. Las flores emiten un agradable olor que puede ser percibido con mayor\nintensidad en las noches.","otros_nombres_comunes":["pittosporum dulce"],"nombre_cientifica":"Pittosporum undulatum Vent.","habito":"","hojas":"","flores":"","fruta":"","distribucion_y_ecologia":"","usos_tradicionales":"","propagacion":"","images":["/resources/img/arboles-179_0.jpg","/resources/img/arboles-179_1.jpg","/resources/img/arboles-179_2.jpg"],"slug":"huesito"},{"page":180,"original":"180   ÁRBOLES Y ARBUSTOS INTRODUCIDOS\n\n\n\n\n                                   Familia: Platanaceae\n                                            Plátano\n                    Nombre científico: Platanus occidentalis L.\n            Otros nombres comunes: “plátano americano”, “sicómoro americano”\n\n      Descripción: Especie originaria de Norteamérica. Se encuentra entre los árboles más gran-\n      des y longevos del este de los Estados Unidos. Por sus hojas verdes brillantes y expansivas\n      es usado en ornamentación. Es una especie rara de las riberas de los ríos en Cuenca; se lo\n      encuentra en el sector El Barranco.\n","familia":"Platanaceae\n\n                    Nombre científico: Platanus occidentalis L.\n            Otros nombres comunes: “plátano americano”, “sicómoro americano”","nombre":"Platanaceae\n                                            Plátano","descripcíon":"Especie originaria de Norteamérica. Se encuentra entre los árboles más gran-\n      des y longevos del este de los Estados Unidos. Por sus hojas verdes brillantes y expansivas\n      es usado en ornamentación. Es una especie rara de las riberas de los ríos en Cuenca; se lo\n      encuentra en el sector El Barranco.","otros_nombres_comunes":["plátano americano","sicómoro americano"],"nombre_cientifica":"Platanus occidentalis L.","habito":"","hojas":"","flores":"","fruta":"","distribucion_y_ecologia":"","usos_tradicionales":"","propagacion":"","images":["/resources/img/arboles-180_0.jpg","/resources/img/arboles-180_1.jpg","/resources/img/arboles-180_2.jpg"],"slug":"platanaceae-pltano"},{"page":181,"original":"                                                                     UNIVERSIDAD DEL AZUAY    181\n\n\n\n\n                              Familia: Proteaceae\n                              Roble australiano\n                       Nombre científico: Grevillea robusta A. Cunn. ex R. Br.\n                Otros nombres comunes: “roble sedoso”, “roble plateado”,\n                                       “árbol de fuego”, “pino de oro”\n\nDescripción: Árbol originario del este de Australia. En el Ecuador se ha registrado en Im-\nbabura, Pichincha y Azuay. Es el árbol más grande de este género. Presenta un rápido cre-\ncimiento que puede llegar a los 25 m de altura. Es una especie intolerante a la sombra, ya\nque al estar bajo un follaje denso o sin luz, se produce una sustancia tóxica que inhibe el\ncrecimiento de las plántulas y produce su muerte.\n","familia":"Proteaceae\n\n                       Nombre científico: Grevillea robusta A. Cunn. ex R. Br.\n                Otros nombres comunes: “roble sedoso”, “roble plateado”,\n                                       “árbol de fuego”, “pino de oro”","nombre":"Proteaceae\n                              Roble australiano","descripcíon":"Árbol originario del este de Australia. En el Ecuador se ha registrado en Im-\nbabura, Pichincha y Azuay. Es el árbol más grande de este género. Presenta un rápido cre-\ncimiento que puede llegar a los 25 m de altura. Es una especie intolerante a la sombra, ya\nque al estar bajo un follaje denso o sin luz, se produce una sustancia tóxica que inhibe el\ncrecimiento de las plántulas y produce su muerte.","otros_nombres_comunes":["roble sedoso","roble plateado","árbol de fuego","pino de oro"],"nombre_cientifica":"Grevillea robusta A. Cunn. ex R. Br.","habito":"","hojas":"","flores":"","fruta":"","distribucion_y_ecologia":"","usos_tradicionales":"","propagacion":"","images":["/resources/img/arboles-181_0.jpg","/resources/img/arboles-181_1.jpg","/resources/img/arboles-181_2.jpg"],"slug":"proteaceae-roble-australiano"},{"page":182,"original":"182   ÁRBOLES Y ARBUSTOS INTRODUCIDOS\n\n\n\n\n                                        Familia: Rosaceae\n                                          Manzanitas\n                             Nombre científico: Cotoneaster acuminatus Lindl.\n                      Otros nombres comunes: “manzanita de espinos”\n\n      Descripción: Especie originaria de Asia, específicamente en la cordillera del Himalaya. Ar-\n      busto fácilmente adaptable, no necesita de lugares muy húmedos o drenados; muy re-\n      sistente al frío, produce unas bayas muy llamativas y decorativas que persisten por largo\n      tiempo. Las semillas son dispersadas por las aves y es frecuente encontrarla compitiendo\n      con la flora nativa. Forma parte del paisaje ornamental de la ciudad de Cuenca.\n","familia":"Rosaceae\n\n                             Nombre científico: Cotoneaster acuminatus Lindl.\n                      Otros nombres comunes: “manzanita de espinos”","nombre":"Rosaceae\n                                          Manzanitas","descripcíon":"Especie originaria de Asia, específicamente en la cordillera del Himalaya. Ar-\n      busto fácilmente adaptable, no necesita de lugares muy húmedos o drenados; muy re-\n      sistente al frío, produce unas bayas muy llamativas y decorativas que persisten por largo\n      tiempo. Las semillas son dispersadas por las aves y es frecuente encontrarla compitiendo\n      con la flora nativa. Forma parte del paisaje ornamental de la ciudad de Cuenca.","otros_nombres_comunes":["manzanita de espinos"],"nombre_cientifica":"Cotoneaster acuminatus Lindl.","habito":"","hojas":"","flores":"","fruta":"","distribucion_y_ecologia":"","usos_tradicionales":"","propagacion":"","images":["/resources/img/arboles-182_0.jpg","/resources/img/arboles-182_1.jpg","/resources/img/arboles-182_2.jpg"],"slug":"rosaceae-manzanitas"},{"page":183,"original":"                                                                     UNIVERSIDAD DEL AZUAY   183\n\n\n\n\n                               Familia: Rosaceae\n                                      Quinua\n                 Nombre científico: Polylepis racemosa Ruiz & Pav.\n          Otros nombres comunes: “coloradito” (Venezuela), “yagual” (Colombia\n                                 y Ecuador), “queñual” (Perú)\nDescripción: Árbol originario de Perú y Bolivia, introducido al Ecuador como un candidato\npara la reforestación y silvicultura; sin embargo esta especie puede reducir la diversidad\nestructural, incrementar la producción de biomasa y alterar la dinámica vegetal y edafoló-\ngica de bosques naturales de Polylepis del Ecuador. Por esta razón su uso debe ser contro-\nlado y no permitir su utilización.\n","familia":"Rosaceae\n\n                 Nombre científico: Polylepis racemosa Ruiz & Pav.\n          Otros nombres comunes: “coloradito” (Venezuela), “yagual” (Colombia\n                                 y Ecuador), “queñual” (Perú)\nDescripción: Árbol originario de Perú y Bolivia, introducido al Ecuador como un candidato\npara la reforestación y silvicultura; sin embargo esta especie puede reducir la diversidad\nestructural, incrementar la producción de biomasa y alterar la dinámica vegetal y edafoló-\ngica de bosques naturales de Polylepis del Ecuador. Por esta razón su uso debe ser contro-\nlado y no permitir su utilización.","nombre":"Rosaceae\n                                      Quinua","descripcíon":"Árbol originario de Perú y Bolivia, introducido al Ecuador como un candidato\npara la reforestación y silvicultura; sin embargo esta especie puede reducir la diversidad\nestructural, incrementar la producción de biomasa y alterar la dinámica vegetal y edafoló-\ngica de bosques naturales de Polylepis del Ecuador. Por esta razón su uso debe ser contro-\nlado y no permitir su utilización.","otros_nombres_comunes":["coloradito (Venezuela)","yagual (Colombia\n                                 y Ecuador)","queñual (Perú)"],"nombre_cientifica":"Polylepis racemosa Ruiz & Pav.","habito":"","hojas":"","flores":"","fruta":"","distribucion_y_ecologia":"","usos_tradicionales":"","propagacion":"","images":["/resources/img/arboles-183_0.jpg","/resources/img/arboles-183_1.jpg","/resources/img/arboles-183_2.jpg"],"slug":"rosaceae-quinua"},{"page":184,"original":"184   ÁRBOLES Y ARBUSTOS INTRODUCIDOS\n\n\n\n\n                                        Familia: Rosaceae\n                                          Manzanitas\n                 Nombre científico: Pyracantha angustifolia (Franch.) C.K. Schneid.\n         Otros nombres comunes: “espino de fuego naranja”\n\n      Descripción: Especie originaria del suroeste de China. Los tallos y las ramas tienen espinos\n      afilados que la diferencia del género Cotoneaster. Produce abundante frutos, los mismos\n      que son consumidos por una variedad de aves. Arbusto raro en las riberas de los ríos de\n      Cuenca.\n","familia":"Rosaceae\n\n                 Nombre científico: Pyracantha angustifolia (Franch.) C.K. Schneid.\n         Otros nombres comunes: “espino de fuego naranja”","nombre":"Rosaceae\n                                          Manzanitas","descripcíon":"Especie originaria del suroeste de China. Los tallos y las ramas tienen espinos\n      afilados que la diferencia del género Cotoneaster. Produce abundante frutos, los mismos\n      que son consumidos por una variedad de aves. Arbusto raro en las riberas de los ríos de\n      Cuenca.","otros_nombres_comunes":["espino de fuego naranja"],"nombre_cientifica":"Pyracantha angustifolia (Franch.) C.K. Schneid.","habito":"","hojas":"","flores":"","fruta":"","distribucion_y_ecologia":"","usos_tradicionales":"","propagacion":"","images":["/resources/img/arboles-184_0.jpg","/resources/img/arboles-184_1.jpg","/resources/img/arboles-184_2.jpg"],"slug":"rosaceae-manzanitas"},{"page":185,"original":"                                                                        UNIVERSIDAD DEL AZUAY     185\n\n\n\n\n                                 Familia: Rosaceae\n                                Mora extranjera\n                        Nombre científico: Rubus niveus Thunb.\n                Otros nombres comunes: “mora”\n\nDescripción: Arbusto originario del sureste de Asia. En el Ecuador se encuentra en las cua-\ntro regiones y en Galápagos se ha convertido en la especie más invasora, llegando a ame-\nnazar la estabilidad ecológica de especies nativas. Sus frutos son comestibles, las flores son\nvisitadas por abejas y otros insectos y las semillas son dispersadas por las aves. En la región\ncrece formando agregados monoespecíficos que desplazan a la flora nativa.\n","familia":"Rosaceae\n\n                        Nombre científico: Rubus niveus Thunb.\n                Otros nombres comunes: “mora”","nombre":"Rosaceae\n                                Mora extranjera","descripcíon":"Arbusto originario del sureste de Asia. En el Ecuador se encuentra en las cua-\ntro regiones y en Galápagos se ha convertido en la especie más invasora, llegando a ame-\nnazar la estabilidad ecológica de especies nativas. Sus frutos son comestibles, las flores son\nvisitadas por abejas y otros insectos y las semillas son dispersadas por las aves. En la región\ncrece formando agregados monoespecíficos que desplazan a la flora nativa.","otros_nombres_comunes":["mora"],"nombre_cientifica":"Rubus niveus Thunb.","habito":"","hojas":"","flores":"","fruta":"","distribucion_y_ecologia":"","usos_tradicionales":"","propagacion":"","images":["/resources/img/arboles-185_0.jpg","/resources/img/arboles-185_1.jpg","/resources/img/arboles-185_2.jpg"],"slug":"rosaceae-mora-extranjera"},{"page":186,"original":"186   ÁRBOLES Y ARBUSTOS INTRODUCIDOS\n\n\n\n\n                                    Familia: Salicaceae\n                                        Álamo blanco\n                             Nombre científico: Populus alba L.\n                     Otros nombres comunes: “álamo común”, “chopo blanco”\n\n      Descripción: Árbol originario de Europa, Asia y norte de África. Introducido al Ecuador\n      como planta ornamental que puede soportar la contaminación urbana, sin embargo por\n      la cantidad de renuevos que emite puede competir con otras especies próximas, convir-\n      tiéndose en una especie invasora. Es común encontrarlo formando parte de la vegetación\n      ornamental de los parques y jardines de la ciudad de Cuenca y los cantones aledaños. Se\n      debe tener cuidado para no introducir a zonas de cultivo ni a bosques naturales.\n","familia":"Salicaceae\n\n                             Nombre científico: Populus alba L.\n                     Otros nombres comunes: “álamo común”, “chopo blanco”","nombre":"Salicaceae\n                                        Álamo blanco","descripcíon":"Árbol originario de Europa, Asia y norte de África. Introducido al Ecuador\n      como planta ornamental que puede soportar la contaminación urbana, sin embargo por\n      la cantidad de renuevos que emite puede competir con otras especies próximas, convir-\n      tiéndose en una especie invasora. Es común encontrarlo formando parte de la vegetación\n      ornamental de los parques y jardines de la ciudad de Cuenca y los cantones aledaños. Se\n      debe tener cuidado para no introducir a zonas de cultivo ni a bosques naturales.","otros_nombres_comunes":["álamo común","chopo blanco"],"nombre_cientifica":"Populus alba L.","habito":"","hojas":"","flores":"","fruta":"","distribucion_y_ecologia":"","usos_tradicionales":"","propagacion":"","images":["/resources/img/arboles-186_0.jpg","/resources/img/arboles-186_1.jpg","/resources/img/arboles-186_2.jpg"],"slug":"salicaceae-lamo-blanco"},{"page":187,"original":"                                                                     UNIVERSIDAD DEL AZUAY    187\n\n\n\n\n                               Familia: Salicaceae\n                                       Álamo\n                       Nombre científico: Populus balsamifera L.\n                Otros nombres comunes: “chopo negro”\n\nDescripción: Árbol caducifolio, originario de Norteamérica. En su hábitat natural es un ár-\nbol grande de hasta 40 m de altura y 20 cm de DAP. El nombre balsamífera, se debe a resina\nroja y fragante que produce. En la ciudad de Cuenca habría árboles grandes de no ser por\nla poda permanente, sin embargo al frente de la Universidad del Azuay existen de tamaño\nconsiderable.\n","familia":"Salicaceae\n\n                       Nombre científico: Populus balsamifera L.\n                Otros nombres comunes: “chopo negro”","nombre":"Salicaceae\n                                       Álamo","descripcíon":"Árbol caducifolio, originario de Norteamérica. En su hábitat natural es un ár-\nbol grande de hasta 40 m de altura y 20 cm de DAP. El nombre balsamífera, se debe a resina\nroja y fragante que produce. En la ciudad de Cuenca habría árboles grandes de no ser por\nla poda permanente, sin embargo al frente de la Universidad del Azuay existen de tamaño\nconsiderable.","otros_nombres_comunes":["chopo negro"],"nombre_cientifica":"Populus balsamifera L.","habito":"","hojas":"","flores":"","fruta":"","distribucion_y_ecologia":"","usos_tradicionales":"","propagacion":"","images":["/resources/img/arboles-187_0.jpg","/resources/img/arboles-187_1.jpg","/resources/img/arboles-187_2.jpg"],"slug":"salicaceae-lamo"},{"page":188,"original":"188   ÁRBOLES Y ARBUSTOS INTRODUCIDOS\n\n\n\n\n                                     Familia: Salicaceae\n                                         Sauce llorón\n                              Nombre científico: Salix babylonica L.\n                      Otros nombres comunes: “sauce péndulo”\n\n      Descripción: Árbol originario de Asia en especial del norte de China. Se adapta muy bien\n      cerca de cursos de agua y todo tipo de suelos, aunque es resistente al frío; pero las fuertes\n      heladas pueden destruir sus hojas. Hace algunos años formaba parte de la vegetación de\n      ribera del río Tarqui, sin embargo en la actualidad ha desaparecido por completo; por otro\n      lado existen algunos plantones en las riberas de los ríos Tomebamba y Yanuncay.\n","familia":"Salicaceae\n\n                              Nombre científico: Salix babylonica L.\n                      Otros nombres comunes: “sauce péndulo”","nombre":"Salicaceae\n                                         Sauce llorón","descripcíon":"Árbol originario de Asia en especial del norte de China. Se adapta muy bien\n      cerca de cursos de agua y todo tipo de suelos, aunque es resistente al frío; pero las fuertes\n      heladas pueden destruir sus hojas. Hace algunos años formaba parte de la vegetación de\n      ribera del río Tarqui, sin embargo en la actualidad ha desaparecido por completo; por otro\n      lado existen algunos plantones en las riberas de los ríos Tomebamba y Yanuncay.","otros_nombres_comunes":["sauce péndulo"],"nombre_cientifica":"Salix babylonica L.","habito":"","hojas":"","flores":"","fruta":"","distribucion_y_ecologia":"","usos_tradicionales":"","propagacion":"","images":["/resources/img/arboles-188_0.jpg","/resources/img/arboles-188_1.jpg","/resources/img/arboles-188_2.jpg"],"slug":"salicaceae-sauce-llorn"},{"page":189,"original":"                                                                     UNIVERSIDAD DEL AZUAY    189\n\n\n\n\n                         Familia: Scrophulariaceae\n                                     Quishuar\n              Nombre científico: Buddleja americana L.\n      Otros nombres comunes: “tepazan” (Colombia), “tabaquillo” (Costa Rica)\n\nDescripción: Arbusto originario del continente americano. Se distribuye desde México has-\nta Bolivia y en muchos de estos países es utilizada como medicinal. En nuestro país se dis-\ntribuye en la mayoría de las provincias, incluyendo a Galápagos, pero no se ha registrado\nen medios naturales, por lo que suponemos que es una especie introducida. Localmente\ncrece en lugares abiertos y suelos movedizos. Sus flores son muy visitadas por las abejas.\n","familia":"Scrophulariaceae\n\n              Nombre científico: Buddleja americana L.\n      Otros nombres comunes: “tepazan” (Colombia), “tabaquillo” (Costa Rica)","nombre":"Scrophulariaceae\n                                     Quishuar","descripcíon":"Arbusto originario del continente americano. Se distribuye desde México has-\nta Bolivia y en muchos de estos países es utilizada como medicinal. En nuestro país se dis-\ntribuye en la mayoría de las provincias, incluyendo a Galápagos, pero no se ha registrado\nen medios naturales, por lo que suponemos que es una especie introducida. Localmente\ncrece en lugares abiertos y suelos movedizos. Sus flores son muy visitadas por las abejas.","otros_nombres_comunes":["tepazan (Colombia)","tabaquillo (Costa Rica)"],"nombre_cientifica":"Buddleja americana L.","habito":"","hojas":"","flores":"","fruta":"","distribucion_y_ecologia":"","usos_tradicionales":"","propagacion":"","images":["/resources/img/arboles-189_0.jpg","/resources/img/arboles-189_1.jpg","/resources/img/arboles-189_2.jpg"],"slug":"scrophulariaceae-quishuar"},{"page":190,"original":"190   ÁRBOLES Y ARBUSTOS INTRODUCIDOS\n\n\n\n\n                                   Familia: Solanaceae\n                                         Palo bobo\n\n                       Nombre científico: Nicotiana glauca Graham\n                Otros nombres comunes: “falso tabaco”, “palán palán” (lugar de origen)\n\n      Descripción: Arbusto originario del noroeste de Argentina y sur de Bolivia. Se ha natu-\n      ralizado en toda América convirtiéndose en una planta invasora sobre todo en terrenos\n      baldíos y muros de las casas. En nuestra región se encuentra en los márgenes de los ríos,\n      en los terrenos de relleno por la explotación de áridos. Es muy común desde el sector de\n      Ucubamba hasta el descanso.\n","familia":"Solanaceae\n","nombre":"Palo bobo","descripcíon":"Arbusto originario del noroeste de Argentina y sur de Bolivia. Se ha natu-\n      ralizado en toda América convirtiéndose en una planta invasora sobre todo en terrenos\n      baldíos y muros de las casas. En nuestra región se encuentra en los márgenes de los ríos,\n      en los terrenos de relleno por la explotación de áridos. Es muy común desde el sector de\n      Ucubamba hasta el descanso.","otros_nombres_comunes":["falso tabaco","palán palán (lugar de origen)"],"nombre_cientifica":"Nicotiana glauca Graham","habito":"","hojas":"","flores":"","fruta":"","distribucion_y_ecologia":"","usos_tradicionales":"","propagacion":"","images":["/resources/img/arboles-190_0.jpg","/resources/img/arboles-190_1.jpg","/resources/img/arboles-190_2.jpg","/resources/img/arboles-191_0.jpg"],"slug":"palo-bobo"},{"page":192,"original":"192   ÁRBOLES Y ARBUSTOS INTRODUCIDOS\n\n\n\n\n                                   Familia: Verbenaceae\n                                           Ingarrosa\n\n                             Nombre científico: Lantana camara L.\n                      Otros nombres comunes: “supirrosa”\n\n      Descripción: Arbusto nativo de las regiones del sur de los Estados Unidos y Centroaméri-\n      ca, está incluida en la lista 100 de las especies exóticas invasoras más dañinas del mundo\n      (Lowe et al, 2004). En el Ecuador es muy utilizada como cerca viva y ornamental. En algunos\n      lugares se ha convertido en maleza que invade ecosistemas agrícolas y naturales. En las\n      riberas de los ríos de Cuenca forman parte del paisaje ornamental.\n","familia":"Verbenaceae\n","nombre":"Ingarrosa","descripcíon":"Arbusto nativo de las regiones del sur de los Estados Unidos y Centroaméri-\n      ca, está incluida en la lista 100 de las especies exóticas invasoras más dañinas del mundo\n      (Lowe et al, 2004). En el Ecuador es muy utilizada como cerca viva y ornamental. En algunos\n      lugares se ha convertido en maleza que invade ecosistemas agrícolas y naturales. En las\n      riberas de los ríos de Cuenca forman parte del paisaje ornamental.","otros_nombres_comunes":["supirrosa"],"nombre_cientifica":"Lantana camara L.","habito":"","hojas":"","flores":"","fruta":"","distribucion_y_ecologia":"","usos_tradicionales":"","propagacion":"","images":["/resources/img/arboles-192_0.jpg","/resources/img/arboles-192_1.jpg","/resources/img/arboles-192_2.jpg","/resources/img/arboles-193_0.jpg"],"slug":"ingarrosa"},{"page":195,"original":"                                                                                 UNIVERSIDAD DEL AZUAY      195\n\n\n\n                                                                                    GLOSARIO\n\nAdnado: adherente, órgano unido a otro                Corolino: relativo a la corola de las flores\n\nAmento: inflorescencia racimosa generalmente          DAP: diámetro a la altura del pecho\ncolgante, con flores inconspicuas, en su mayoría\nunisexuales                                           Dehiscente: que se abre cuando está maduro\n\nAntesis: apertura de la flor para la polinización     Dialisépalo: cáliz con los sépalos libres o sepa-\n                                                      rados\nAntiespasmódico: que alivia las contracciones\nmusculares                                            Didínamos: androceo con dos estambres largos\n                                                      y dos cortos.\nÁrbol: planta leñosa, generalmente con un tallo\ncon ramas a cierta altura                             Dormancia: período en el ciclo biológico de un\n                                                      organismo en el que el crecimiento, desarrollo\nArbusto: planta leñosa, generalmente ramifica-        y actividad física se suspenden temporalmente.\nda desde su base\n                                                      Epipétalos: órgano soldado a un pétalo.\nArilo: tejido que forma una cobertura carnosa en\nalgunas semillas                                      Estípula: estructuras laminares, a veces presen-\n                                                      tes a los dos lados del pecíolo\nBisexual: con los dos sexos.\n                                                      Estratificación: tratamiento pregerminativo que\nBráctea: hoja reducida de las inflorescencias,        consiste en situar las semillas en capas con estra-\ndiferente de las hojas normales como las que          tos de arena por un período determinado.\nsuele haber junto al punto de cada inserción del\npendúnculo de cada flor. Cada bráctea lleva en la     Fascículos: cada una de las “hojuelas” (láminas\naxila una flor, una inflorescencia o una rama de la   foliares individuales) de una hoja compuesta.\ninflorescencia.\n                                                      Filaria: bráctea subyacente a la cabezuela en la\nCactácea: familia de plantas suculentas y, en         familia de las Compuestas\ngran mayoría, espinosas, conocidas en conjunto\ncomo cactus                                           Fimbriado: se aplica a los bordes recortados me-\n                                                      nudamente a modo de flecos o lacinias\nCaducifolia: árbol o arbusto que pierde las hojas\nen la estación desfavorable.                          Flósculos: en las gramíneas es la estructura floral\n                                                      entera, compuesta por lema, palea, lodículas, es-\nCarpelo: cada una de las hojas modificadas y fér-     tabres y ovario. En las compuestas, son las flores\ntiles, que forman el gineceo.                         tubulosas del capítulo.\n\nCauliflora: plantas cuyas flores nacen sobre el       Foliolos: cada segmento de una hoja compuesta.\ntronco de las ramas principales\n                                                      Glauco: color verde claro, con matiz ligeramente\nCipselas: fruto seco, indehiscente, uniseminado,      azulado.\nderivado de un ovario ínfero, con la semilla no\nadherida al tegumento.                                Hipanto: tálamo acopado, en cuyo extremo es-\n                                                      tán perianto y androceo\nConnadas: aquellos órganos que se desarrollan\nconjuntamente y permanecen más o menos sol-           Homógamo: inflorescencia que posee flores o\ndados entre sí.                                       espiguillas de igual sexo.\n\nCoriácea: que tiene consistencia del cuero.           Inconspicuo: poco visible; se aplica a un órgano\n                                                      poco desarrollado\n","familia":"","nombre":"","descripcíon":"","otros_nombres_comunes":[],"nombre_cientifica":"","habito":"","hojas":"","flores":"","fruta":"","distribucion_y_ecologia":"","usos_tradicionales":"","propagacion":""},{"page":197,"original":"                                                                               UNIVERSIDAD DEL AZUAY       197\n\n\n\n                                                                           BIBLIOGRAFÍA\n\nAcosta, M. 1992. Vademecum de plantas medicinales del Ecuador. Fundación Ecuatoriana de Estu-\ndios Sociales. Ediciones Abya-Yala. 243p.\n\nBonifaz, C., and X, Cornejo. 2002. Flora of Ecuador, Proteaceae No 69. Edited by Harling and Anders-\nson. Berlings Skogs, Trelleborg, Sweden. 123 p.\n\nBarrera Marín N. 1996 Chachafruto o balú (Erythrina edulis, T.): cultivo y aprovechamiento. Universi-\ndad Distrital Francisco José de Caldas, 242 p.\n\nCaranqui A., J. 2011. Avances taxonómicos y de propagación del género Fuchsia en Ecuador Rev.\nQ’EUÑA 4: 39 – 45. Sociedad Botánica del Cuzco-Perú.\n\nCentral Ecuatoriana de Servicios Agrícolas (CESA). 1989. Especies forestales nativas de los Andes\nEcuatorianos, resultados preliminares de algunas experiencias. Quito. 50 p.\n\nCentral Ecuatoriana de Servicios Agrícolas (CESA). 1993. Usos medicinales de las especies forestales\nnativas en el Ecuador, Manual de difusión popular. Quito. 57 p.\n\nCordero, L. 1984. Estudios Botánicos. Cuenca. Reedición del Departamento de Difusión Cultural de\nla Universidad de Cuenca. 240p.\n\nCuamacás, B., and G, Tipaz. 1995. Árboles de los Bosques Interandinos del Norte del Ecuador. Museo\nEcuatoriano de Ciencias Naturales. Quito, Ecuador.\n\nDe la Torre, L., Navarrete, H., Muriel P., Macía., M and H, Balslev. 2008. Enciclopedia de las Plantas\nÚtiles del Ecuador. Herbario QCA de la Escuela de Ciencias Biológicas de la Pontificia Universidad\nCatólica del Ecuador and Herbario AAU del Departamento de Ciencias Biológicas de la Universidad\nde Aarhus. Quito and Aarhus. 949 p.\n\nElleman, L. 1990. El uso de la madera del Bosque Montano por los Saraguros. In: Las plantas y el\nhombre, Borgoft Pedersen, H. y Ríos M. (eds) Quito: ediciones Abya-yala.\n\nEriksen, B., Stahl ., and C, Persson. 2000. Flora of Ecuador, Polygalaceae, No 65. Edited by Harling and\nAndersson. Berlings Skogs AB, Trelleborg, Sweden. 134p.\n\nGarcía, J.E. y F. B. Tello. 1998. Identificación y descripción morfológica floral de árboles y arbustos\ncon características apícolas de la microcuenca del río Uchima. Tesis no publicada. Universidad Na-\ncional de Loja. Ecuador.\n\nJorgensen, P. M., and S, León-Yánez. 1999. Catalogue of the Vascular Plants of Ecuador. Missouri\nBotanical Garden. St. Louis, Missouri, USA. 1181 p.\n\nHarling, G. 1999. Flora of Ecuador, Cunoniaceae No 61. Departament of Systematic Botany, Göte-\nborg University, Sweden. 74 p.\n\nJaramillo, T. 2013. Plantas Nativas de la Hoya de Quito. Fundación Botánica de los Andes, Jardín\nBotánico de Quito. Quito, Ecuador.\n\nKing, J. 1987. Birds: Ornithological studies at the Río Mazán montane rainforest reserve, In: McLean\nand Hancock. Cuenca: Río Mazán Project Report 1988 Unpublished report 22p.\n","familia":"","nombre":"","descripcíon":"","otros_nombres_comunes":[],"nombre_cientifica":"","habito":"","hojas":"","flores":"","fruta":"","distribucion_y_ecologia":"","usos_tradicionales":"","propagacion":""}]